Workbook
Name BBSpread: WACC!$C$19
Name Beta: WACC!$C$16
Name Beta_2yDaily: WACC!$C$9
Name Beta_Blume: WACC!$C$8
Name Beta_BU_Relev: WACC!$C$15
Name Beta_BU_Unlev: WACC!$C$10
Name Beta_Raw: WACC!$C$7
Name BookEquityJun: Valuation!$C$17
Name Br_Cash: Valuation!$C$34
Name Br_Debt: Valuation!$C$33
Name Br_UTP: Valuation!$C$35
Name BuybackPxMode: Inputs!$E$12
Name CashJun: Valuation!$C$14
Name CashRate: Inputs!$E$15
Name CircSwitch: Inputs!$E$8
Name CommitFee: Inputs!$E$18
Name Comps_EV_High: Comps!$F$30
Name Comps_EV_Low: Comps!$D$30
Name Comps_EV_Value: Comps!$E$30
Name Comps_PE_High: Comps!$F$31
Name Comps_PE_Low: Comps!$D$31
Name Comps_PE_Value: Comps!$E$31
Name Coupon_Notes29: Inputs!$E$21
Name Coupon_Notes31: Inputs!$E$22
Name Coverage26: WACC!$C$22
Name DCF_Base: Valuation!$C$66
Name DCF_Bear: Valuation!$C$68
Name DCF_Bull: Valuation!$C$67
Name DCF_PW: Valuation!$C$69
Name DE_Market: WACC!$C$13
Name DebtFace: WACC!$C$11
Name Dilution: Inputs!$E$27
Name DTAYears: Valuation!$C$12
Name Eq_Jun: Valuation!$C$36
Name Eq_Sep: Valuation!$C$37
Name ERP: WACC!$C$6
Name EV_DCF: Valuation!$C$31
Name ExcessToBuybacks: Inputs!$E$11
Name ExitMultiple: Valuation!$C$9
Name FCFF_2035: Valuation!$C$20
Name FCFF_TV: Valuation!$C$21
Name FeeAmort: Inputs!$E$25
Name GMShift: Sensitivity!$C$6
Name GrowthShift: Sensitivity!$C$5
Name H2Share: Valuation!$C$11
Name HD_Carrying: HEYDUDE!$C$30
Name HD_Cash: HEYDUDE!$C$6
Name HD_CorpAlloc: HEYDUDE!$C$25
Name HD_CumNOPAT: HEYDUDE!$C$14
Name HD_Destroyed: HEYDUDE!$C$22
Name HD_Destroyed_PS: HEYDUDE!$C$23
Name HD_EBITDA21: HEYDUDE!$C$9
Name HD_EBITDA26: HEYDUDE!$C$19
Name HD_EntryMult: HEYDUDE!$C$10
Name HD_FV: HEYDUDE!$C$29
Name HD_Goodwill0: HEYDUDE!$C$11
Name HD_Headline: HEYDUDE!$C$5
Name HD_Headroom: HEYDUDE!$C$31
Name HD_Impair25: HEYDUDE!$C$12
Name HD_Mult_Today: HEYDUDE!$C$20

Sheet Cover
B2: Crocs, Inc. (NASDAQ: CROX)
B3: Valuation model: three statements, DCF, comps, LBO and merger analysis
B4: Prepared by Sidhant Thalor | Valuation date 30-Sep-2026 | US$ millions unless stated
B6: Summary
B7: Rating | C7: =Rating -> BUY
B8: 12-month price target | C8: =PriceTarget -> 190
B9: Upside to price target | C9: =PT_Upside -> 0.60283449
B10: DCF value per share (live scenario) | C10: =ValuePerShare -> 222.98832
B11: Probability-weighted DCF value | C11: =DCF_PW -> 206.89506
B12: Share price (30-Sep-2026) | C12: =SharePrice -> 118.54
B13: Basic shares outstanding (m) | C13: =SharesOut -> 47.945
B14: Market capitalisation | C14: =SharePrice*SharesOut -> 5683.4003
B15: Net debt FY25A (excl. leases) | C15: =Debt!$I$54 -> 1100.531
B16: Enterprise value | C16: =SharePrice*SharesOut+Debt!$I$54 -> 6783.9313
B17: EV / EBITDA FY26E | C17: =(SharePrice*SharesOut+Debt!$I$54)/IS!$J$33 -> 6.9935135
B18: P / E FY26E (adjusted) | C18: =SharePrice/IS!$J$39 -> 8.2064617
B19: FCF yield FY26E | C19: =CF!$J$37/(SharePrice*SharesOut) -> 0.1280283
B20: Scenario shown | C20: =CHOOSE(Scenario,"Base","Bull","Bear") -> Base
B21: Balance sheet check | C21: =IF(MasterCheck=0,"OK","Error") -> OK
B23: Contents
B24: Dashboard | D24: Key outputs, FY26E vs guidance, scenario comparison
B25: Valuation | D25: Terminal value, equity bridge, other methods, SOTP, price target
B26: Football_Field | D26: Value per share by method
B27: Inputs | D27: Scenario switch and forecast drivers
B28: Rev_Build | D28: Revenue by brand, region and channel
B29: IS / BS / CF | D29: Integrated financial statements
B30: NWC / Fixed_Assets / Tax | D30: Supporting schedules
B31: Debt / Equity | D31: Debt schedule, cash sweep, buybacks and share count
B32: WACC / DCF / Sensitivity | D32: Cost of capital, DCF and sensitivity tables
B33: Comps / Precedents | D33: Trading comparables and precedent transactions
B34: LBO / LBO_CF | D34: Leveraged buyout returns
B35: HEYDUDE | D35: Acquisition returns and impairment test
... B37: Hist | D37: Historical financials as reported
B39: Colour code
C40: 1,234.5 | D40: Hard-coded input or historical data
C41: 1,234.5 | D41: Formula
C42: 1,234.5 | D42: Link to another sheet
B44: Interest is on average balances (circular; iterative calculation is on). Set Inputs!CircSwitch to 0 to break the loop.

Sheet Dashboard
B1: Dashboard - operating model outputs
B2: Crocs, Inc. (NASDAQ: CROX) | US$ millions unless stated
B4: Fiscal year ending 31-Dec | C4: Unit | E4: FY2021A | F4: FY2022A | G4: FY2023A | H4: FY2024A | I4: FY2025A | J4: FY2026E | K4: FY2027E | L4: FY2028E | M4: FY2029E | N4: FY2030E | O4: FY2031E | P4: FY2032E | Q4: FY2033E | R4: FY2034E | S4: FY2035E
B6: Scenario override (used by the scenario table - leave at 0) | E6: 0
B7: Key outputs
B8: Revenue | E8: =IS!E7 -> 2313.416 | F8: =IS!F7 -> 3554.985 | G8: =IS!G7 -> 3962.347 | H8: =IS!H7 -> 4102.108 | I8: =IS!I7 -> 4040.647 | J8: =IS!J7 -> 4104.026 | K8: =IS!K7 -> 4247.9569 | L8: =IS!L7 -> 4423.3961 | ... S8: =IS!S7 -> 5624.6101
B9: growth | E9: =IS!E8 -> 0 | F9: =IS!F8 -> 0.53668212 | G9: =IS!G8 -> 0.11458895 | H9: =IS!H8 -> 0.035272277 | I9: =IS!I8 -> -0.014982784 | J9: =IS!J8 -> 0.015685357 | K9: =IS!K8 -> 0.035070669 | L9: =IS!L8 -> 0.041299662 | ... S9: =IS!S8 -> 0.028536689
B10: Crocs brand revenue | E10: =Rev_Build!E17 -> 2313.416 | F10: =Rev_Build!F17 -> 2659.125 | G10: =Rev_Build!G17 -> 3012.954 | H10: =Rev_Build!H17 -> 3277.967 | I10: =Rev_Build!I17 -> 3325.807 | J10: =Rev_Build!J17 -> 3409.3535 | K10: =Rev_Build!K17 -> 3554.0852 | L10: =Rev_Build!L17 -> 3722.1444 | ... S10: =Rev_Build!S17 -> 4792.4506
B11: HEYDUDE revenue | E11: =Rev_Build!E24 -> 0 | F11: =Rev_Build!F24 -> 895.86 | G11: =Rev_Build!G24 -> 949.393 | H11: =Rev_Build!H24 -> 824.141 | I11: =Rev_Build!I24 -> 714.84 | J11: =Rev_Build!J24 -> 694.67245 | K11: =Rev_Build!K24 -> 693.87172 | L11: =Rev_Build!L24 -> 701.25169 | ... S11: =Rev_Build!S24 -> 832.15955
B12: Gross margin | E12: =IS!E11 -> 0.61390602 | F12: =IS!F11 -> 0.52328828 | G12: =IS!G11 -> 0.55775277 | H12: =IS!H11 -> 0.58756571 | I12: =IS!I11 -> 0.58333604 | J12: =IS!J11 -> 0.57783944 | K12: =IS!K11 -> 0.58059836 | L12: =IS!L11 -> 0.58304949 | ... S12: =IS!S11 -> 0.58484855
B13: Management EBIT margin | E13: =IS!E38 -> 0.30053479 | F13: =IS!F38 -> 0.2774504 | G13: =IS!G38 -> 0.27726925 | H13: =IS!H38 -> 0.25602885 | I13: =IS!I38 -> 0.22290168 | J13: =IS!J38 -> 0.22352981 | K13: =IS!K38 -> 0.22847706 | L13: =IS!L38 -> 0.2330192 | ... S13: =IS!S38 -> 0.23819081
B14: Analyst EBIT margin | E14: =IS!E36 -> 0.29801212 | F14: =IS!F36 -> 0.2675654 | G14: =IS!G36 -> 0.26476606 | H14: =IS!H36 -> 0.2549889 | I14: =IS!I36 -> 0.21967522 | J14: =IS!J36 -> 0.21752981 | K14: =IS!K36 -> 0.22447706 | L14: =IS!L36 -> 0.2290192 | ... S14: =IS!S36 -> 0.23419081
B15: EBITDA | E15: =IS!E33 -> 715.04 | F15: =IS!F33 -> 889.985 | G15: =IS!G33 -> 1100.374 | H15: =IS!H33 -> 1115.833 | I15: =IS!I33 -> 966.912 | J15: =IS!J33 -> 970.03191 | K15: =IS!K33 -> 1031.2553 | L15: =IS!L33 -> 1091.2857 | ... S15: =IS!S33 -> 1410.3925
B16: Adjusted diluted EPS (US$) | E16: =IS!E39 -> 8.3153269 | F16: =IS!F39 -> 10.923588 | G16: =IS!G39 -> 12.034785 | H16: =IS!H39 -> 13.167903 | I16: =IS!I39 -> 12.597403 | J16: =IS!J39 -> 14.444715 | K16: =IS!K39 -> 17.050403 | L16: =IS!L39 -> 20.208268 | ... S16: =IS!S39 -> 57.035882
B17: GAAP diluted EPS (US$) | E17: =IS!E25 -> 11.389152 | F17: =IS!F25 -> 8.7113989 | G17: =IS!G25 -> 12.793227 | H17: =IS!H25 -> 15.878995 | I17: =IS!I25 -> -1.497897 | J17: =IS!J25 -> 13.171743 | K17: =IS!K25 -> 15.91723 | L17: =IS!L25 -> 18.876946 | ... S17: =IS!S25 -> 53.316132
B18: Free cash flow | E18: =CF!E37 -> 511.249 | F18: =CF!F37 -> 498.952 | G18: =CF!G37 -> 814.819 | H18: =CF!H37 -> 923.139 | I18: =CF!I37 -> 659.2 | J18: =CF!J37 -> 727.63606 | K18: =CF!K37 -> 789.21823 | L18: =CF!L37 -> 844.47355 | ... S18: =CF!S37 -> 1098.52
B19: Share repurchases | E19: =-CF!E29 -> 1000 | F19: =-CF!F29 -> 0 | G19: =-CF!G29 -> 175.019 | H19: =-CF!H29 -> 552.451 | I19: =-CF!I29 -> 582.32 | J19: =-CF!J29 -> 582.10885 | K19: =-CF!K29 -> 631.37459 | L19: =-CF!L29 -> 675.57884 | ... S19: =-CF!S29 -> 1098.52
B20: Net debt | E20: =Debt!E54 -> 558.193 | F20: =Debt!F54 -> 2130.76 | G20: =Debt!G54 -> 1515.036 | H20: =Debt!H54 -> 1168.854 | I20: =Debt!I54 -> 1100.531 | J20: =Debt!J54 -> 964.00379 | K20: =Debt!K54 -> 815.16014 | L20: =Debt!L54 -> 655.26543 | ... S20: =Debt!S54 -> 550
B21: Net debt / EBITDA | E21: =Debt!E55 -> 0.78064584 | F21: =Debt!F55 -> 2.3941527 | G21: =Debt!G55 -> 1.3768373 | H21: =Debt!H55 -> 1.047517 | I21: =Debt!I55 -> 1.1381915 | J21: =Debt!J55 -> 0.99378565 | K21: =Debt!K55 -> 0.79045425 | L21: =Debt!L55 -> 0.6004527 | ... S21: =Debt!S55 -> 0.38996238
B22: Diluted shares (m) | E22: =IS!E24 -> 63.718 | F22: =IS!F24 -> 62.006 | G22: =IS!G24 -> 61.952 | H22: =IS!H24 -> 59.832 | I22: =IS!I24 -> 54.208 | J22: =IS!J24 -> 48.344673 | K22: =IS!K24 -> 43.966801 | L22: =IS!L24 -> 39.93889 | ... S22: =IS!S24 -> 18.718461
B23: FY2026E vs management guidance (30-Jul-2026)
B24: Revenue growth | J24: =IS!J8 -> 0.015685357
B25: within guidance? | J25: =IF(AND(J24>=0.01-0.0005,J24<=0.02+0.0005),"Yes","No") -> Yes
B26: Crocs brand growth | J26: =Rev_Build!J18 -> 0.025120682
B27: within guidance? | J27: =IF(AND(J26>=0.02-0.0005,J26<=0.03+0.0005),"Yes","No") -> Yes
B28: HEYDUDE growth | J28: =Rev_Build!J25 -> -0.028212677
B29: within guidance? | J29: =IF(AND(J28>=-0.04-0.0005,J28<=-0.02+0.0005),"Yes","No") -> Yes
B30: Management (adjusted) EBIT margin | J30: =IS!J38 -> 0.22352981
B31: within guidance? | J31: =IF(AND(J30>=0.223-0.0005,J30<=0.235+0.0005),"Yes","No") -> Yes
B32: GAAP effective tax rate | J32: =IS!J22 -> 0.23
B33: within guidance? | J33: =IF(AND(J32>=0.225-0.0005,J32<=0.235+0.0005),"Yes","No") -> Yes
B34: Adjusted diluted EPS (US$) | J34: =IS!J39 -> 14.444715
B35: within guidance? | J35: =IF(AND(J34>=13.7-0.0005,J34<=14+0.0005),"Yes","No") -> No
B36: Memo: model FY26 diluted shares (m) | J36: =IS!J24 -> 48.344673
B37: Memo: diluted shares implied by guidance-midpoint EPS | J37: =IS!J39*IS!J24/13.85 -> 50.420579
B39: Scenario comparison (data table)
B40: Scenario | E40: Input | F40: FY26E revenue | G40: FY30E revenue | H40: FY25-30 revenue CAGR | I40: FY30E mgmt EBIT margin | J40: FY26E adj. EPS | K40: FY30E adj. EPS | L40: FY26-30 cumulative FCF | M40: FY30E net debt / EBITDA | N40: DCF value / share | O40: Upside to DCF value
B41: Live model (current selection) | F41: =IS!$J$7 -> 4104.026 | G41: =IS!$N$7 -> 4785.326 | H41: =(IS!$N$7/IS!$I$7)^(1/5)-1 -> 0.034408604 | I41: =IS!$N$38 -> 0.23698135 | J41: =IS!$J$39 -> 14.444715 | K41: =IS!$N$39 -> 27.708377 | L41: =SUM(CF!$J$37:$N$37) -> 4182.3202 | M41: =Debt!$N$55 -> 0.46036728 | N41: =ValuePerShare -> 222.98832 | O41: =Upside -> 0.88112298
B42: Base | E42: 1 | F42: 4104.026 | G42: 4785.326 | H42: 0.034408604 | I42: 0.23698135 | J42: 14.444715 | K42: 27.708377 | L42: 4182.3202 | M42: 0.46036728 | N42: 222.98832 | O42: 0.88112298
B43: Bull | E43: 2 | F43: 4188.2022 | G43: 5321.6687 | H43: 0.056621358 | I43: 0.26507681 | J43: 15.583661 | K43: 35.941766 | L43: 4961.7524 | M43: 0.37296963 | N43: 306.6416 | O43: 1.5868196
B44: Bear | E44: 3 | F44: 3999.9029 | G44: 3925.5935 | H44: -0.0057607973 | I44: 0.18697548 | J44: 12.697635 | K44: 16.384386 | L44: 2979.0637 | M44: 0.67816822 | N44: 113.57526 | O44: -0.041882392

Sheet Valuation
B1: Valuation summary & price target
B2: Crocs, Inc. (NASDAQ: CROX) | US$ millions unless stated
B4: Terminal-value and bridge assumptions
B5: Terminal growth - Base | C5: 0.025 | D5: Long-run nominal growth for a mature brand
B6: Terminal growth - Bull | C6: 0.03
B7: Terminal growth - Bear | C7: 0.01 | D7: A shrinking brand cannot grow at GDP forever
B8: Terminal growth - live scenario | C8: =CHOOSE(Scenario,TG_Base,TG_Bull,TG_Bear) -> 0.025
B9: Exit EV / EBITDA (cross-check method) | C9: 8 | D9: US GAAP basis; Crocs trades ~7x, developed peers ~9x
B10: Terminal cash tax rate | C10: 0.22 | D10: IP step-up shield has expired by then
B11: H2 share of FY26 free cash flow | C11: 0.668 | D11: FY23-25 average (quarterly data)
B12: Years to realise the residual deferred tax asset | C12: 10
B13: Roll-forward from 30-Jun to 30-Sep (years) | C13: 0.25
B14: Cash at 30-Jun-2026 | C14: 170.276 | D14: 10-Q Q2-26
B15: Long-term income taxes payable (uncertain tax positions) | C15: 639.58 | D15: 10-Q Q2-26 - a debt-like claim most models miss
B16: Share of UTP treated as debt | C16: 1 | D16: 100% = conservative
B17: Book equity at 30-Jun-2026 | C17: 1384.674 | D17: For residual income
B18: Diluted shares (m) | C18: =SharesOut+Dilution -> 48.345
B19: Terminal value
B20: FY35E FCFF | C20: =DCF!$S$17 -> 1078.8535
B21: FCFF normalised for terminal tax rate | C21: =FCFF_2035-DCF!$S$8*(TaxTV-Inputs!$S$103) -> 1026.1642
B22: Discount period to end-FY35 (years) | C22: =DCF!$S$21+0.5 -> 9.5
B23: Terminal value - Gordon growth | C23: =FCFF_TV*(1+TG)/(WACC-TG) -> 14968.19
B24: Terminal value - exit multiple | C24: =DCF!$S$24*ExitMultiple -> 11283.14
B25: Implied exit multiple in Gordon TV | C25: =TV_Gordon/DCF!$S$24 -> 10.612784
B26: Implied perpetual growth in exit-multiple TV | C26: =(TV_Exit*WACC-FCFF_TV)/(TV_Exit+FCFF_TV) -> 0.003963116
B27: Enterprise value -> equity value (Gordon, primary)
B28: PV of FCFF H2-26 to FY35 | C28: =SUM(DCF!$J$23:$S$23) -> 5883.3969
B29: PV of terminal value | C29: =TV_Gordon*(1+WACC)^-N_End -> 6305.4644
B30: PV of residual deferred-tax-asset shield after FY35 | C30: =Tax!$S$15/DTAYears*(1-(1+WACC)^-DTAYears)/WACC*(1+WACC)^-N_End -> 130.54831
B31: Enterprise value | C31: =PV_Explicit+PV_TV+PV_DTA -> 12319.41
B32: terminal value share of EV | C32: =PV_TV/EV_DCF -> 0.5118317
B33: Less: debt (face) | C33: =-DebtFace -> -1334
B34: Plus: cash | C34: =CashJun -> 170.276
B35: Less: uncertain tax positions | C35: =-UTP*UTPPct -> -639.58
B36: Equity value at 30-Jun-2026 | C36: =EV_DCF+Br_Debt+Br_Cash+Br_UTP -> 10516.106
B37: Equity value rolled to 30-Sep-2026 | C37: =Eq_Jun*(1+Ke)^RollFwd -> 10780.37
B38: DCF value per share (US$) | C38: =Eq_Sep/SharesDil -> 222.98832
B39: upside / (downside) vs share price | C39: =ValuePerShare/SharePrice-1 -> 0.88112298
B40: Cross-check: value per share, exit-multiple TV | C40: =((PV_Explicit+TV_Exit*(1+WACC)^-N_End+PV_DTA)+Br_Debt+Br_Cash+Br_UTP)*(1+Ke)^RollFwd/SharesDil -> 190.07146
B41: Implied EV / FY26E EBITDA at DCF value | C41: =EV_DCF/IS!$J$33 -> 12.700004
B42: NTM adjusted EPS (25% FY26E + 75% FY27E) | C42: =0.25*IS!$J$39+0.75*IS!$K$39 -> 16.398981
B43: Implied NTM P/E at DCF value | C43: =ValuePerShare/NTM_EPS -> 13.597694
B44: Alternative lenses
B45: FCFE model - value per share | C45: =(SUM(DCF!$J$28:$S$28)+DCF!$S$26*(1+TG)/(Ke-TG)*(1+Ke)^-N_End+CashJun-MinCash-UTP*UTPPct)*(1+Ke)^RollFwd/SharesDil -> 216.52282 | D45: Levered cash flows at Ke; excess cash added, UTP deducted
B46: Residual income model - value per share | C46: =(BookEquityJun+SUM(DCF!$J$33:$S$33)+DCF!$S$32*(1+TG)/(Ke-TG)*(1+Ke)^-N_End-UTP*UTPPct)*(1+Ke)^RollFwd/SharesDil -> 192.82717 | D46: Book value is small after buybacks, so most value is residual income
B47: FY27E total payout (buybacks / net income) | C47: =Equity!$K$10/IS!$K$23 -> 0.90218321
B48: Justified forward P/E = payout / (Ke - g) | C48: =MIN(Payout27,1)/(Ke-TG) -> 11.366671 | D48: Gordon-growth-based multiple
B49: Justified P/E x NTM EPS | C49: =Justified_PE*NTM_EPS -> 186.40183
B50: Sum of the parts (FY26E EBITDA)
B51: Crocs brand EBITDA | C51: =IS!$J$42+IS!$J$32*Rev_Build!$J$17/IS!$J$7 -> 1206.3358
B52: HEYDUDE EBITDA | C52: =IS!$J$44+IS!$J$32*Rev_Build!$J$24/IS!$J$7 -> 75.602069
B53: Corporate costs & charges | C53: =IS!$J$46 -> -311.90598
B54: Multiple - Crocs brand | C54: 9 | D54: Developed-market peer median (~9-10x)
B55: Multiple - HEYDUDE | C55: 6 | D55: Shrinking brand in reset: Wolverine / Dr. Martens-type
B56: Multiple - corporate costs | C56: 8.5 | D56: Blended
B57: SOTP enterprise value | C57: =SOTP_Crocs_EBITDA*SOTP_M_Crocs+SOTP_HD_EBITDA*SOTP_M_HD+SOTP_Corp*SOTP_M_Corp -> 8659.434
B58: SOTP value per share | C58: =(SOTP_EV-DebtFace+CashJun-UTP*UTPPct)/SharesDil -> 141.81673
B59: Market enterprise value (incl. UTP) | C59: =MktCap+DebtFace-CashJun+UTP*UTPPct -> 7486.7043
B60: What the market pays for HEYDUDE (residual) | C60: =MarketEV-SOTP_Crocs_EBITDA*SOTP_M_Crocs-SOTP_Corp*SOTP_M_Corp -> -719.11726 | D60: Market EV less Crocs brand and corporate at the multiples above
B61: implied HEYDUDE EV / EBITDA | C61: =Impl_HD_EV/SOTP_HD_EBITDA -> -9.5118727
B62: Scenarios, probability weights and price target
B63: Probability - Bull | C63: 0.2
B64: Probability - Base | C64: 0.5
B65: Probability - Bear | C65: 0.3 | D65: Bear weighted up for fashion-cycle risk
B66: DCF value - Base (data table) | C66: =Dashboard!$N$42 -> 222.98832
B67: DCF value - Bull (data table) | C67: =Dashboard!$N$43 -> 306.6416
B68: DCF value - Bear (data table) | C68: =Dashboard!$N$44 -> 113.57526
B69: Probability-weighted DCF value | C69: =W_Bull*DCF_Bull+W_Base*DCF_Base+W_Bear*DCF_Bear -> 206.89506
B70: Price-target weight - probability-weighted DCF | C70: 0.5
B71: Price-target weight - EV/EBITDA comps | C71: 0.25
B72: Price-target weight - P/E comps | C72: 0.25
B73: Blended value | C73: =PTW_DCF*DCF_PW+PTW_EV*Comps_EV_Value+PTW_PE*Comps_PE_Value -> 191.82799
B74: 12-month PRICE TARGET (US$, rounded to $5) | C74: =MROUND(PT_Raw,5) -> 190
B75: upside to price target | C75: =PriceTarget/SharePrice-1 -> 0.60283449
B76: RATING | C76: =IF(PT_Upside>0.15,"BUY",IF(PT_Upside<-0.1,"SELL","HOLD")) -> BUY | D76: BUY > +15%, SELL < -10%
B77: Reverse DCF (Base case, Goal Seek: ValuePerShare = SharePrice)
B78: Growth shift that equates DCF to the share price (all leaves, all years) | C78: -0.077389 | D78: Goal Seek on Sensitivity!GrowthShift with CircSwitch = 0, pasted as value
B79: Market-implied FY25-30 revenue CAGR | C79: -0.042737 | D79: FY30 revenue at the Goal Seek solution, pasted as value
B80: Live-scenario FY25-30 revenue CAGR | C80: =(IS!N7/IS!I7)^(1/5)-1 -> 0.034408604
B81: Market-implied terminal growth (Base margins) | C81: -0.166045 | D81: Goal Seek on TG_Base with CircSwitch = 0, pasted as value

Sheet Football_Field
B1: Valuation football field (US$ per share)
B2: Crocs, Inc. (NASDAQ: CROX) | US$ millions unless stated
B5: Method | C5: Low | D5: High | E5: Range (chart)
B6: 52-week trading range | C6: 73.39 | D6: 141.19 | E6: =MAX(0,D6-C6) -> 67.8
B7: Analyst price targets (consensus low-high) | C7: 95 | D7: 163 | E7: =MAX(0,D7-C7) -> 68
B8: Trading comps - EV/EBITDA (IFRS 16), 25th-75th | C8: =Comps_EV_Low -> 144.05876 | D8: =Comps_EV_High -> 179.6987 | E8: =MAX(0,D8-C8) -> 35.639936
B9: Trading comps - forward P/E, 25th-75th | C9: =Comps_PE_Low -> 173.61888 | D9: =Comps_PE_High -> 225.18999 | E9: =MAX(0,D9-C9) -> 51.571106
B10: Precedent transactions (control), 25th-75th | C10: =Prec_Low -> 163.60386 | D10: =Prec_High -> 213.43353 | E10: =MAX(0,D10-C10) -> 49.829665
B11: LBO - price for a 25% to 20% sponsor IRR | C11: =LBO_Px25 -> 135.47043 | D11: =LBO_Px20 -> 149.63484 | E11: =MAX(0,D11-C11) -> 14.164415
B12: DCF - Bear to Bull scenario | C12: =DCF_Bear -> 113.57526 | D12: =DCF_Bull -> 306.6416 | E12: =MAX(0,D12-C12) -> 193.06634
B13: DCF - Base, WACC +/-1%, growth +/-0.5% | C13: =MIN(Sensitivity!D11:F15) -> 184.78568 | D13: =MAX(Sensitivity!D11:F15) -> 281.09757 | E13: =MAX(0,D13-C13) -> 96.311885
B15: Current share price | C15: =SharePrice -> 118.54
B16: Price target | C16: =PriceTarget -> 190
B17: Rating | C17: =Rating -> BUY
B18: ="Value per share by method (US$) | price "&TEXT(SharePrice,"$0.00")&" | price target "&TEXT(PriceTarget,"$0") -> Value per share by method (US$) | price $118.54 | price target $190

Sheet Inputs
B1: Inputs & scenarios
B2: Crocs, Inc. (NASDAQ: CROX) | US$ millions unless stated
B4: Fiscal year ending 31-Dec | C4: Unit | D4: Comment | E4: FY2021A | F4: FY2022A | G4: FY2023A | H4: FY2024A | I4: FY2025A | J4: FY2026E | K4: FY2027E | L4: FY2028E | M4: FY2029E | N4: FY2030E | O4: FY2031E | P4: FY2032E | Q4: FY2033E | R4: FY2034E | S4: FY2035E
B6: Model controls & market data
B7: Scenario (1 = Base, 2 = Bull, 3 = Bear) | D7: Drives every CHOOSE() on this sheet | E7: 1
B8: Circularity switch (1 = average balances, 0 = opening) | D8: Set to 0 if Excel ever shows a circular-reference warning, then back to 1 | E8: 1
B9: Share price (US$) - Nasdaq close 30-Sep-2026 (valuation date) | D9: Nasdaq close; update before use | E9: 118.54
B10: Basic shares outstanding (m) - 23-Jul-2026 | D10: 10-Q Q2-26 cover page | E10: 47.945
B11: Return all excess cash once revolver & TLB are repaid (1 = yes) | D11: Stops idle cash piling up; mgmt targets 1.0-1.5x leverage | E11: 1
B12: Buyback price method (1 = constant P/E on trailing EPS, 2 = fixed growth) | D12: Mode 1 keeps the multiple constant, so cheap buybacks do not compound forever | E12: 1
B13: Repurchase price growth p.a. (mode 2 only) | D13: ~cost of equity | E13: 0.08
B14: Minimum operating cash balance | D14: FY25 year-end 130; LTM 170 | E14: 150
B15: Interest rate earned on cash | E15: 0.03
B16: Revolving credit facility capacity | D16: 10-K: $1.0bn senior revolver | E16: 1000
B17: Revolver margin over SOFR | D17: 10-K grid: SOFR + 1.35% to 1.98% | E17: 0.015
B18: Commitment fee on undrawn revolver | E18: 0.002
B19: Term Loan B margin over SOFR | D19: 10-K: SOFR + 2.25%; matures Feb-2029 | E19: 0.0225
B20: Excess-cash sweep to Term Loan B | D20: After the revolver is repaid | E20: 1
B21: Coupon - 4.25% senior notes due Mar-2029 | D21: 10-K; $350m outstanding | E21: 0.0425
B22: Coupon - 4.125% senior notes due Aug-2031 | D22: 10-K; $350m outstanding | E22: 0.04125
B23: Refinance senior notes at maturity (1 = yes) | D23: 0 = repay from cash / revolver | E23: 1
B24: Coupon on refinancing notes | D24: Assumption: BB-rated consumer credit | E24: 0.0575
B25: Amortisation of deferred financing fees p.a. | D25: Unamortised $31.1m at FY25 | E25: 9
B26: Shares issued on RSU vesting p.a. (m) | D26: Net of withholding | E26: 0.4
B27: Dilutive securities (m) | D27: FY25: 0.37m under treasury-stock method | E27: 0.4
B28: Live scenario used by the model | D28: Equals the selector unless the Dashboard scenario table is overriding it | E28: =IF(ScenarioOverride=0,Scenario_Select,ScenarioOverride) -> 1
B29: Revenue drivers (scenario)
B30: Crocs North America wholesale growth | D30: H1-26 -14%; retailers de-stocking the clog, DTC taking share | F30: =IFERROR(Rev_Build!F7/Rev_Build!E7-1,"n.m.") -> -0.04451745 | G30: =IFERROR(Rev_Build!G7/Rev_Build!F7-1,"n.m.") -> 0.013548272 | H30: =IFERROR(Rev_Build!H7/Rev_Build!G7-1,"n.m.") -> -0.012913838 | I30: =IFERROR(Rev_Build!I7/Rev_Build!H7-1,"n.m.") -> -0.092836274 | J30: =CHOOSE(Scenario,J31,J32,J33)+GrowthShift -> -0.1 | K30: =CHOOSE(Scenario,K31,K32,K33)+GrowthShift -> -0.03 | L30: =CHOOSE(Scenario,L31,L32,L33)+GrowthShift -> 0 | M30: =CHOOSE(Scenario,M31,M32,M33)+GrowthShift -> 0.01 | N30: =CHOOSE(Scenario,N31,N32,N33)+GrowthShift -> 0.02 | O30: =CHOOSE(Scenario,O31,O32,O33)+GrowthShift -> 0.021 | P30: =CHOOSE(Scenario,P31,P32,P33)+GrowthShift -> 0.022 | Q30: =CHOOSE(Scenario,Q31,Q32,Q33)+GrowthShift -> 0.023 | ... S30: =CHOOSE(Scenario,S31,S32,S33)+GrowthShift -> 0.025
B31: Base | J31: -0.1 | K31: -0.03 | L31: 0 | M31: 0.01 | N31: 0.02 | O31: 0.021 | P31: 0.022 | Q31: 0.023 | R31: 0.024 | S31: 0.025
B32: Bull | J32: -0.08 | K32: 0.01 | L32: 0.03 | M32: 0.03 | N32: 0.03 | O32: 0.03 | P32: 0.03 | Q32: 0.03 | R32: 0.03 | S32: 0.03
B33: Bear | J33: -0.12 | K33: -0.08 | L33: -0.05 | M33: -0.03 | N33: -0.02 | O33: -0.014 | P33: -0.008 | Q33: -0.002 | R33: 0.004 | S33: 0.01
B34: Crocs North America DTC growth | D34: H1-26 +5%; mature channel, growth ~ nominal consumer spend | F34: =IFERROR(Rev_Build!F9/Rev_Build!E9-1,"n.m.") -> 0.13719042 | G34: =IFERROR(Rev_Build!G9/Rev_Build!F9-1,"n.m.") -> 0.12444612 | H34: =IFERROR(Rev_Build!H9/Rev_Build!G9-1,"n.m.") -> 0.056864265 | I34: =IFERROR(Rev_Build!I9/Rev_Build!H9-1,"n.m.") -> -0.053791243 | J34: =CHOOSE(Scenario,J35,J36,J37)+GrowthShift -> 0.03 | K34: =CHOOSE(Scenario,K35,K36,K37)+GrowthShift -> 0.03 | L34: =CHOOSE(Scenario,L35,L36,L37)+GrowthShift -> 0.03 | M34: =CHOOSE(Scenario,M35,M36,M37)+GrowthShift -> 0.03 | N34: =CHOOSE(Scenario,N35,N36,N37)+GrowthShift -> 0.03 | O34: =CHOOSE(Scenario,O35,O36,O37)+GrowthShift -> 0.029 | P34: =CHOOSE(Scenario,P35,P36,P37)+GrowthShift -> 0.028 | Q34: =CHOOSE(Scenario,Q35,Q36,Q37)+GrowthShift -> 0.027 | ... S34: =CHOOSE(Scenario,S35,S36,S37)+GrowthShift -> 0.025
B35: Base | J35: 0.03 | K35: 0.03 | L35: 0.03 | M35: 0.03 | N35: 0.03 | O35: 0.029 | P35: 0.028 | Q35: 0.027 | R35: 0.026 | S35: 0.025
B36: Bull | J36: 0.05 | K36: 0.05 | L36: 0.04 | M36: 0.04 | N36: 0.04 | O36: 0.038 | P36: 0.036 | Q36: 0.034 | R36: 0.032 | S36: 0.03
B37: Bear | J37: 0.01 | K37: -0.02 | L37: -0.02 | M37: 0 | N37: 0.01 | O37: 0.011 | P37: 0.012 | Q37: 0.013 | R37: 0.014 | S37: 0.015
B38: Crocs International wholesale growth | D38: H1-26 -1% as distributor markets move to DTC (takebacks) | F38: =IFERROR(Rev_Build!F11/Rev_Build!E11-1,"n.m.") -> 0.46661105 | G38: =IFERROR(Rev_Build!G11/Rev_Build!F11-1,"n.m.") -> 0.14664972 | H38: =IFERROR(Rev_Build!H11/Rev_Build!G11-1,"n.m.") -> 0.14566009 | I38: =IFERROR(Rev_Build!I11/Rev_Build!H11-1,"n.m.") -> 0.053644987 | J38: =CHOOSE(Scenario,J39,J40,J41)+GrowthShift -> 0 | K38: =CHOOSE(Scenario,K39,K40,K41)+GrowthShift -> 0.04 | L38: =CHOOSE(Scenario,L39,L40,L41)+GrowthShift -> 0.05 | M38: =CHOOSE(Scenario,M39,M40,M41)+GrowthShift -> 0.05 | N38: =CHOOSE(Scenario,N39,N40,N41)+GrowthShift -> 0.04 | O38: =CHOOSE(Scenario,O39,O40,O41)+GrowthShift -> 0.038 | P38: =CHOOSE(Scenario,P39,P40,P41)+GrowthShift -> 0.036 | Q38: =CHOOSE(Scenario,Q39,Q40,Q41)+GrowthShift -> 0.034 | ... S38: =CHOOSE(Scenario,S39,S40,S41)+GrowthShift -> 0.03
B39: Base | J39: 0 | K39: 0.04 | L39: 0.05 | M39: 0.05 | N39: 0.04 | O39: 0.038 | P39: 0.036 | Q39: 0.034 | R39: 0.032 | S39: 0.03
B40: Bull | J40: 0.02 | K40: 0.07 | L40: 0.07 | M40: 0.06 | N40: 0.05 | O40: 0.047 | P40: 0.044 | Q40: 0.041 | R40: 0.038 | S40: 0.035
B41: Bear | J41: -0.03 | K41: -0.02 | L41: 0.01 | M41: 0.02 | N41: 0.02 | O41: 0.02 | P41: 0.02 | Q41: 0.02 | R41: 0.02 | S41: 0.02
B42: Crocs International DTC growth | D42: H1-26 +26%; China, India, SE Asia store & e-com build-out | F42: =IFERROR(Rev_Build!F13/Rev_Build!E13-1,"n.m.") -> 0.083960291 | G42: =IFERROR(Rev_Build!G13/Rev_Build!F13-1,"n.m.") -> 0.40191981 | H42: =IFERROR(Rev_Build!H13/Rev_Build!G13-1,"n.m.") -> 0.22063502 | I42: =IFERROR(Rev_Build!I13/Rev_Build!H13-1,"n.m.") -> 0.24914332 | J42: =CHOOSE(Scenario,J43,J44,J45)+GrowthShift -> 0.18 | K42: =CHOOSE(Scenario,K43,K44,K45)+GrowthShift -> 0.12 | L42: =CHOOSE(Scenario,L43,L44,L45)+GrowthShift -> 0.1 | M42: =CHOOSE(Scenario,M43,M44,M45)+GrowthShift -> 0.08 | N42: =CHOOSE(Scenario,N43,N44,N45)+GrowthShift -> 0.07 | O42: =CHOOSE(Scenario,O43,O44,O45)+GrowthShift -> 0.063 | P42: =CHOOSE(Scenario,P43,P44,P45)+GrowthShift -> 0.056 | Q42: =CHOOSE(Scenario,Q43,Q44,Q45)+GrowthShift -> 0.049 | ... S42: =CHOOSE(Scenario,S43,S44,S45)+GrowthShift -> 0.035
B43: Base | J43: 0.18 | K43: 0.12 | L43: 0.1 | M43: 0.08 | N43: 0.07 | O43: 0.063 | P43: 0.056 | Q43: 0.049 | R43: 0.042 | S43: 0.035
B44: Bull | J44: 0.2 | K44: 0.16 | L44: 0.14 | M44: 0.12 | N44: 0.1 | O44: 0.089 | P44: 0.078 | Q44: 0.067 | R44: 0.056 | S44: 0.045
B45: Bear | J45: 0.15 | K45: 0.06 | L45: 0.04 | M45: 0.03 | N45: 0.029167 | O45: 0.028333 | P45: 0.0275 | Q45: 0.026667 | R45: 0.025833 | S45: 0.025
B46: HEYDUDE wholesale growth | D46: H1-26 -21%; brand reset, cleaning up channel inventory | G46: =IFERROR(Rev_Build!G20/Rev_Build!F20-1,"n.m.") -> -0.012545721 | H46: =IFERROR(Rev_Build!H20/Rev_Build!G20-1,"n.m.") -> -0.19484528 | I46: =IFERROR(Rev_Build!I20/Rev_Build!H20-1,"n.m.") -> -0.26320782 | J46: =CHOOSE(Scenario,J47,J48,J49)+GrowthShift -> -0.15 | K46: =CHOOSE(Scenario,K47,K48,K49)+GrowthShift -> -0.06 | L46: =CHOOSE(Scenario,L47,L48,L49)+GrowthShift -> -0.02 | M46: =CHOOSE(Scenario,M47,M48,M49)+GrowthShift -> 0.01 | N46: =CHOOSE(Scenario,N47,N48,N49)+GrowthShift -> 0.02 | O46: =CHOOSE(Scenario,O47,O48,O49)+GrowthShift -> 0.021 | P46: =CHOOSE(Scenario,P47,P48,P49)+GrowthShift -> 0.022 | Q46: =CHOOSE(Scenario,Q47,Q48,Q49)+GrowthShift -> 0.023 | ... S46: =CHOOSE(Scenario,S47,S48,S49)+GrowthShift -> 0.025
B47: Base | J47: -0.15 | K47: -0.06 | L47: -0.02 | M47: 0.01 | N47: 0.02 | O47: 0.021 | P47: 0.022 | Q47: 0.023 | R47: 0.024 | S47: 0.025
B48: Bull | J48: -0.12 | K48: 0 | L48: 0.03 | M48: 0.04 | N48: 0.04 | O48: 0.038 | P48: 0.036 | Q48: 0.034 | R48: 0.032 | S48: 0.03
B49: Bear | J49: -0.18 | K49: -0.15 | L49: -0.1 | M49: -0.05 | N49: -0.02 | O49: -0.014 | P49: -0.008 | Q49: -0.002 | R49: 0.004 | S49: 0.01
B50: HEYDUDE DTC growth | D50: H1-26 +8%; DTC holding up while wholesale resets | G50: =IFERROR(Rev_Build!G22/Rev_Build!F22-1,"n.m.") -> 0.18878528 | H50: =IFERROR(Rev_Build!H22/Rev_Build!G22-1,"n.m.") -> -0.038663271 | I50: =IFERROR(Rev_Build!I22/Rev_Build!H22-1,"n.m.") -> 0.029499359 | J50: =CHOOSE(Scenario,J51,J52,J53)+GrowthShift -> 0.08 | K50: =CHOOSE(Scenario,K51,K52,K53)+GrowthShift -> 0.04 | L50: =CHOOSE(Scenario,L51,L52,L53)+GrowthShift -> 0.03 | M50: =CHOOSE(Scenario,M51,M52,M53)+GrowthShift -> 0.029286 | N50: =CHOOSE(Scenario,N51,N52,N53)+GrowthShift -> 0.028571 | O50: =CHOOSE(Scenario,O51,O52,O53)+GrowthShift -> 0.027857 | P50: =CHOOSE(Scenario,P51,P52,P53)+GrowthShift -> 0.027143 | Q50: =CHOOSE(Scenario,Q51,Q52,Q53)+GrowthShift -> 0.026429 | ... S50: =CHOOSE(Scenario,S51,S52,S53)+GrowthShift -> 0.025
B51: Base | J51: 0.08 | K51: 0.04 | L51: 0.03 | M51: 0.029286 | N51: 0.028571 | O51: 0.027857 | P51: 0.027143 | Q51: 0.026429 | R51: 0.025714 | S51: 0.025
B52: Bull | J52: 0.1 | K52: 0.07 | L52: 0.05 | M52: 0.045 | N52: 0.04 | O52: 0.038 | P52: 0.036 | Q52: 0.034 | R52: 0.032 | S52: 0.03
B53: Bear | J53: 0.05 | K53: -0.03 | L53: -0.03 | M53: 0 | N53: 0.01 | O53: 0.01 | P53: 0.01 | Q53: 0.01 | R53: 0.01 | S53: 0.01
B54: Margin drivers (scenario)
B55: Crocs brand gross margin | D55: FY24 61.6%, FY25 61.3%, LTM 60.6%; tariffs offset by DTC mix | F55: =1-Hist!F91/Hist!F90 -> 0.56324957 | G55: =1-Hist!G91/Hist!G90 -> 0.5998379 | H55: =1-Hist!H91/Hist!H90 -> 0.61600376 | I55: =1-Hist!I91/Hist!I90 -> 0.61289185 | J55: =CHOOSE(Scenario,J56,J57,J58)+GMShift -> 0.61 | K55: =CHOOSE(Scenario,K56,K57,K58)+GMShift -> 0.61 | L55: =CHOOSE(Scenario,L56,L57,L58)+GMShift -> 0.61 | M55: =CHOOSE(Scenario,M56,M57,M58)+GMShift -> 0.61 | N55: =CHOOSE(Scenario,N56,N57,N58)+GMShift -> 0.61 | O55: =CHOOSE(Scenario,O56,O57,O58)+GMShift -> 0.61 | P55: =CHOOSE(Scenario,P56,P57,P58)+GMShift -> 0.61 | Q55: =CHOOSE(Scenario,Q56,Q57,Q58)+GMShift -> 0.61 | ... S55: =CHOOSE(Scenario,S56,S57,S58)+GMShift -> 0.61
B56: Base | J56: 0.61 | K56: 0.61 | L56: 0.61 | M56: 0.61 | N56: 0.61 | O56: 0.61 | P56: 0.61 | Q56: 0.61 | R56: 0.61 | S56: 0.61
B57: Bull | J57: 0.615 | K57: 0.6175 | L57: 0.62 | M57: 0.62 | N57: 0.62 | O57: 0.62 | P57: 0.62 | Q57: 0.62 | R57: 0.62 | S57: 0.62
B58: Bear | J58: 0.6 | K58: 0.595 | L58: 0.59 | M58: 0.59 | N58: 0.59 | O58: 0.59 | P58: 0.59 | Q58: 0.59 | R58: 0.59 | S58: 0.59
B59: HEYDUDE gross margin | D59: FY24 47.7% -> LTM 42.1% on clearance; partial recovery once channel is clean | F59: =1-Hist!F95/Hist!F94 -> 0.40832385 | G59: =1-Hist!G95/Hist!G94 -> 0.4402592 | H59: =1-Hist!H95/Hist!H94 -> 0.47716107 | I59: =1-Hist!I95/Hist!I94 -> 0.44770158 | J59: =CHOOSE(Scenario,J60,J61,J62)+GMShift -> 0.42 | K59: =CHOOSE(Scenario,K60,K61,K62)+GMShift -> 0.43 | L59: =CHOOSE(Scenario,L60,L61,L62)+GMShift -> 0.44 | M59: =CHOOSE(Scenario,M60,M61,M62)+GMShift -> 0.44 | N59: =CHOOSE(Scenario,N60,N61,N62)+GMShift -> 0.44 | O59: =CHOOSE(Scenario,O60,O61,O62)+GMShift -> 0.44 | P59: =CHOOSE(Scenario,P60,P61,P62)+GMShift -> 0.44 | Q59: =CHOOSE(Scenario,Q60,Q61,Q62)+GMShift -> 0.44 | ... S59: =CHOOSE(Scenario,S60,S61,S62)+GMShift -> 0.44
B60: Base | J60: 0.42 | K60: 0.43 | L60: 0.44 | M60: 0.44 | N60: 0.44 | O60: 0.44 | P60: 0.44 | Q60: 0.44 | R60: 0.44 | S60: 0.44
B61: Bull | J61: 0.43 | K61: 0.445 | L61: 0.4525 | M61: 0.46 | N61: 0.46 | O61: 0.46 | P61: 0.46 | Q61: 0.46 | R61: 0.46 | S61: 0.46
B62: Bear | J62: 0.41 | K62: 0.405 | L62: 0.4 | M62: 0.4 | N62: 0.4 | O62: 0.4 | P62: 0.4 | Q62: 0.4 | R62: 0.4 | S62: 0.4
B63: Crocs brand SG&A % revenue | D63: FY24 25.5% -> FY25 27.9% (marketing, DTC build); operating leverage in Base | F63: =Hist!F92/Hist!F90 -> 0.24283401 | G63: =Hist!G92/Hist!G90 -> 0.24160807 | H63: =Hist!H92/Hist!H90 -> 0.25541075 | I63: =Hist!I92/Hist!I90 -> 0.27863343 | J63: =CHOOSE(Scenario,J64,J65,J66) -> 0.275 | K63: =CHOOSE(Scenario,K64,K65,K66) -> 0.27375 | L63: =CHOOSE(Scenario,L64,L65,L66) -> 0.2725 | M63: =CHOOSE(Scenario,M64,M65,M66) -> 0.27125 | N63: =CHOOSE(Scenario,N64,N65,N66) -> 0.27 | O63: =CHOOSE(Scenario,O64,O65,O66) -> 0.27 | P63: =CHOOSE(Scenario,P64,P65,P66) -> 0.27 | Q63: =CHOOSE(Scenario,Q64,Q65,Q66) -> 0.27 | ... S63: =CHOOSE(Scenario,S64,S65,S66) -> 0.27
B64: Base | J64: 0.275 | K64: 0.27375 | L64: 0.2725 | M64: 0.27125 | N64: 0.27 | O64: 0.27 | P64: 0.27 | Q64: 0.27 | R64: 0.27 | S64: 0.27
B65: Bull | J65: 0.273 | K65: 0.26975 | L65: 0.2665 | M65: 0.26325 | N65: 0.26 | O65: 0.26 | P65: 0.26 | Q65: 0.26 | R65: 0.26 | S65: 0.26
B66: Bear | J66: 0.28 | K66: 0.283333 | L66: 0.286667 | M66: 0.29 | N66: 0.29 | O66: 0.29 | P66: 0.29 | Q66: 0.29 | R66: 0.29 | S66: 0.29
B67: HEYDUDE SG&A % revenue | D67: FY25 35.2%, LTM 34.0% after cost actions | F67: =Hist!F96/Hist!F94 -> 0.17239301 | G67: =Hist!G96/Hist!G94 -> 0.21655205 | H67: =Hist!H96/Hist!H94 -> 0.30383878 | I67: =Hist!I96/Hist!I94 -> 0.35237256 | J67: =CHOOSE(Scenario,J68,J69,J70) -> 0.33 | K67: =CHOOSE(Scenario,K68,K69,K70) -> 0.325 | L67: =CHOOSE(Scenario,L68,L69,L70) -> 0.32 | M67: =CHOOSE(Scenario,M68,M69,M70) -> 0.315 | N67: =CHOOSE(Scenario,N68,N69,N70) -> 0.315 | O67: =CHOOSE(Scenario,O68,O69,O70) -> 0.315 | P67: =CHOOSE(Scenario,P68,P69,P70) -> 0.315 | Q67: =CHOOSE(Scenario,Q68,Q69,Q70) -> 0.315 | ... S67: =CHOOSE(Scenario,S68,S69,S70) -> 0.315
B68: Base | J68: 0.33 | K68: 0.325 | L68: 0.32 | M68: 0.315 | N68: 0.315 | O68: 0.315 | P68: 0.315 | Q68: 0.315 | R68: 0.315 | S68: 0.315
B69: Bull | J69: 0.32 | K69: 0.31 | L69: 0.3 | M69: 0.29 | N69: 0.29 | O69: 0.29 | P69: 0.29 | Q69: 0.29 | R69: 0.29 | S69: 0.29
B70: Bear | J70: 0.34 | K70: 0.346667 | L70: 0.353333 | M70: 0.36 | N70: 0.36 | O70: 0.36 | P70: 0.36 | Q70: 0.36 | R70: 0.36 | S70: 0.36
B71: Corporate / unallocated costs % revenue | D71: FY25 7.3%; shared services, corporate IT | E71: =-Hist!E98/Hist!E7 -> 0.077085142 | F71: =-Hist!F98/Hist!F7 -> 0.059811785 | G71: =-Hist!G98/Hist!G7 -> 0.064338888 | H71: =-Hist!H98/Hist!H7 -> 0.072524175 | I71: =-Hist!I98/Hist!I7 -> 0.072589613 | J71: =CHOOSE(Scenario,J72,J73,J74) -> 0.07 | K71: =CHOOSE(Scenario,K72,K73,K74) -> 0.07 | L71: =CHOOSE(Scenario,L72,L73,L74) -> 0.07 | M71: =CHOOSE(Scenario,M72,M73,M74) -> 0.07 | N71: =CHOOSE(Scenario,N72,N73,N74) -> 0.07 | O71: =CHOOSE(Scenario,O72,O73,O74) -> 0.07 | P71: =CHOOSE(Scenario,P72,P73,P74) -> 0.07 | Q71: =CHOOSE(Scenario,Q72,Q73,Q74) -> 0.07 | ... S71: =CHOOSE(Scenario,S72,S73,S74) -> 0.07
B72: Base | J72: 0.07 | K72: 0.07 | L72: 0.07 | M72: 0.07 | N72: 0.07 | O72: 0.07 | P72: 0.07 | Q72: 0.07 | R72: 0.07 | S72: 0.07
B73: Bull | J73: 0.069 | K73: 0.068 | L73: 0.067 | M73: 0.066 | N73: 0.065 | O73: 0.065 | P73: 0.065 | Q73: 0.065 | R73: 0.065 | S73: 0.065
B74: Bear | J74: 0.072 | K74: 0.07275 | L74: 0.0735 | M74: 0.07425 | N74: 0.075 | O74: 0.075 | P74: 0.075 | Q74: 0.075 | R74: 0.075 | S74: 0.075
B75: Restructuring & other charges % revenue | D75: Guided ~$25m FY26; treated as a recurring cost (appears every year since 2019) | E75: =(Hist!E29-Hist!E28)/Hist!E7 -> 0.0025226764 | F75: =(Hist!F29-Hist!F28)/Hist!F7 -> 0.0098849925 | G75: =(Hist!G29-Hist!G28)/Hist!G7 -> 0.012503196 | H75: =(Hist!H29-Hist!H28)/Hist!H7 -> 0.0010399531 | I75: =(Hist!I29-Hist!I28)/Hist!I7 -> 0.0032264635 | J75: =CHOOSE(Scenario,J76,J77,J78) -> 0.006 | K75: =CHOOSE(Scenario,K76,K77,K78) -> 0.004 | L75: =CHOOSE(Scenario,L76,L77,L78) -> 0.004 | M75: =CHOOSE(Scenario,M76,M77,M78) -> 0.004 | N75: =CHOOSE(Scenario,N76,N77,N78) -> 0.004 | O75: =CHOOSE(Scenario,O76,O77,O78) -> 0.004 | P75: =CHOOSE(Scenario,P76,P77,P78) -> 0.004 | Q75: =CHOOSE(Scenario,Q76,Q77,Q78) -> 0.004 | ... S75: =CHOOSE(Scenario,S76,S77,S78) -> 0.004
B76: Base | J76: 0.006 | K76: 0.004 | L76: 0.004 | M76: 0.004 | N76: 0.004 | O76: 0.004 | P76: 0.004 | Q76: 0.004 | R76: 0.004 | S76: 0.004
B77: Bull | J77: 0.005 | K77: 0.003 | L77: 0.003 | M77: 0.003 | N77: 0.003 | O77: 0.003 | P77: 0.003 | Q77: 0.003 | R77: 0.003 | S77: 0.003
B78: Bear | J78: 0.008 | K78: 0.006 | L78: 0.006 | M78: 0.006 | N78: 0.006 | O78: 0.006 | P78: 0.006 | Q78: 0.006 | R78: 0.006 | S78: 0.006
B79: Working capital & capex (scenario)
B80: Receivable days (DSO, on revenue) | D80: FY23 28.2, FY24 22.9, FY25 25.1 (year-end) | E80: =Hist!E33/Hist!E7*365 -> 28.814353 | F80: =Hist!F33/Hist!F7*365 -> 30.349442 | G80: =Hist!G33/Hist!G7*365 -> 28.164534 | H80: =Hist!H33/Hist!H7*365 -> 22.92597 | I80: =Hist!I33/Hist!I7*365 -> 25.129568 | J80: =CHOOSE(Scenario,J81,J82,J83) -> 25 | K80: =CHOOSE(Scenario,K81,K82,K83) -> 25 | L80: =CHOOSE(Scenario,L81,L82,L83) -> 25 | M80: =CHOOSE(Scenario,M81,M82,M83) -> 25 | N80: =CHOOSE(Scenario,N81,N82,N83) -> 25 | O80: =CHOOSE(Scenario,O81,O82,O83) -> 25 | P80: =CHOOSE(Scenario,P81,P82,P83) -> 25 | Q80: =CHOOSE(Scenario,Q81,Q82,Q83) -> 25 | ... S80: =CHOOSE(Scenario,S81,S82,S83) -> 25
B81: Base | J81: 25 | K81: 25 | L81: 25 | M81: 25 | N81: 25 | O81: 25 | P81: 25 | Q81: 25 | R81: 25 | S81: 25
B82: Bull | J82: 24 | K82: 24 | L82: 24 | M82: 24 | N82: 24 | O82: 24 | P82: 24 | Q82: 24 | R82: 24 | S82: 24
B83: Bear | J83: 27 | K83: 27 | L83: 27 | M83: 27 | N83: 27 | O83: 27 | P83: 27 | Q83: 27 | R83: 27 | S83: 27
B84: Inventory days (DIO, on COGS) | D84: FY23 80.2, FY24 76.9, FY25 79.9 | E84: =Hist!E34/Hist!E8*365 -> 87.253861 | F84: =Hist!F34/Hist!F8*365 -> 101.56123 | G84: =Hist!G34/Hist!G8*365 -> 80.204156 | H84: =Hist!H34/Hist!H8*365 -> 76.858297 | I84: =Hist!I34/Hist!I8*365 -> 79.93074 | J84: =CHOOSE(Scenario,J85,J86,J87) -> 80 | K84: =CHOOSE(Scenario,K85,K86,K87) -> 80 | L84: =CHOOSE(Scenario,L85,L86,L87) -> 80 | M84: =CHOOSE(Scenario,M85,M86,M87) -> 80 | N84: =CHOOSE(Scenario,N85,N86,N87) -> 80 | O84: =CHOOSE(Scenario,O85,O86,O87) -> 80 | P84: =CHOOSE(Scenario,P85,P86,P87) -> 80 | Q84: =CHOOSE(Scenario,Q85,Q86,Q87) -> 80 | ... S84: =CHOOSE(Scenario,S85,S86,S87) -> 80
B85: Base | J85: 80 | K85: 80 | L85: 80 | M85: 80 | N85: 80 | O85: 80 | P85: 80 | Q85: 80 | R85: 80 | S85: 80
B86: Bull | J86: 76 | K86: 76 | L86: 76 | M86: 76 | N86: 76 | O86: 76 | P86: 76 | Q86: 76 | R86: 76 | S86: 76
B87: Bear | J87: 88 | K87: 88 | L87: 88 | M87: 88 | N87: 88 | O87: 88 | P87: 88 | Q87: 88 | R87: 88 | S87: 88
B88: Payable days (DPO, on COGS) | D88: FY23 54.4, FY24 57.2, FY25 57.7 | E88: =Hist!E46/Hist!E8*365 -> 66.259729 | F88: =Hist!F46/Hist!F8*365 -> 49.713528 | G88: =Hist!G46/Hist!G8*365 -> 54.35996 | H88: =Hist!H46/Hist!H8*365 -> 57.149786 | I88: =Hist!I46/Hist!I8*365 -> 57.687878 | J88: =CHOOSE(Scenario,J89,J90,J91) -> 57 | K88: =CHOOSE(Scenario,K89,K90,K91) -> 57 | L88: =CHOOSE(Scenario,L89,L90,L91) -> 57 | M88: =CHOOSE(Scenario,M89,M90,M91) -> 57 | N88: =CHOOSE(Scenario,N89,N90,N91) -> 57 | O88: =CHOOSE(Scenario,O89,O90,O91) -> 57 | P88: =CHOOSE(Scenario,P89,P90,P91) -> 57 | Q88: =CHOOSE(Scenario,Q89,Q90,Q91) -> 57 | ... S88: =CHOOSE(Scenario,S89,S90,S91) -> 57
B89: Base | J89: 57 | K89: 57 | L89: 57 | M89: 57 | N89: 57 | O89: 57 | P89: 57 | Q89: 57 | R89: 57 | S89: 57
B90: Bull | J90: 58 | K90: 58 | L90: 58 | M90: 58 | N90: 58 | O90: 58 | P90: 58 | Q90: 58 | R90: 58 | S90: 58
B91: Bear | J91: 55 | K91: 55 | L91: 55 | M91: 55 | N91: 55 | O91: 55 | P91: 55 | Q91: 55 | R91: 55 | S91: 55
B92: Capex % revenue | D92: FY22-23 2.9% (DC build-out), FY25 1.3%, LTM 1.4% | E92: =-Hist!E70/Hist!E7 -> 0.024170318 | F92: =-Hist!F70/Hist!F7 -> 0.029308141 | G92: =-Hist!G70/Hist!G7 -> 0.029180937 | H92: =-Hist!H70/Hist!H7 -> 0.016905211 | I92: =-Hist!I70/Hist!I7 -> 0.01267891 | J92: =CHOOSE(Scenario,J93,J94,J95) -> 0.016 | K92: =CHOOSE(Scenario,K93,K94,K95) -> 0.016 | L92: =CHOOSE(Scenario,L93,L94,L95) -> 0.016 | M92: =CHOOSE(Scenario,M93,M94,M95) -> 0.016 | N92: =CHOOSE(Scenario,N93,N94,N95) -> 0.016 | O92: =CHOOSE(Scenario,O93,O94,O95) -> 0.016 | P92: =CHOOSE(Scenario,P93,P94,P95) -> 0.016 | Q92: =CHOOSE(Scenario,Q93,Q94,Q95) -> 0.016 | ... S92: =CHOOSE(Scenario,S93,S94,S95) -> 0.016
B93: Base | J93: 0.016 | K93: 0.016 | L93: 0.016 | M93: 0.016 | N93: 0.016 | O93: 0.016 | P93: 0.016 | Q93: 0.016 | R93: 0.016 | S93: 0.016
B94: Bull | J94: 0.015 | K94: 0.015 | L94: 0.015 | M94: 0.015 | N94: 0.015 | O94: 0.015 | P94: 0.015 | Q94: 0.015 | R94: 0.015 | S94: 0.015
B95: Bear | J95: 0.018 | K95: 0.018 | L95: 0.018 | M95: 0.018 | N95: 0.018 | O95: 0.018 | P95: 0.018 | Q95: 0.018 | R95: 0.018 | S95: 0.018
B96: Other drivers (all scenarios)
B97: Accrued expenses % revenue | D97: FY25 7.4% | E97: =Hist!E47/Hist!E7 -> 0.072138777 | F97: =Hist!F47/Hist!F7 -> 0.067348807 | G97: =Hist!G47/Hist!G7 -> 0.072121649 | H97: =Hist!H47/Hist!H7 -> 0.072662153 | I97: =Hist!I47/Hist!I7 -> 0.074482874 | J97: 0.074 | K97: 0.074 | L97: 0.074 | M97: 0.074 | N97: 0.074 | O97: 0.074 | P97: 0.074 | Q97: 0.074 | R97: 0.074 | S97: 0.074
B98: Prepaid & other current assets % revenue | D98: FY25 1.9% | E98: =Hist!E36/Hist!E7 -> 0.015095426 | F98: =Hist!F36/Hist!F7 -> 0.014753649 | G98: =Hist!G36/Hist!G7 -> 0.016707774 | H98: =Hist!H36/Hist!H7 -> 0.017997332 | I98: =Hist!I36/Hist!I7 -> 0.018776448 | J98: 0.019 | K98: 0.019 | L98: 0.019 | M98: 0.019 | N98: 0.019 | O98: 0.019 | P98: 0.019 | Q98: 0.019 | R98: 0.019 | S98: 0.019
B99: Depreciation % beginning net PP&E | D99: FY25 55.7 / 244.3 = 22.8% | F99: =(Hist!F21-Hist!F22)/Hist!E38 -> 0.18120261 | G99: =(Hist!G21-Hist!G22)/Hist!F38 -> 0.17454511 | H99: =(Hist!H21-Hist!H22)/Hist!G38 -> 0.19682353 | I99: =(Hist!I21-Hist!I22)/Hist!H38 -> 0.22801072 | J99: 0.23 | K99: 0.23 | L99: 0.23 | M99: 0.23 | N99: 0.23 | O99: 0.23 | P99: 0.23 | Q99: 0.23 | R99: 0.23 | S99: 0.23
B100: Share-based compensation % revenue | D100: FY23-25 0.7-0.9% | E100: =Hist!E23/Hist!E7 -> 0.016478662 | F100: =Hist!F23/Hist!F7 -> 0.0088053817 | G100: =Hist!G23/Hist!G7 -> 0.0073370656 | H100: =Hist!H23/Hist!H7 -> 0.0080575645 | I100: =Hist!I23/Hist!I7 -> 0.0090829513 | J100: 0.009 | K100: 0.009 | L100: 0.009 | M100: 0.009 | N100: 0.009 | O100: 0.009 | P100: 0.009 | Q100: 0.009 | R100: 0.009 | S100: 0.009
B101: Operating lease liabilities % revenue | D101: FY25 9.5%, rising with DTC stores | E101: =(Hist!E49+Hist!E54)/Hist!E7 -> 0.083067205 | F101: =(Hist!F49+Hist!F54)/Hist!F7 -> 0.076674023 | G101: =(Hist!G49+Hist!G54)/Hist!G7 -> 0.08379781 | H101: =(Hist!H49+Hist!H54)/Hist!H7 -> 0.085799057 | I101: =(Hist!I49+Hist!I54)/Hist!I7 -> 0.094777891 | J101: 0.095 | K101: 0.095 | L101: 0.095 | M101: 0.095 | N101: 0.095 | O101: 0.095 | P101: 0.095 | Q101: 0.095 | R101: 0.095 | S101: 0.095
B102: GAAP effective tax rate | D102: Guided ~23% FY26; includes non-cash IP deferred-tax unwind | E102: =IFERROR(Hist!E17/Hist!E16,"n.m.") -> -0.093161246 | F102: =IFERROR(Hist!F17/Hist!F16,"n.m.") -> 0.24822131 | G102: =IFERROR(Hist!G17/Hist!G16,"n.m.") -> 0.095525134 | H102: =IFERROR(Hist!H17/Hist!H16,"n.m.") -> -0.043363332 | I102: =IFERROR(Hist!I17/Hist!I16,"n.m.") -> 2.1126367 | J102: 0.23 | K102: 0.22 | L102: 0.22 | M102: 0.22 | N102: 0.22 | O102: 0.22 | P102: 0.22 | Q102: 0.22 | R102: 0.22 | S102: 0.22
...

Sheet Rev_Build
B1: Revenue build - brand x region x channel
B2: Crocs, Inc. (NASDAQ: CROX) | US$ millions unless stated
B4: Fiscal year ending 31-Dec | C4: Unit | E4: FY2021A | F4: FY2022A | G4: FY2023A | H4: FY2024A | I4: FY2025A | J4: FY2026E | K4: FY2027E | L4: FY2028E | M4: FY2029E | N4: FY2030E | O4: FY2031E | P4: FY2032E | Q4: FY2033E | R4: FY2034E | S4: FY2035E
B6: Crocs brand
B7: North America - Wholesale | E7: =Hist!E83 -> 674.23 | F7: =Hist!F83 -> 644.215 | G7: =Hist!G83 -> 652.943 | H7: =Hist!H83 -> 644.511 | I7: =Hist!I83 -> 584.677 | J7: =I7*(1+Inputs!J30) -> 526.2093 | K7: =J7*(1+Inputs!K30) -> 510.42302 | L7: =K7*(1+Inputs!L30) -> 510.42302 | M7: =L7*(1+Inputs!M30) -> 515.52725 | N7: =M7*(1+Inputs!N30) -> 525.8378 | O7: =N7*(1+Inputs!O30) -> 536.88039 | P7: =O7*(1+Inputs!P30) -> 548.69176 | Q7: =P7*(1+Inputs!Q30) -> 561.31167 | ... S7: =R7*(1+Inputs!S30) -> 589.15273
B8: growth | F8: =IFERROR(F7/E7-1,"n.m.") -> -0.04451745 | G8: =IFERROR(G7/F7-1,"n.m.") -> 0.013548272 | H8: =IFERROR(H7/G7-1,"n.m.") -> -0.012913838 | I8: =IFERROR(I7/H7-1,"n.m.") -> -0.092836274 | J8: =Inputs!J30 -> -0.1 | K8: =Inputs!K30 -> -0.03 | L8: =Inputs!L30 -> 0 | M8: =Inputs!M30 -> 0.01 | N8: =Inputs!N30 -> 0.02 | O8: =Inputs!O30 -> 0.021 | P8: =Inputs!P30 -> 0.022 | Q8: =Inputs!Q30 -> 0.023 | ... S8: =Inputs!S30 -> 0.025
B9: North America - DTC | E9: =Hist!E84 -> 879.748 | F9: =Hist!F84 -> 1000.441 | G9: =Hist!G84 -> 1124.942 | H9: =Hist!H84 -> 1188.911 | I9: =Hist!I84 -> 1124.958 | J9: =I9*(1+Inputs!J34) -> 1158.7067 | K9: =J9*(1+Inputs!K34) -> 1193.4679 | L9: =K9*(1+Inputs!L34) -> 1229.272 | M9: =L9*(1+Inputs!M34) -> 1266.1501 | N9: =M9*(1+Inputs!N34) -> 1304.1346 | O9: =N9*(1+Inputs!O34) -> 1341.9545 | P9: =O9*(1+Inputs!P34) -> 1379.5293 | Q9: =P9*(1+Inputs!Q34) -> 1416.7766 | ... S9: =R9*(1+Inputs!S34) -> 1489.9531
B10: growth | F10: =IFERROR(F9/E9-1,"n.m.") -> 0.13719042 | G10: =IFERROR(G9/F9-1,"n.m.") -> 0.12444612 | H10: =IFERROR(H9/G9-1,"n.m.") -> 0.056864265 | I10: =IFERROR(I9/H9-1,"n.m.") -> -0.053791243 | J10: =Inputs!J34 -> 0.03 | K10: =Inputs!K34 -> 0.03 | L10: =Inputs!L34 -> 0.03 | M10: =Inputs!M34 -> 0.03 | N10: =Inputs!N34 -> 0.03 | O10: =Inputs!O34 -> 0.029 | P10: =Inputs!P34 -> 0.028 | Q10: =Inputs!Q34 -> 0.027 | ... S10: =Inputs!S34 -> 0.025
B11: International - Wholesale | E11: =Hist!E85 -> 499.851 | F11: =Hist!F85 -> 733.087 | G11: =Hist!G85 -> 840.594 | H11: =Hist!H85 -> 963.035 | I11: =Hist!I85 -> 1014.697 | J11: =I11*(1+Inputs!J38) -> 1014.697 | K11: =J11*(1+Inputs!K38) -> 1055.2849 | L11: =K11*(1+Inputs!L38) -> 1108.0491 | M11: =L11*(1+Inputs!M38) -> 1163.4516 | N11: =M11*(1+Inputs!N38) -> 1209.9896 | O11: =N11*(1+Inputs!O38) -> 1255.9692 | P11: =O11*(1+Inputs!P38) -> 1301.1841 | Q11: =P11*(1+Inputs!Q38) -> 1345.4244 | ... S11: =R11*(1+Inputs!S38) -> 1430.1323
B12: growth | F12: =IFERROR(F11/E11-1,"n.m.") -> 0.46661105 | G12: =IFERROR(G11/F11-1,"n.m.") -> 0.14664972 | H12: =IFERROR(H11/G11-1,"n.m.") -> 0.14566009 | I12: =IFERROR(I11/H11-1,"n.m.") -> 0.053644987 | J12: =Inputs!J38 -> 0 | K12: =Inputs!K38 -> 0.04 | L12: =Inputs!L38 -> 0.05 | M12: =Inputs!M38 -> 0.05 | N12: =Inputs!N38 -> 0.04 | O12: =Inputs!O38 -> 0.038 | P12: =Inputs!P38 -> 0.036 | Q12: =Inputs!Q38 -> 0.034 | ... S12: =Inputs!S38 -> 0.03
B13: International - DTC | E13: =Hist!E86 -> 259.587 | F13: =Hist!F86 -> 281.382 | G13: =Hist!G86 -> 394.475 | H13: =Hist!H86 -> 481.51 | I13: =Hist!I86 -> 601.475 | J13: =I13*(1+Inputs!J42) -> 709.7405 | K13: =J13*(1+Inputs!K42) -> 794.90936 | L13: =K13*(1+Inputs!L42) -> 874.4003 | M13: =L13*(1+Inputs!M42) -> 944.35232 | N13: =M13*(1+Inputs!N42) -> 1010.457 | O13: =N13*(1+Inputs!O42) -> 1074.1158 | P13: =O13*(1+Inputs!P42) -> 1134.2663 | Q13: =P13*(1+Inputs!Q42) -> 1189.8453 | ... S13: =R13*(1+Inputs!S42) -> 1283.2125
B14: growth | F14: =IFERROR(F13/E13-1,"n.m.") -> 0.083960291 | G14: =IFERROR(G13/F13-1,"n.m.") -> 0.40191981 | H14: =IFERROR(H13/G13-1,"n.m.") -> 0.22063502 | I14: =IFERROR(I13/H13-1,"n.m.") -> 0.24914332 | J14: =Inputs!J42 -> 0.18 | K14: =Inputs!K42 -> 0.12 | L14: =Inputs!L42 -> 0.1 | M14: =Inputs!M42 -> 0.08 | N14: =Inputs!N42 -> 0.07 | O14: =Inputs!O42 -> 0.063 | P14: =Inputs!P42 -> 0.056 | Q14: =Inputs!Q42 -> 0.049 | ... S14: =Inputs!S42 -> 0.035
B15: Crocs North America | E15: =E7+E9 -> 1553.978 | F15: =F7+F9 -> 1644.656 | G15: =G7+G9 -> 1777.885 | H15: =H7+H9 -> 1833.422 | I15: =I7+I9 -> 1709.635 | J15: =J7+J9 -> 1684.916 | K15: =K7+K9 -> 1703.891 | L15: =L7+L9 -> 1739.695 | ... S15: =S7+S9 -> 2079.1058
B16: Crocs International | E16: =E11+E13 -> 759.438 | F16: =F11+F13 -> 1014.469 | G16: =G11+G13 -> 1235.069 | H16: =H11+H13 -> 1444.545 | I16: =I11+I13 -> 1616.172 | J16: =J11+J13 -> 1724.4375 | K16: =K11+K13 -> 1850.1942 | L16: =L11+L13 -> 1982.4494 | ... S16: =S11+S13 -> 2713.3448
B17: Crocs brand revenue | E17: =E15+E16 -> 2313.416 | F17: =F15+F16 -> 2659.125 | G17: =G15+G16 -> 3012.954 | H17: =H15+H16 -> 3277.967 | I17: =I15+I16 -> 3325.807 | J17: =J15+J16 -> 3409.3535 | K17: =K15+K16 -> 3554.0852 | L17: =L15+L16 -> 3722.1444 | ... S17: =S15+S16 -> 4792.4506
B18: growth | F18: =IFERROR(F17/E17-1,"n.m.") -> 0.14943659 | G18: =IFERROR(G17/F17-1,"n.m.") -> 0.13306219 | H18: =IFERROR(H17/G17-1,"n.m.") -> 0.087957865 | I18: =IFERROR(I17/H17-1,"n.m.") -> 0.014594412 | J18: =J17/I17-1 -> 0.025120682 | K18: =K17/J17-1 -> 0.042451351 | L18: =L17/K17-1 -> 0.04728621 | M18: =M17/L17-1 -> 0.044957114 | N18: =N17/M17-1 -> 0.041377696 | O18: =O17/N17-1 -> 0.039131974 | P18: =P17/O17-1 -> 0.036767502 | Q18: =Q17/P17-1 -> 0.034302882 | ... S18: =S17/R17-1 -> 0.029153286
B19: HEYDUDE brand
B20: Wholesale | E20: =Hist!E87 -> 0 | F20: =Hist!F87 -> 574.14 | G20: =Hist!G87 -> 566.937 | H20: =Hist!H87 -> 456.472 | I20: =Hist!I87 -> 336.325 | J20: =I20*(1+Inputs!J46) -> 285.87625 | K20: =J20*(1+Inputs!K46) -> 268.72367 | L20: =K20*(1+Inputs!L46) -> 263.3492 | M20: =L20*(1+Inputs!M46) -> 265.98269 | N20: =M20*(1+Inputs!N46) -> 271.30235 | O20: =N20*(1+Inputs!O46) -> 276.9997 | P20: =O20*(1+Inputs!P46) -> 283.09369 | Q20: =P20*(1+Inputs!Q46) -> 289.60484 | ... S20: =R20*(1+Inputs!S46) -> 303.96925
B21: growth | F21: =IFERROR(F20/E20-1,"n.m.") -> n.m. | G21: =IFERROR(G20/F20-1,"n.m.") -> -0.012545721 | H21: =IFERROR(H20/G20-1,"n.m.") -> -0.19484528 | I21: =IFERROR(I20/H20-1,"n.m.") -> -0.26320782 | J21: =Inputs!J46 -> -0.15 | K21: =Inputs!K46 -> -0.06 | L21: =Inputs!L46 -> -0.02 | M21: =Inputs!M46 -> 0.01 | N21: =Inputs!N46 -> 0.02 | O21: =Inputs!O46 -> 0.021 | P21: =Inputs!P46 -> 0.022 | Q21: =Inputs!Q46 -> 0.023 | ... S21: =Inputs!S46 -> 0.025
B22: DTC | E22: =Hist!E88 -> 0 | F22: =Hist!F88 -> 321.72 | G22: =Hist!G88 -> 382.456 | H22: =Hist!H88 -> 367.669 | I22: =Hist!I88 -> 378.515 | J22: =I22*(1+Inputs!J50) -> 408.7962 | K22: =J22*(1+Inputs!K50) -> 425.14805 | L22: =K22*(1+Inputs!L50) -> 437.90249 | M22: =L22*(1+Inputs!M50) -> 450.7269 | N22: =M22*(1+Inputs!N50) -> 463.60462 | O22: =N22*(1+Inputs!O50) -> 476.51925 | P22: =O22*(1+Inputs!P50) -> 489.45342 | Q22: =P22*(1+Inputs!Q50) -> 502.38918 | ... S22: =R22*(1+Inputs!S50) -> 528.19031
B23: growth | F23: =IFERROR(F22/E22-1,"n.m.") -> n.m. | G23: =IFERROR(G22/F22-1,"n.m.") -> 0.18878528 | H23: =IFERROR(H22/G22-1,"n.m.") -> -0.038663271 | I23: =IFERROR(I22/H22-1,"n.m.") -> 0.029499359 | J23: =Inputs!J50 -> 0.08 | K23: =Inputs!K50 -> 0.04 | L23: =Inputs!L50 -> 0.03 | M23: =Inputs!M50 -> 0.029286 | N23: =Inputs!N50 -> 0.028571 | O23: =Inputs!O50 -> 0.027857 | P23: =Inputs!P50 -> 0.027143 | Q23: =Inputs!Q50 -> 0.026429 | ... S23: =Inputs!S50 -> 0.025
B24: HEYDUDE revenue | E24: =E20+E22 -> 0 | F24: =F20+F22 -> 895.86 | G24: =G20+G22 -> 949.393 | H24: =H20+H22 -> 824.141 | I24: =I20+I22 -> 714.84 | J24: =J20+J22 -> 694.67245 | K24: =K20+K22 -> 693.87172 | L24: =L20+L22 -> 701.25169 | ... S24: =S20+S22 -> 832.15955
B25: growth | G25: =IFERROR(G24/F24-1,"n.m.") -> 0.059755989 | H25: =IFERROR(H24/G24-1,"n.m.") -> -0.13192851 | I25: =IFERROR(I24/H24-1,"n.m.") -> -0.13262415 | J25: =J24/I24-1 -> -0.028212677 | K25: =K24/J24-1 -> -0.0011526684 | L25: =L24/K24-1 -> 0.010635925 | M25: =M24/L24-1 -> 0.022043304 | N25: =N24/M24-1 -> 0.025390161 | O25: =O24/N24-1 -> 0.025325632 | P25: =P24/O24-1 -> 0.025252391 | Q25: =Q24/P24-1 -> 0.02517247 | ... S25: =S24/R24-1 -> 0.025
B26: Consolidated
B27: Total revenue | E27: =E17+E24 -> 2313.416 | F27: =F17+F24 -> 3554.985 | G27: =G17+G24 -> 3962.347 | H27: =H17+H24 -> 4102.108 | I27: =I17+I24 -> 4040.647 | J27: =J17+J24 -> 4104.026 | K27: =K17+K24 -> 4247.9569 | L27: =L17+L24 -> 4423.3961 | ... S27: =S17+S24 -> 5624.6101
B28: growth | F28: =IFERROR(F27/E27-1,"n.m.") -> 0.53668212 | G28: =IFERROR(G27/F27-1,"n.m.") -> 0.11458895 | H28: =IFERROR(H27/G27-1,"n.m.") -> 0.035272277 | I28: =IFERROR(I27/H27-1,"n.m.") -> -0.014982784 | J28: =J27/I27-1 -> 0.015685357 | K28: =K27/J27-1 -> 0.035070669 | L28: =L27/K27-1 -> 0.041299662 | M28: =M27/L27-1 -> 0.041324532 | N28: =N27/M27-1 -> 0.038890083 | O28: =O27/N27-1 -> 0.037011664 | P28: =P27/O27-1 -> 0.035018996 | Q28: =Q27/P27-1 -> 0.032929562 | ... S28: =S27/R27-1 -> 0.028536689
B29: Direct-to-consumer revenue | E29: =E9+E13+E22 -> 1139.335 | F29: =F9+F13+F22 -> 1603.543 | G29: =G9+G13+G22 -> 1901.873 | H29: =H9+H13+H22 -> 2038.09 | I29: =I9+I13+I22 -> 2104.948 | J29: =J9+J13+J22 -> 2277.2434 | K29: =K9+K13+K22 -> 2413.5254 | L29: =L9+L13+L22 -> 2541.5748 | ... S29: =S9+S13+S22 -> 3301.3558
B30: DTC share of revenue | E30: =E29/E27 -> 0.49249033 | F30: =F29/F27 -> 0.45106885 | G30: =G29/G27 -> 0.47998648 | H30: =H29/H27 -> 0.49683967 | I30: =I29/I27 -> 0.5209433 | J30: =J29/J27 -> 0.55488037 | K30: =K29/K27 -> 0.56816145 | L30: =L29/L27 -> 0.57457544 | ... S30: =S29/S27 -> 0.58694839
B31: Crocs International share of Crocs brand | E31: =E16/E17 -> 0.32827559 | F31: =F16/F17 -> 0.38150482 | G31: =G16/G17 -> 0.40991963 | H31: =H16/H17 -> 0.4406832 | I31: =I16/I17 -> 0.48594882 | J31: =J16/J17 -> 0.50579603 | K31: =K16/K17 -> 0.52058241 | L31: =L16/L17 -> 0.53260948 | ... S31: =S16/S17 -> 0.56617063
B32: HEYDUDE share of revenue | E32: =E24/E27 -> 0 | F32: =F24/F27 -> 0.25200106 | G32: =G24/G27 -> 0.2396037 | H32: =H24/H27 -> 0.2009067 | I32: =I24/I27 -> 0.17691226 | J32: =J24/J27 -> 0.16926609 | K32: =K24/K27 -> 0.16334246 | L32: =L24/L27 -> 0.15853242 | ... S32: =S24/S27 -> 0.14794973
B33: Cross-check: units x ASP (footwear only)
B34: Crocs footwear ASP (US$) | E34: =Hist!E101 -> 22.27 | F34: =Hist!F101 -> 22.72 | G34: =Hist!G101 -> 24.92 | H34: =Hist!H101 -> 25.52 | I34: =Hist!I101 -> 25.4 | J34: =I34*(1+Inputs!J107) -> 25.908 | K34: =J34*(1+Inputs!K107) -> 26.42616 | L34: =K34*(1+Inputs!L107) -> 26.954683 | M34: =L34*(1+Inputs!M107) -> 27.493777 | N34: =M34*(1+Inputs!N107) -> 28.043652 | O34: =N34*(1+Inputs!O107) -> 28.604525 | P34: =O34*(1+Inputs!P107) -> 29.176616 | Q34: =P34*(1+Inputs!Q107) -> 29.760148 | ... S34: =R34*(1+Inputs!S107) -> 30.962458
B35: Crocs footwear share of brand revenue | E35: =Hist!E100*Hist!E101/E17 -> 0.99115928 | F35: =Hist!F100*Hist!F101/F17 -> 0.9873465 | G35: =Hist!G100*Hist!G101/G17 -> 0.98901571 | H35: =Hist!H100*Hist!H101/H17 -> 0.98873479 | I35: =Hist!I100*Hist!I101/I17 -> 0.98473098 | J35: =$I$35 -> 0.98473098 | K35: =$I$35 -> 0.98473098 | L35: =$I$35 -> 0.98473098 | M35: =$I$35 -> 0.98473098 | N35: =$I$35 -> 0.98473098 | O35: =$I$35 -> 0.98473098 | P35: =$I$35 -> 0.98473098 | Q35: =$I$35 -> 0.98473098 | ... S35: =$I$35 -> 0.98473098
B36: Crocs implied footwear units (m pairs) | E36: =Hist!E100 -> 102.962 | F36: =Hist!F100 -> 115.558 | G36: =Hist!G100 -> 119.577 | H36: =Hist!H100 -> 127 | I36: =Hist!I100 -> 128.938 | J36: =J17*J35/J34 -> 129.5853 | K36: =K17*K35/K34 -> 132.43762 | L36: =L17*L35/L34 -> 135.98049 | M36: =M17*M35/M34 -> 139.30762 | N36: =N17*N35/N34 -> 142.22731 | O36: =O17*O35/O34 -> 144.89504 | P36: =P17*P35/P34 -> 147.27693 | Q36: =Q17*Q35/Q34 -> 149.34211 | ... S36: =S17*S35/S34 -> 152.41925
B37: implied unit growth | F37: =IFERROR(F36/E36-1,"n.m.") -> 0.1223364 | G37: =IFERROR(G36/F36-1,"n.m.") -> 0.034779072 | H37: =IFERROR(H36/G36-1,"n.m.") -> 0.062077155 | I37: =IFERROR(I36/H36-1,"n.m.") -> 0.015259843 | J37: =J36/I36-1 -> 0.0050202765 | K37: =K36/J36-1 -> 0.022011128 | L37: =L36/K36-1 -> 0.026751186 | M37: =M36/L36-1 -> 0.024467758 | N37: =N36/M36-1 -> 0.020958526 | O37: =O36/N36-1 -> 0.018756838 | P37: =P36/O36-1 -> 0.016438727 | Q37: =Q36/P36-1 -> 0.014022434 | ... S37: =S36/R36-1 -> 0.0089738101
B38: HEYDUDE footwear ASP (US$) | F38: =Hist!F103 -> 29.35 | G38: =Hist!G103 -> 28.8 | H38: =Hist!H103 -> 30.54 | I38: =Hist!I103 -> 31.67 | J38: =I38*(1+Inputs!J108) -> 31.9867 | K38: =J38*(1+Inputs!K108) -> 32.306567 | L38: =K38*(1+Inputs!L108) -> 32.629633 | M38: =L38*(1+Inputs!M108) -> 32.955929 | N38: =M38*(1+Inputs!N108) -> 33.285488 | O38: =N38*(1+Inputs!O108) -> 33.618343 | P38: =O38*(1+Inputs!P108) -> 33.954527 | Q38: =P38*(1+Inputs!Q108) -> 34.294072 | ... S38: =R38*(1+Inputs!S108) -> 34.983383
B39: HEYDUDE footwear share of brand revenue | F39: =Hist!F102*Hist!F103/F24 -> 0.99985785 | G39: =Hist!G102*Hist!G103/G24 -> 1.0001203 | H39: =Hist!H102*Hist!H103/H24 -> 0.99867984 | I39: =Hist!I102*Hist!I103/I24 -> 0.9949264 | J39: =$I$39 -> 0.9949264 | K39: =$I$39 -> 0.9949264 | L39: =$I$39 -> 0.9949264 | M39: =$I$39 -> 0.9949264 | N39: =$I$39 -> 0.9949264 | O39: =$I$39 -> 0.9949264 | P39: =$I$39 -> 0.9949264 | Q39: =$I$39 -> 0.9949264 | ... S39: =$I$39 -> 0.9949264
B40: HEYDUDE implied footwear units (m pairs) | F40: =Hist!F102 -> 30.519 | G40: =Hist!G102 -> 32.969 | H40: =Hist!H102 -> 26.95 | I40: =Hist!I102 -> 22.457 | J40: =J24*J39/J38 -> 21.607354 | K40: =K24*K39/K38 -> 21.368761 | L40: =L24*L39/L38 -> 21.382215 | M40: =M24*M39/M38 -> 21.637178 | N40: =N24*N39/N38 -> 21.966881 | O40: =O24*O39/O38 -> 22.300204 | P40: =P24*P39/P38 -> 22.636967 | Q40: =Q24*Q39/Q38 -> 22.977026 | ... S40: =S24*S39/S38 -> 23.666594
B41: implied unit growth | G41: =IFERROR(G40/F40-1,"n.m.") -> 0.08027786 | H41: =IFERROR(H40/G40-1,"n.m.") -> -0.18256544 | I41: =IFERROR(I40/H40-1,"n.m.") -> -0.16671614 | J41: =J40/I40-1 -> -0.037834334 | K41: =K40/J40-1 -> -0.011042246 | L41: =L40/K40-1 -> 0.00062962919 | M41: =M40/L40-1 -> 0.011924064 | N41: =N40/M40-1 -> 0.015237783 | O41: =O40/N40-1 -> 0.015173893 | P41: =P40/O40-1 -> 0.015101378 | Q41: =Q40/P40-1 -> 0.015022248 | ... S41: =S40/R40-1 -> 0.014851485

Sheet IS
B1: Income statement
B2: Crocs, Inc. (NASDAQ: CROX) | US$ millions unless stated
B4: Fiscal year ending 31-Dec | C4: Unit | E4: FY2021A | F4: FY2022A | G4: FY2023A | H4: FY2024A | I4: FY2025A | J4: FY2026E | K4: FY2027E | L4: FY2028E | M4: FY2029E | N4: FY2030E | O4: FY2031E | P4: FY2032E | Q4: FY2033E | R4: FY2034E | S4: FY2035E
B6: Profit & loss
B7: Revenue | E7: =Rev_Build!E27 -> 2313.416 | F7: =Rev_Build!F27 -> 3554.985 | G7: =Rev_Build!G27 -> 3962.347 | H7: =Rev_Build!H27 -> 4102.108 | I7: =Rev_Build!I27 -> 4040.647 | J7: =Rev_Build!J27 -> 4104.026 | K7: =Rev_Build!K27 -> 4247.9569 | L7: =Rev_Build!L27 -> 4423.3961 | ... S7: =Rev_Build!S27 -> 5624.6101
B8: growth | F8: =IFERROR(F7/E7-1,"n.m.") -> 0.53668212 | G8: =IFERROR(G7/F7-1,"n.m.") -> 0.11458895 | H8: =IFERROR(H7/G7-1,"n.m.") -> 0.035272277 | I8: =IFERROR(I7/H7-1,"n.m.") -> -0.014982784 | J8: =J7/I7-1 -> 0.015685357 | K8: =K7/J7-1 -> 0.035070669 | L8: =L7/K7-1 -> 0.041299662 | M8: =M7/L7-1 -> 0.041324532 | N8: =N7/M7-1 -> 0.038890083 | O8: =O7/N7-1 -> 0.037011664 | P8: =P7/O7-1 -> 0.035018996 | Q8: =Q7/P7-1 -> 0.032929562 | ... S8: =S7/R7-1 -> 0.028536689
B9: Cost of sales | E9: =Hist!E8 -> 893.196 | F9: =Hist!F8 -> 1694.703 | G9: =Hist!G8 -> 1752.337 | H9: =Hist!H8 -> 1691.85 | I9: =Hist!I8 -> 1683.592 | J9: =Rev_Build!J17*(1-Inputs!J55)+Rev_Build!J24*(1-Inputs!J59) -> 1732.5579 | K9: =Rev_Build!K17*(1-Inputs!K55)+Rev_Build!K24*(1-Inputs!K59) -> 1781.6001 | L9: =Rev_Build!L17*(1-Inputs!L55)+Rev_Build!L24*(1-Inputs!L59) -> 1844.3373 | M9: =Rev_Build!M17*(1-Inputs!M55)+Rev_Build!M24*(1-Inputs!M59) -> 1918.2551 | N9: =Rev_Build!N17*(1-Inputs!N55)+Rev_Build!N24*(1-Inputs!N59) -> 1991.2113 | O9: =Rev_Build!O17*(1-Inputs!O55)+Rev_Build!O24*(1-Inputs!O59) -> 2063.4494 | P9: =Rev_Build!P17*(1-Inputs!P55)+Rev_Build!P24*(1-Inputs!P59) -> 2134.4582 | Q9: =Rev_Build!Q17*(1-Inputs!Q55)+Rev_Build!Q24*(1-Inputs!Q59) -> 2203.7263 | ... S9: =Rev_Build!S17*(1-Inputs!S55)+Rev_Build!S24*(1-Inputs!S59) -> 2335.0651
B10: Gross profit | E10: =E7-E9 -> 1420.22 | F10: =F7-F9 -> 1860.282 | G10: =G7-G9 -> 2210.01 | H10: =H7-H9 -> 2410.258 | I10: =I7-I9 -> 2357.055 | J10: =J7-J9 -> 2371.4681 | K10: =K7-K9 -> 2466.3568 | L10: =L7-L9 -> 2579.0588 | ... S10: =S7-S9 -> 3289.5451
B11: gross margin | E11: =E10/E7 -> 0.61390602 | F11: =F10/F7 -> 0.52328828 | G11: =G10/G7 -> 0.55775277 | H11: =H10/H7 -> 0.58756571 | I11: =I10/I7 -> 0.58333604 | J11: =J10/J7 -> 0.57783944 | K11: =K10/K7 -> 0.58059836 | L11: =L10/L7 -> 0.58304949 | ... S11: =S10/S7 -> 0.58484855
B12: SG&A (incl. restructuring charges) | E12: =Hist!E10 -> 737.156 | F12: =Hist!F10 -> 1009.526 | G12: =Hist!G10 -> 1163.94 | H12: =Hist!H10 -> 1364.265 | I12: =Hist!I10 -> 1469.425 | J12: =J27+J28+J29+J30 -> 1478.7201 | K12: =K27+K28+K29+K30 -> 1512.7879 | L12: =L27+L28+L29+L30 -> 1566.0162 | M12: =M27+M28+M29+M30 -> 1621.6434 | N12: =N27+N28+N29+N30 -> 1679.223 | O12: =O27+O28+O29+O30 -> 1740.9873 | P12: =P27+P28+P29+P30 -> 1801.6238 | Q12: =Q27+Q28+Q29+Q30 -> 1860.6808 | ... S12: =S27+S28+S29+S30 -> 1972.3131
B13: % revenue | E13: =E12/E7 -> 0.31864394 | F13: =F12/F7 -> 0.28397476 | G13: =G12/G7 -> 0.29375014 | H13: =H12/H7 -> 0.33257657 | I13: =I12/I7 -> 0.36366082 | J13: =J12/J7 -> 0.36030964 | K13: =K12/K7 -> 0.3561213 | L13: =L12/L7 -> 0.35403029 | ... S13: =S12/S7 -> 0.35065774
B14: Asset impairments | E14: =Hist!E11 -> 0 | F14: =Hist!F11 -> 0 | G14: =Hist!G11 -> 9.287 | H14: =Hist!H11 -> 24.081 | I14: =Hist!I11 -> 738.115 | J14: 0 | K14: 0 | L14: 0 | M14: 0 | N14: 0 | O14: 0 | P14: 0 | Q14: 0 | R14: 0 | S14: 0
B15: Operating income (EBIT) | E15: =E10-E12-E14 -> 683.064 | F15: =F10-F12-F14 -> 850.756 | G15: =G10-G12-G14 -> 1036.783 | H15: =H10-H12-H14 -> 1021.912 | I15: =I10-I12-I14 -> 149.515 | J15: =J10-J12-J14 -> 892.74798 | K15: =K10-K12-K14 -> 953.56887 | L15: =L10-L12-L14 -> 1013.0426 | ... S15: =S10-S12-S14 -> 1317.232
B16: EBIT margin | E16: =E15/E7 -> 0.29526207 | F16: =F15/F7 -> 0.23931353 | G16: =G15/G7 -> 0.26165881 | H16: =H15/H7 -> 0.24911875 | I16: =I15/I7 -> 0.037002737 | J16: =J15/J7 -> 0.21752981 | K16: =K15/K7 -> 0.22447706 | L16: =L15/L7 -> 0.2290192 | ... S16: =S15/S7 -> 0.23419081
B17: Interest income | E17: =Hist!E13 -> 0.775 | F17: =Hist!F13 -> 1.02 | G17: =Hist!G13 -> 2.406 | H17: =Hist!H13 -> 3.484 | I17: =Hist!I13 -> 1.844 | J17: =Debt!J52 -> 4.20531 | K17: =Debt!K52 -> 4.5 | L17: =Debt!L52 -> 4.5 | M17: =Debt!M52 -> 5.5321816 | N17: =Debt!N52 -> 5.5321816 | O17: =Debt!O52 -> 4.5 | P17: =Debt!P52 -> 4.5 | Q17: =Debt!Q52 -> 4.5 | ... S17: =Debt!S52 -> 4.5
B18: Interest expense | E18: =Hist!E14 -> 21.647 | F18: =Hist!F14 -> 136.158 | G18: =Hist!G14 -> 161.351 | H18: =Hist!H14 -> 109.264 | I18: =Hist!I14 -> 88.287 | J18: =Debt!J51 -> 69.961564 | K18: =Debt!K51 -> 60.851325 | L18: =Debt!L51 -> 50.973028 | M18: =Debt!M51 -> 41.060462 | N18: =Debt!N51 -> 36.5625 | O18: =Debt!O51 -> 39.40625 | P18: =Debt!P51 -> 42.25 | Q18: =Debt!Q51 -> 42.25 | ... S18: =Debt!S51 -> 42.25
B19: Other non-operating income (incl. FX) | E19: =Hist!E15 -> 1.657 | F19: =Hist!F15 -> 2.89 | G19: =Hist!G15 -> -1.566 | H19: =Hist!H15 -> -5.546 | I19: =Hist!I15 -> 9.906 | J19: 0 | K19: 0 | L19: 0 | M19: 0 | N19: 0 | O19: 0 | P19: 0 | Q19: 0 | R19: 0 | S19: 0
B20: Pre-tax income | E20: =E15+E17-E18+E19 -> 663.849 | F20: =F15+F17-F18+F19 -> 718.508 | G20: =G15+G17-G18+G19 -> 876.272 | H20: =H15+H17-H18+H19 -> 910.586 | I20: =I15+I17-I18+I19 -> 72.978 | J20: =J15+J17-J18+J19 -> 826.99173 | K20: =K15+K17-K18+K19 -> 897.21754 | L20: =L15+L17-L18+L19 -> 966.5696 | ... S20: =S15+S17-S18+S19 -> 1279.482
B21: Income tax expense / (benefit) | E21: =Hist!E17 -> -61.845 | F21: =Hist!F17 -> 178.349 | G21: =Hist!G17 -> 83.706 | H21: =Hist!H17 -> -39.486 | I21: =Hist!I17 -> 154.176 | J21: =Tax!J8 -> 190.2081 | K21: =Tax!K8 -> 197.38786 | L21: =Tax!L8 -> 212.64531 | M21: =Tax!M8 -> 226.7681 | N21: =Tax!N8 -> 238.44951 | O21: =Tax!O8 -> 247.0811 | P21: =Tax!P8 -> 255.72503 | Q21: =Tax!Q8 -> 264.70288 | ... S21: =Tax!S8 -> 281.48604
B22: effective tax rate | E22: =IFERROR(E21/E20,"n.m.") -> -0.093161246 | F22: =IFERROR(F21/F20,"n.m.") -> 0.24822131 | G22: =IFERROR(G21/G20,"n.m.") -> 0.095525134 | H22: =IFERROR(H21/H20,"n.m.") -> -0.043363285 | I22: =IFERROR(I21/I20,"n.m.") -> 2.1126367 | J22: =J21/J20 -> 0.23 | K22: =K21/K20 -> 0.22 | L22: =L21/L20 -> 0.22 | M22: =M21/M20 -> 0.22 | N22: =N21/N20 -> 0.22 | O22: =O21/O20 -> 0.22 | P22: =P21/P20 -> 0.22 | Q22: =Q21/Q20 -> 0.22 | ... S22: =S21/S20 -> 0.22
B23: Net income | E23: =E20-E21 -> 725.694 | F23: =F20-F21 -> 540.159 | G23: =G20-G21 -> 792.566 | H23: =H20-H21 -> 950.072 | I23: =I20-I21 -> -81.198 | J23: =J20-J21 -> 636.78363 | K23: =K20-K21 -> 699.82968 | L23: =L20-L21 -> 753.92429 | ... S23: =S20-S21 -> 997.99596
B24: Diluted weighted-average shares (m) | E24: =Hist!E19 -> 63.718 | F24: =Hist!F19 -> 62.006 | G24: =Hist!G19 -> 61.952 | H24: =Hist!H19 -> 59.832 | I24: =Hist!I19 -> 54.208 | J24: =Equity!J20 -> 48.344673 | K24: =Equity!K20 -> 43.966801 | L24: =Equity!L20 -> 39.93889 | M24: =Equity!M20 -> 36.359366 | N24: =Equity!N20 -> 32.642195 | O24: =Equity!O20 -> 28.951515 | P24: =Equity!P20 -> 25.866868 | Q24: =Equity!Q20 -> 23.166982 | ... S24: =Equity!S20 -> 18.718461
B25: Diluted EPS (US$) | E25: =E23/E24 -> 11.389152 | F25: =F23/F24 -> 8.7113989 | G25: =G23/G24 -> 12.793227 | H25: =H23/H24 -> 15.878995 | I25: =I23/I24 -> -1.497897 | J25: =J23/J24 -> 13.171743 | K25: =K23/K24 -> 15.91723 | L25: =L23/L24 -> 18.876946 | ... S25: =S23/S24 -> 53.316132
B26: SG&A build (forecast)
B27: Crocs brand SG&A | E27: =Hist!E92 -> 0 | F27: =Hist!F92 -> 645.726 | G27: =Hist!G92 -> 727.954 | H27: =Hist!H92 -> 837.228 | I27: =Hist!I92 -> 926.681 | J27: =Rev_Build!J17*Inputs!J63 -> 937.57222 | K27: =Rev_Build!K17*Inputs!K63 -> 972.93082 | L27: =Rev_Build!L17*Inputs!L63 -> 1014.2844 | M27: =Rev_Build!M17*Inputs!M63 -> 1055.0218 | N27: =Rev_Build!N17*Inputs!N63 -> 1093.6131 | O27: =Rev_Build!O17*Inputs!O63 -> 1136.4084 | P27: =Rev_Build!P17*Inputs!P63 -> 1178.1913 | Q27: =Rev_Build!Q17*Inputs!Q63 -> 1218.6066 | ... S27: =Rev_Build!S17*Inputs!S63 -> 1293.9617
B28: HEYDUDE SG&A | E28: =Hist!E96 -> 0 | F28: =Hist!F96 -> 154.44 | G28: =Hist!G96 -> 205.593 | H28: =Hist!H96 -> 250.406 | I28: =Hist!I96 -> 251.89 | J28: =Rev_Build!J24*Inputs!J67 -> 229.24191 | K28: =Rev_Build!K24*Inputs!K67 -> 225.50831 | L28: =Rev_Build!L24*Inputs!L67 -> 224.40054 | M28: =Rev_Build!M24*Inputs!M67 -> 225.76352 | N28: =Rev_Build!N24*Inputs!N67 -> 231.49569 | O28: =Rev_Build!O24*Inputs!O67 -> 237.35847 | P28: =Rev_Build!P24*Inputs!P67 -> 243.35234 | Q28: =Rev_Build!Q24*Inputs!Q67 -> 249.47812 | ... S28: =Rev_Build!S24*Inputs!S67 -> 262.13026
B29: Corporate / unallocated | J29: =J7*Inputs!J71 -> 287.28182 | K29: =K7*Inputs!K71 -> 297.35698 | L29: =L7*Inputs!L71 -> 309.63773 | M29: =M7*Inputs!M71 -> 322.43336 | N29: =N7*Inputs!N71 -> 334.97282 | O29: =O7*Inputs!O71 -> 347.37072 | P29: =P7*Inputs!P71 -> 359.5353 | Q29: =Q7*Inputs!Q71 -> 371.37464 | ... S29: =S7*Inputs!S71 -> 393.72271
B30: Restructuring & other charges (recurring) | E30: =Hist!E29-Hist!E28 -> 5.836 | F30: =Hist!F29-Hist!F28 -> 35.141 | G30: =Hist!G29-Hist!G28 -> 49.542 | H30: =Hist!H29-Hist!H28 -> 4.266 | I30: =Hist!I29-Hist!I28 -> 13.037 | J30: =J7*Inputs!J75 -> 24.624156 | K30: =K7*Inputs!K75 -> 16.991828 | L30: =L7*Inputs!L75 -> 17.693584 | M30: =M7*Inputs!M75 -> 18.424764 | N30: =N7*Inputs!N75 -> 19.141304 | O30: =O7*Inputs!O75 -> 19.849756 | P30: =P7*Inputs!P75 -> 20.544874 | Q30: =Q7*Inputs!Q75 -> 21.221408 | ... S30: =S7*Inputs!S75 -> 22.498441
B31: Adjusted metrics & EBITDA
B32: Depreciation & amortisation | E32: =Hist!E21 -> 31.976 | F32: =Hist!F21 -> 39.229 | G32: =Hist!G21 -> 54.304 | H32: =Hist!H21 -> 69.84 | I32: =Hist!I21 -> 79.282 | J32: =Fixed_Assets!J9+Fixed_Assets!J15 -> 77.28393 | K32: =Fixed_Assets!K9+Fixed_Assets!K15 -> 77.686442 | L32: =Fixed_Assets!L9+Fixed_Assets!L15 -> 78.243042 | M32: =Fixed_Assets!M9+Fixed_Assets!M15 -> 78.98024 | N32: =Fixed_Assets!N9+Fixed_Assets!N15 -> 79.806567 | O32: =Fixed_Assets!O9+Fixed_Assets!O15 -> 82.288056 | P32: =Fixed_Assets!P9+Fixed_Assets!P15 -> 85.004579 | Q32: =Fixed_Assets!Q9+Fixed_Assets!Q15 -> 87.73581 | ... S32: =Fixed_Assets!S9+Fixed_Assets!S15 -> 93.160462
B33: EBITDA (before impairments) | E33: =E15+E32+E14 -> 715.04 | F33: =F15+F32+F14 -> 889.985 | G33: =G15+G32+G14 -> 1100.374 | H33: =H15+H32+H14 -> 1115.833 | I33: =I15+I32+I14 -> 966.912 | J33: =J15+J32+J14 -> 970.03191 | K33: =K15+K32+K14 -> 1031.2553 | L33: =L15+L32+L14 -> 1091.2857 | ... S33: =S15+S32+S14 -> 1410.3925
B34: EBITDA margin | E34: =E33/E7 -> 0.30908406 | F34: =F33/F7 -> 0.25034845 | G34: =G33/G7 -> 0.27770763 | H34: =H33/H7 -> 0.27201453 | I34: =I33/I7 -> 0.23929633 | J34: =J33/J7 -> 0.23636105 | K34: =K33/K7 -> 0.24276501 | L34: =L33/L7 -> 0.24670765 | ... S34: =S33/S7 -> 0.25075382
B35: Analyst-adjusted EBIT | E35: =Hist!E28 -> 689.426 | F35: =Hist!F28 -> 951.191 | G35: =Hist!G28 -> 1049.095 | H35: =Hist!H28 -> 1045.992 | I35: =Hist!I28 -> 887.63 | J35: =J15+J14 -> 892.74798 | K35: =K15+K14 -> 953.56887 | L35: =L15+L14 -> 1013.0426 | M35: =M15+M14 -> 1066.2924 | N35: =N15+N14 -> 1114.8917 | O35: =O15+O14 -> 1158.0022 | P35: =P15+P14 -> 1200.1365 | Q35: =Q15+Q14 -> 1240.9449 | ... S35: =S15+S14 -> 1317.232
B36: analyst EBIT margin | E36: =E35/E7 -> 0.29801212 | F36: =F35/F7 -> 0.2675654 | G36: =G35/G7 -> 0.26476606 | H36: =H35/H7 -> 0.2549889 | I36: =I35/I7 -> 0.21967522 | J36: =J35/J7 -> 0.21752981 | K36: =K35/K7 -> 0.22447706 | L36: =L35/L7 -> 0.2290192 | ... S36: =S35/S7 -> 0.23419081
B37: Management non-GAAP EBIT | E37: =Hist!E29 -> 695.262 | F37: =Hist!F29 -> 986.332 | G37: =Hist!G29 -> 1098.637 | H37: =Hist!H29 -> 1050.258 | I37: =Hist!I29 -> 900.667 | J37: =J35+J30 -> 917.37214 | K37: =K35+K30 -> 970.5607 | L37: =L35+L30 -> 1030.7362 | M37: =M35+M30 -> 1084.7171 | N37: =N35+N30 -> 1134.033 | O37: =O35+O30 -> 1177.8519 | P37: =P35+P30 -> 1220.6814 | Q37: =Q35+Q30 -> 1262.1663 | ... S37: =S35+S30 -> 1339.7304
B38: management EBIT margin | E38: =E37/E7 -> 0.30053479 | F38: =F37/F7 -> 0.2774504 | G38: =G37/G7 -> 0.27726925 | H38: =H37/H7 -> 0.25602885 | I38: =I37/I7 -> 0.22290168 | J38: =J37/J7 -> 0.22352981 | K38: =K37/K7 -> 0.22847706 | L38: =L37/L7 -> 0.2330192 | ... S38: =S37/S7 -> 0.23819081
B39: Adjusted diluted EPS - management basis (US$) | E39: =Hist!E30/E24 -> 8.3153269 | F39: =Hist!F30/F24 -> 10.923588 | G39: =Hist!G30/G24 -> 12.034785 | H39: =Hist!H30/H24 -> 13.167903 | I39: =Hist!I30/I24 -> 12.597403 | J39: =(J37+J17-J18+J19)*(1-Inputs!J103)/J24 -> 14.444715 | K39: =(K37+K17-K18+K19)*(1-Inputs!K103)/K24 -> 17.050403 | L39: =(L37+L17-L18+L19)*(1-Inputs!L103)/L24 -> 20.208268 | M39: =(M37+M17-M18+M19)*(1-Inputs!M103)/M24 -> 23.661987 | N39: =(N37+N17-N18+N19)*(1-Inputs!N103)/N24 -> 27.708377 | O39: =(O37+O17-O18+O19)*(1-Inputs!O103)/O24 -> 32.371897 | P39: =(P37+P17-P18+P19)*(1-Inputs!P103)/P24 -> 37.499852 | Q39: =(Q37+Q17-Q18+Q19)*(1-Inputs!Q103)/Q24 -> 43.338463 | ... S39: =(S37+S17-S18+S19)*(1-Inputs!S103)/S24 -> 57.035882
B40: growth | F40: =IFERROR(F39/E39-1,"n.m.") -> 0.3136691 | G40: =IFERROR(G39/F39-1,"n.m.") -> 0.10172454 | H40: =IFERROR(H39/G39-1,"n.m.") -> 0.094153611 | I40: =IFERROR(I39/H39-1,"n.m.") -> -0.04332511 | J40: =J39/I39-1 -> 0.14664232 | K40: =K39/J39-1 -> 0.18039042 | L40: =L39/K39-1 -> 0.18520766 | M40: =M39/L39-1 -> 0.17090623 | N40: =N39/M39-1 -> 0.17100801 | O40: =O39/N39-1 -> 0.16830725 | P40: =P39/O39-1 -> 0.15840761 | Q40: =Q39/P39-1 -> 0.1556969 | ... S40: =S39/R39-1 -> 0.14422413
B41: Segment EBIT
B42: Crocs brand segment EBIT | E42: =Hist!E93 -> 861.394 | F42: =Hist!F93 -> 852.025 | G42: =Hist!G93 -> 1079.33 | H42: =Hist!H93 -> 1182.012 | I42: =Hist!I93 -> 1111.679 | J42: =Rev_Build!J17*(Inputs!J55-Inputs!J63) -> 1142.1334 | K42: =Rev_Build!K17*(Inputs!K55-Inputs!K63) -> 1195.0611 | L42: =Rev_Build!L17*(Inputs!L55-Inputs!L63) -> 1256.2237 | M42: =Rev_Build!M17*(Inputs!M55-Inputs!M63) -> 1317.5618 | N42: =Rev_Build!N17*(Inputs!N55-Inputs!N63) -> 1377.1425 | O42: =Rev_Build!O17*(Inputs!O55-Inputs!O63) -> 1431.0328 | P42: =Rev_Build!P17*(Inputs!P55-Inputs!P63) -> 1483.6483 | Q42: =Rev_Build!Q17*(Inputs!Q55-Inputs!Q63) -> 1534.5417 | ... S42: =Rev_Build!S17*(Inputs!S55-Inputs!S63) -> 1629.4332
B43: margin | E43: =E42/Rev_Build!E17 -> 0.37234721 | F43: =F42/Rev_Build!F17 -> 0.32041555 | G43: =G42/Rev_Build!G17 -> 0.35822983 | H43: =H42/Rev_Build!H17 -> 0.36059301 | I43: =I42/Rev_Build!I17 -> 0.33425842 | J43: =J42/Rev_Build!J17 -> 0.335 | K43: =K42/Rev_Build!K17 -> 0.33625 | L43: =L42/Rev_Build!L17 -> 0.3375 | ... S43: =S42/Rev_Build!S17 -> 0.34
B44: HEYDUDE segment EBIT | E44: =Hist!E97 -> 0 | F44: =Hist!F97 -> 211.361 | G44: =Hist!G97 -> 212.386 | H44: =Hist!H97 -> 137.401 | I44: =Hist!I97 -> -668.855 | J44: =Rev_Build!J24*(Inputs!J59-Inputs!J67) -> 62.52052 | K44: =Rev_Build!K24*(Inputs!K59-Inputs!K67) -> 72.856531 | L44: =Rev_Build!L24*(Inputs!L59-Inputs!L67) -> 84.150203 | M44: =Rev_Build!M24*(Inputs!M59-Inputs!M67) -> 89.588699 | N44: =Rev_Build!N24*(Inputs!N59-Inputs!N67) -> 91.863371 | O44: =Rev_Build!O24*(Inputs!O59-Inputs!O67) -> 94.189869 | P44: =Rev_Build!P24*(Inputs!P59-Inputs!P67) -> 96.568388 | Q44: =Rev_Build!Q24*(Inputs!Q59-Inputs!Q67) -> 98.999253 | ... S44: =Rev_Build!S24*(Inputs!S59-Inputs!S67) -> 104.01994
B45: margin | F45: =F44/Rev_Build!F24 -> 0.23593084 | G45: =G44/Rev_Build!G24 -> 0.22370715 | H45: =H44/Rev_Build!H24 -> 0.16672026 | I45: =I44/Rev_Build!I24 -> -0.93567092 | J45: =J44/Rev_Build!J24 -> 0.09 | K45: =K44/Rev_Build!K24 -> 0.105 | L45: =L44/Rev_Build!L24 -> 0.12 | M45: =M44/Rev_Build!M24 -> 0.125 | ... S45: =S44/Rev_Build!S24 -> 0.125
B46: Corporate, unallocated & charges | E46: =Hist!E98 -> -178.33 | F46: =Hist!F98 -> -212.63 | G46: =Hist!G98 -> -254.933 | H46: =Hist!H98 -> -297.502 | I46: =Hist!I98 -> -293.309 | J46: =-J29-J30 -> -311.90598 | K46: =-K29-K30 -> -314.34881 | L46: =-L29-L30 -> -327.33131 | M46: =-M29-M30 -> -340.85813 | N46: =-N29-N30 -> -354.11413 | O46: =-O29-O30 -> -367.22048 | P46: =-P29-P30 -> -380.08017 | Q46: =-Q29-Q30 -> -392.59605 | ... S46: =-S29-S30 -> -416.22115
B47: Total = EBIT | E47: =E42+E44+E46 -> 683.064 | F47: =F42+F44+F46 -> 850.756 | G47: =G42+G44+G46 -> 1036.783 | H47: =H42+H44+H46 -> 1021.911 | I47: =I42+I44+I46 -> 149.515 | J47: =J42+J44+J46 -> 892.74798 | K47: =K42+K44+K46 -> 953.56887 | L47: =L42+L44+L46 -> 1013.0426 | ... S47: =S42+S44+S46 -> 1317.232

Sheet BS
B1: Balance sheet
B2: Crocs, Inc. (NASDAQ: CROX) | US$ millions unless stated
B4: Fiscal year ending 31-Dec | C4: Unit | E4: FY2021A | F4: FY2022A | G4: FY2023A | H4: FY2024A | I4: FY2025A | J4: FY2026E | K4: FY2027E | L4: FY2028E | M4: FY2029E | N4: FY2030E | O4: FY2031E | P4: FY2032E | Q4: FY2033E | R4: FY2034E | S4: FY2035E
B6: Assets
B7: Cash & equivalents | E7: =Hist!E32 -> 213.197 | F7: =Hist!F32 -> 191.629 | G7: =Hist!G32 -> 149.288 | H7: =Hist!H32 -> 180.485 | I7: =Hist!I32 -> 130.354 | J7: =CF!J35 -> 150 | K7: =CF!K35 -> 150 | L7: =CF!L35 -> 150 | M7: =CF!M35 -> 218.81211 | N7: =CF!N35 -> 150 | O7: =CF!O35 -> 150 | P7: =CF!P35 -> 150 | Q7: =CF!Q35 -> 150 | ... S7: =CF!S35 -> 150
B8: Accounts receivable | E8: =Hist!E33 -> 182.629 | F8: =Hist!F33 -> 295.594 | G8: =Hist!G33 -> 305.747 | H8: =Hist!H33 -> 257.657 | I8: =Hist!I33 -> 278.191 | J8: =NWC!J7 -> 281.09767 | K8: =NWC!K7 -> 290.95595 | L8: =NWC!L7 -> 302.97234 | M8: =NWC!M7 -> 315.49253 | N8: =NWC!N7 -> 327.76206 | O8: =NWC!O7 -> 339.89308 | P8: =NWC!P7 -> 351.79579 | Q8: =NWC!Q7 -> 363.38027 | ... S8: =NWC!S7 -> 385.24727
B9: Inventories | E9: =Hist!E34 -> 213.52 | F9: =Hist!F34 -> 471.551 | G9: =Hist!G34 -> 385.054 | H9: =Hist!H34 -> 356.254 | I9: =Hist!I34 -> 368.687 | J9: =NWC!J9 -> 379.73872 | K9: =NWC!K9 -> 390.4877 | L9: =NWC!L9 -> 404.23831 | M9: =NWC!M9 -> 420.43947 | N9: =NWC!N9 -> 436.42988 | O9: =NWC!O9 -> 452.26288 | P9: =NWC!P9 -> 467.82646 | Q9: =NWC!Q9 -> 483.00849 | ... S9: =NWC!S9 -> 511.79509
B10: Income taxes receivable | E10: =Hist!E35 -> 22.301 | F10: =Hist!F35 -> 14.752 | G10: =Hist!G35 -> 4.413 | H10: =Hist!H35 -> 4.046 | I10: =Hist!I35 -> 32.782 | J10: =NWC!J12 -> 32.782 | K10: =NWC!K12 -> 32.782 | L10: =NWC!L12 -> 32.782 | M10: =NWC!M12 -> 32.782 | N10: =NWC!N12 -> 32.782 | O10: =NWC!O12 -> 32.782 | P10: =NWC!P12 -> 32.782 | Q10: =NWC!Q12 -> 32.782 | ... S10: =NWC!S12 -> 32.782
B11: Prepaid & other current assets | E11: =Hist!E36 -> 34.922 | F11: =Hist!F36 -> 52.449 | G11: =Hist!G36 -> 66.202 | H11: =Hist!H36 -> 73.827 | I11: =Hist!I36 -> 75.869 | J11: =NWC!J11 -> 77.976494 | K11: =NWC!K11 -> 80.711182 | L11: =NWC!L11 -> 84.044526 | M11: =NWC!M11 -> 87.517627 | N11: =NWC!N11 -> 90.921195 | O11: =NWC!O11 -> 94.286339 | P11: =NWC!P11 -> 97.588152 | Q11: =NWC!Q11 -> 100.80169 | ... S11: =NWC!S11 -> 106.86759
B12: Total current assets | E12: =E7+E8+E9+E10+E11 -> 666.569 | F12: =F7+F8+F9+F10+F11 -> 1025.975 | G12: =G7+G8+G9+G10+G11 -> 910.704 | H12: =H7+H8+H9+H10+H11 -> 872.269 | I12: =I7+I8+I9+I10+I11 -> 885.883 | J12: =J7+J8+J9+J10+J11 -> 921.59488 | K12: =K7+K8+K9+K10+K11 -> 944.93683 | L12: =L7+L8+L9+L10+L11 -> 974.03717 | ... S12: =S7+S8+S9+S10+S11 -> 1186.6919
B13: PP&E, net | E13: =Hist!E38 -> 108.398 | F13: =Hist!F38 -> 181.529 | G13: =Hist!G38 -> 238.315 | H13: =Hist!H38 -> 244.335 | I13: =Hist!I38 -> 238.191 | J13: =Fixed_Assets!J11 -> 249.07149 | K13: =Fixed_Assets!K11 -> 259.75235 | L13: =Fixed_Assets!L11 -> 270.78365 | M13: =Fixed_Assets!M11 -> 282.20247 | N13: =Fixed_Assets!N11 -> 293.86111 | O13: =Fixed_Assets!O11 -> 305.67208 | P13: =Fixed_Assets!P11 -> 317.547 | Q13: =Fixed_Assets!Q11 -> 329.39682 | ... S13: =Fixed_Assets!S11 -> 352.66574
B14: Operating lease ROU assets | E14: =Hist!E39 -> 160.768 | F14: =Hist!F39 -> 239.905 | G14: =Hist!G39 -> 287.44 | H14: =Hist!H39 -> 307.228 | I14: =Hist!I39 -> 338.669 | J14: =Fixed_Assets!J22 -> 344.78725 | K14: =Fixed_Assets!K22 -> 356.87917 | L14: =Fixed_Assets!L22 -> 371.61816 | M14: =Fixed_Assets!M22 -> 386.97511 | N14: =Fixed_Assets!N22 -> 402.0246 | O14: =Fixed_Assets!O22 -> 416.9042 | P14: =Fixed_Assets!P22 -> 431.50377 | Q14: =Fixed_Assets!Q22 -> 445.713 | ... S14: =Fixed_Assets!S22 -> 472.5345
B15: Goodwill | E15: =Hist!E40 -> 1.6 | F15: =Hist!F40 -> 714.814 | G15: =Hist!G40 -> 711.588 | H15: =Hist!H40 -> 711.491 | I15: =Hist!I40 -> 404.689 | J15: =Fixed_Assets!J19 -> 404.689 | K15: =Fixed_Assets!K19 -> 404.689 | L15: =Fixed_Assets!L19 -> 404.689 | M15: =Fixed_Assets!M19 -> 404.689 | N15: =Fixed_Assets!N19 -> 404.689 | O15: =Fixed_Assets!O19 -> 404.689 | P15: =Fixed_Assets!P19 -> 404.689 | Q15: =Fixed_Assets!Q19 -> 404.689 | ... S15: =Fixed_Assets!S19 -> 404.689
B16: Intangible assets, net | E16: =Hist!E41 -> 28.802 | F16: =Hist!F41 -> 1800.167 | G16: =Hist!G41 -> 1792.562 | H16: =Hist!H41 -> 1777.08 | I16: =Hist!I41 -> 1324.68 | J16: =Fixed_Assets!J18 -> 1302.18 | K16: =Fixed_Assets!K18 -> 1281.78 | L16: =Fixed_Assets!L18 -> 1263.28 | M16: =Fixed_Assets!M18 -> 1246.58 | N16: =Fixed_Assets!N18 -> 1231.68 | O16: =Fixed_Assets!O18 -> 1216.98 | P16: =Fixed_Assets!P18 -> 1202.28 | Q16: =Fixed_Assets!Q18 -> 1187.58 | ... S16: =Fixed_Assets!S18 -> 1158.18
B17: Deferred tax assets | E17: =Hist!E43 -> 567.201 | F17: =Hist!F43 -> 528.278 | G17: =Hist!G43 -> 667.972 | H17: =Hist!H43 -> 872.35 | I17: =Hist!I43 -> 935.054 | J17: =Tax!J15 -> 893.70441 | K17: =Tax!K15 -> 857.81571 | L17: =Tax!L15 -> 819.15293 | M17: =Tax!M15 -> 777.92236 | N17: =Tax!N15 -> 734.56791 | O17: =Tax!O15 -> 689.64407 | P17: =Tax!P15 -> 643.14861 | Q17: =Tax!Q15 -> 595.02081 | ... S17: =Tax!S15 -> 494.14812
B18: Other non-current assets | E18: =Hist!E44 -> 11.73 | F18: =Hist!F44 -> 11.129 | G18: =Hist!G44 -> 35.253 | H18: =Hist!H44 -> 27.4 | I18: =Hist!I44 -> 47.584 | J18: =I18 -> 47.584 | K18: =J18 -> 47.584 | L18: =K18 -> 47.584 | M18: =L18 -> 47.584 | N18: =M18 -> 47.584 | O18: =N18 -> 47.584 | P18: =O18 -> 47.584 | Q18: =P18 -> 47.584 | ... S18: =R18 -> 47.584
B19: Total assets | E19: =E12+E13+E14+E15+E16+E17+E18 -> 1545.068 | F19: =F12+F13+F14+F15+F16+F17+F18 -> 4501.797 | G19: =G12+G13+G14+G15+G16+G17+G18 -> 4643.834 | H19: =H12+H13+H14+H15+H16+H17+H18 -> 4812.153 | I19: =I12+I13+I14+I15+I16+I17+I18 -> 4174.75 | J19: =J12+J13+J14+J15+J16+J17+J18 -> 4163.611 | K19: =K12+K13+K14+K15+K16+K17+K18 -> 4153.4371 | L19: =L12+L13+L14+L15+L16+L17+L18 -> 4151.1449 | ... S19: =S12+S13+S14+S15+S16+S17+S18 -> 4116.4933
B20: Liabilities
B21: Accounts payable | E21: =Hist!E46 -> 162.145 | F21: =Hist!F46 -> 230.821 | G21: =Hist!G46 -> 260.978 | H21: =Hist!H46 -> 264.901 | I21: =Hist!I46 -> 266.09 | J21: =NWC!J14 -> 270.56384 | K21: =NWC!K14 -> 278.22248 | L21: =NWC!L14 -> 288.01979 | M21: =NWC!M14 -> 299.56312 | N21: =NWC!N14 -> 310.95629 | O21: =NWC!O14 -> 322.2373 | P21: =NWC!P14 -> 333.32635 | Q21: =NWC!Q14 -> 344.14355 | ... S21: =NWC!S14 -> 364.654
B22: Accrued expenses & other | E22: =Hist!E47 -> 166.887 | F22: =Hist!F47 -> 239.424 | G22: =Hist!G47 -> 285.771 | H22: =Hist!H47 -> 298.068 | I22: =Hist!I47 -> 300.959 | J22: =NWC!J16 -> 303.69792 | K22: =NWC!K16 -> 314.34881 | L22: =NWC!L16 -> 327.33131 | M22: =NWC!M16 -> 340.85813 | N22: =NWC!N16 -> 354.11413 | O22: =NWC!O16 -> 367.22048 | P22: =NWC!P16 -> 380.08017 | Q22: =NWC!Q16 -> 392.59605 | ... S22: =NWC!S16 -> 416.22115
B23: Income taxes payable | E23: =Hist!E48 -> 16.279 | F23: =Hist!F48 -> 89.211 | G23: =Hist!G48 -> 65.952 | H23: =Hist!H48 -> 108.688 | I23: =Hist!I48 -> 47.308 | J23: =NWC!J17 -> 47.308 | K23: =NWC!K17 -> 47.308 | L23: =NWC!L17 -> 47.308 | M23: =NWC!M17 -> 47.308 | N23: =NWC!N17 -> 47.308 | O23: =NWC!O17 -> 47.308 | P23: =NWC!P17 -> 47.308 | Q23: =NWC!Q17 -> 47.308 | ... S23: =NWC!S17 -> 47.308
B24: Operating lease liabilities - current | E24: =Hist!E49 -> 42.932 | F24: =Hist!F49 -> 57.456 | G24: =Hist!G49 -> 62.267 | H24: =Hist!H49 -> 68.551 | I24: =Hist!I49 -> 85.772 | J24: =Fixed_Assets!J23 -> 87.321521 | K24: =Fixed_Assets!K23 -> 90.383946 | L24: =Fixed_Assets!L23 -> 94.116772 | M24: =Fixed_Assets!M23 -> 98.006104 | N24: =Fixed_Assets!N23 -> 101.81757 | O24: =Fixed_Assets!O23 -> 105.58601 | P24: =Fixed_Assets!P23 -> 109.28352 | Q24: =Fixed_Assets!Q23 -> 112.88218 | ... S24: =Fixed_Assets!S23 -> 119.67505
B25: Current debt | E25: =Hist!E50 -> 0 | F25: =Hist!F50 -> 24.362 | G25: =Hist!G50 -> 23.328 | H25: =Hist!H50 -> 0 | I25: =Hist!I50 -> 0 | J25: 0 | K25: 0 | L25: 0 | M25: 0 | N25: 0 | O25: 0 | P25: 0 | Q25: 0 | R25: 0 | S25: 0
B26: Other current liabilities | E26: =Hist!E51 -> 0 | F26: =Hist!F51 -> 0 | G26: =Hist!G51 -> 0 | H26: =Hist!H51 -> 0 | I26: =Hist!I51 -> 0 | J26: =NWC!J18 -> 0 | K26: =NWC!K18 -> 0 | L26: =NWC!L18 -> 0 | M26: =NWC!M18 -> 0 | N26: =NWC!N18 -> 0 | O26: =NWC!O18 -> 0 | P26: =NWC!P18 -> 0 | Q26: =NWC!Q18 -> 0 | ... S26: =NWC!S18 -> 0
B27: Total current liabilities | E27: =E21+E22+E23+E24+E25+E26 -> 388.243 | F27: =F21+F22+F23+F24+F25+F26 -> 641.274 | G27: =G21+G22+G23+G24+G25+G26 -> 698.296 | H27: =H21+H22+H23+H24+H25+H26 -> 740.208 | I27: =I21+I22+I23+I24+I25+I26 -> 700.129 | J27: =J21+J22+J23+J24+J25+J26 -> 708.89128 | K27: =K21+K22+K23+K24+K25+K26 -> 730.26324 | L27: =L21+L22+L23+L24+L25+L26 -> 756.77588 | ... S27: =S21+S22+S23+S24+S25+S26 -> 947.8582
B28: Long-term debt (net of fees) | E28: =Hist!E53 -> 771.39 | F28: =Hist!F53 -> 2298.027 | G28: =Hist!G53 -> 1640.996 | H28: =Hist!H53 -> 1349.339 | I28: =Hist!I53 -> 1230.885 | J28: =Debt!J50 -> 1114.0038 | K28: =Debt!K50 -> 965.16014 | L28: =Debt!L50 -> 805.26543 | M28: =Debt!M50 -> 700 | N28: =Debt!N50 -> 700 | O28: =Debt!O50 -> 700 | P28: =Debt!P50 -> 700 | Q28: =Debt!Q50 -> 700 | ... S28: =Debt!S50 -> 700
B29: Operating lease liabilities - non-current | E29: =Hist!E54 -> 149.237 | F29: =Hist!F54 -> 215.119 | G29: =Hist!G54 -> 269.769 | H29: =Hist!H54 -> 283.406 | I29: =Hist!I54 -> 297.192 | J29: =Fixed_Assets!J24 -> 302.56095 | K29: =Fixed_Assets!K24 -> 313.17196 | L29: =Fixed_Assets!L24 -> 326.10586 | M29: =Fixed_Assets!M24 -> 339.58203 | N29: =Fixed_Assets!N24 -> 352.7884 | O29: =Fixed_Assets!O24 -> 365.84569 | P29: =Fixed_Assets!P24 -> 378.65724 | Q29: =Fixed_Assets!Q24 -> 391.12626 | ... S29: =Fixed_Assets!S24 -> 414.66291
B30: Long-term income taxes payable | E30: =Hist!E55 -> 219.568 | F30: =Hist!F55 -> 224.837 | G30: =Hist!G55 -> 565.171 | H30: =Hist!H55 -> 595.434 | I30: =Hist!I55 -> 649.057 | J30: =I30 -> 649.057 | K30: =J30 -> 649.057 | L30: =K30 -> 649.057 | M30: =L30 -> 649.057 | N30: =M30 -> 649.057 | O30: =N30 -> 649.057 | P30: =O30 -> 649.057 | Q30: =P30 -> 649.057 | ... S30: =R30 -> 649.057
B31: Deferred tax liabilities | E31: =Hist!E56 -> 0.176 | F31: =Hist!F56 -> 302.03 | G31: =Hist!G56 -> 12.912 | H31: =Hist!H56 -> 4.086 | I31: =Hist!I56 -> 0.882 | J31: =I31 -> 0.882 | K31: =J31 -> 0.882 | L31: =K31 -> 0.882 | M31: =L31 -> 0.882 | N31: =M31 -> 0.882 | O31: =N31 -> 0.882 | P31: =O31 -> 0.882 | Q31: =P31 -> 0.882 | ... S31: =R31 -> 0.882
B32: Other non-current liabilities | E32: =Hist!E57 -> 2.372 | F32: =Hist!F57 -> 2.579 | G32: =Hist!G57 -> 2.767 | H32: =Hist!H57 -> 3.948 | I32: =Hist!I57 -> 3.322 | J32: =I32 -> 3.322 | K32: =J32 -> 3.322 | L32: =K32 -> 3.322 | M32: =L32 -> 3.322 | N32: =M32 -> 3.322 | O32: =N32 -> 3.322 | P32: =O32 -> 3.322 | Q32: =P32 -> 3.322 | ... S32: =R32 -> 3.322
B33: Total liabilities | E33: =E27+E28+E29+E30+E31+E32 -> 1530.986 | F33: =F27+F28+F29+F30+F31+F32 -> 3683.866 | G33: =G27+G28+G29+G30+G31+G32 -> 3189.911 | H33: =H27+H28+H29+H30+H31+H32 -> 2976.421 | I33: =I27+I28+I29+I30+I31+I32 -> 2881.467 | J33: =J27+J28+J29+J30+J31+J32 -> 2778.717 | K33: =K27+K28+K29+K30+K31+K32 -> 2661.8563 | L33: =L27+L28+L29+L30+L31+L32 -> 2541.4082 | ... S33: =S27+S28+S29+S30+S31+S32 -> 2715.7821
B34: Equity
B35: Total stockholders' equity | E35: =Hist!E59 -> 14.082 | F35: =Hist!F59 -> 817.931 | G35: =Hist!G59 -> 1453.923 | H35: =Hist!H59 -> 1835.732 | I35: =Hist!I59 -> 1293.283 | J35: =Equity!J12 -> 1384.894 | K35: =Equity!K12 -> 1491.5807 | L35: =Equity!L12 -> 1609.7367 | M35: =Equity!M12 -> 1742.4183 | N35: =Equity!N12 -> 1632.0564 | O35: =Equity!O12 -> 1589.2392 | P35: =Equity!P12 -> 1544.8285 | Q35: =Equity!Q12 -> 1498.6391 | ... S35: =Equity!S12 -> 1400.7112
B36: Total liabilities & equity | E36: =E33+E35 -> 1545.068 | F36: =F33+F35 -> 4501.797 | G36: =G33+G35 -> 4643.834 | H36: =H33+H35 -> 4812.153 | I36: =I33+I35 -> 4174.75 | J36: =J33+J35 -> 4163.611 | K36: =K33+K35 -> 4153.4371 | L36: =L33+L35 -> 4151.1449 | ... S36: =S33+S35 -> 4116.4933
B37: Memo
B38: Net debt (excl. leases) | E38: =E25+E28-E7 -> 558.193 | F38: =F25+F28-F7 -> 2130.76 | G38: =G25+G28-G7 -> 1515.036 | H38: =H25+H28-H7 -> 1168.854 | I38: =I25+I28-I7 -> 1100.531 | J38: =J25+J28-J7 -> 964.00379 | K38: =K25+K28-K7 -> 815.16014 | L38: =L25+L28-L7 -> 655.26543 | ... S38: =S25+S28-S7 -> 550
B39: Balance check: assets - (liabilities + equity) | E39: =ROUND(E19-E36,2) -> 0 | F39: =ROUND(F19-F36,2) -> 0 | G39: =ROUND(G19-G36,2) -> 0 | H39: =ROUND(H19-H36,2) -> 0 | I39: =ROUND(I19-I36,2) -> 0 | J39: =ROUND(J19-J36,2) -> 0 | K39: =ROUND(K19-K36,2) -> 0 | L39: =ROUND(L19-L36,2) -> 0 | ... S39: =ROUND(S19-S36,2) -> 0
B40: Balance check, all years (0 = OK) | E40: =SUMPRODUCT(ABS($E$39:$S$39)) -> 0

Sheet CF
B1: Cash flow statement
B2: Crocs, Inc. (NASDAQ: CROX) | US$ millions unless stated
B4: Fiscal year ending 31-Dec | C4: Unit | E4: FY2021A | F4: FY2022A | G4: FY2023A | H4: FY2024A | I4: FY2025A | J4: FY2026E | K4: FY2027E | L4: FY2028E | M4: FY2029E | N4: FY2030E | O4: FY2031E | P4: FY2032E | Q4: FY2033E | R4: FY2034E | S4: FY2035E
B6: Operating activities
B7: Net income | E7: =Hist!E63 -> 725.694 | F7: =Hist!F63 -> 540.159 | G7: =Hist!G63 -> 792.566 | H7: =Hist!H63 -> 950.071 | I7: =Hist!I63 -> -81.198 | J7: =IS!J23 -> 636.78363 | K7: =IS!K23 -> 699.82968 | L7: =IS!L23 -> 753.92429 | M7: =IS!M23 -> 803.99598 | N7: =IS!N23 -> 845.4119 | O7: =IS!O23 -> 876.01482 | P7: =IS!P23 -> 906.66147 | Q7: =IS!Q23 -> 938.49203 | ... S7: =IS!S23 -> 997.99596
B8: Depreciation & amortisation | E8: =Hist!E64 -> 31.976 | F8: =Hist!F64 -> 39.229 | G8: =Hist!G64 -> 54.304 | H8: =Hist!H64 -> 69.84 | I8: =Hist!I64 -> 79.282 | J8: =Fixed_Assets!J9+Fixed_Assets!J15 -> 77.28393 | K8: =Fixed_Assets!K9+Fixed_Assets!K15 -> 77.686442 | L8: =Fixed_Assets!L9+Fixed_Assets!L15 -> 78.243042 | M8: =Fixed_Assets!M9+Fixed_Assets!M15 -> 78.98024 | N8: =Fixed_Assets!N9+Fixed_Assets!N15 -> 79.806567 | O8: =Fixed_Assets!O9+Fixed_Assets!O15 -> 82.288056 | P8: =Fixed_Assets!P9+Fixed_Assets!P15 -> 85.004579 | Q8: =Fixed_Assets!Q9+Fixed_Assets!Q15 -> 87.73581 | ... S8: =Fixed_Assets!S9+Fixed_Assets!S15 -> 93.160462
B9: Amortisation of debt issuance costs | J9: =Debt!J48 -> 9 | K9: =Debt!K48 -> 9 | L9: =Debt!L48 -> 9 | M9: =Debt!M48 -> 4.115 | N9: =Debt!N48 -> 0 | O9: =Debt!O48 -> 0 | P9: =Debt!P48 -> 0 | Q9: =Debt!Q48 -> 0 | ... S9: =Debt!S48 -> 0
B10: Share-based compensation | E10: =Hist!E65 -> 38.122 | F10: =Hist!F65 -> 31.303 | G10: =Hist!G65 -> 29.072 | H10: =Hist!H65 -> 33.053 | I10: =Hist!I65 -> 36.701 | J10: =Equity!J9 -> 36.936234 | K10: =Equity!K9 -> 38.231612 | L10: =Equity!L9 -> 39.810565 | M10: =Equity!M9 -> 41.455718 | N10: =Equity!N9 -> 43.067934 | O10: =Equity!O9 -> 44.66195 | P10: =Equity!P9 -> 46.225967 | Q10: =Equity!Q9 -> 47.748168 | ... S10: =Equity!S9 -> 50.621491
B11: Asset impairments | E11: =Hist!E66 -> 0 | F11: =Hist!F66 -> 0 | G11: =Hist!G66 -> 9.287 | H11: =Hist!H66 -> 24.081 | I11: =Hist!I66 -> 738.115 | J11: =IS!J14 -> 0 | K11: =IS!K14 -> 0 | L11: =IS!L14 -> 0 | M11: =IS!M14 -> 0 | N11: =IS!N14 -> 0 | O11: =IS!O14 -> 0 | P11: =IS!P14 -> 0 | Q11: =IS!Q14 -> 0 | ... S11: =IS!S14 -> 0
B12: Deferred taxes | E12: =Hist!E67 -> -241.283 | F12: =Hist!F67 -> -4.76 | G12: =Hist!G67 -> -410.319 | H12: =Hist!H67 -> -254.454 | I12: =Hist!I67 -> 47.093 | J12: =Tax!J11 -> 41.349586 | K12: =Tax!K11 -> 35.888702 | L12: =Tax!L11 -> 38.662784 | M12: =Tax!M11 -> 41.230563 | N12: =Tax!N11 -> 43.354456 | O12: =Tax!O11 -> 44.923837 | P12: =Tax!P11 -> 46.49546 | Q12: =Tax!Q11 -> 48.127796 | ... S12: =Tax!S11 -> 51.17928
B13: (Increase) / decrease in receivables | J13: =NWC!I7-NWC!J7 -> -2.9066705 | K13: =NWC!J7-NWC!K7 -> -9.8582833 | L13: =NWC!K7-NWC!L7 -> -12.016383 | M13: =NWC!L7-NWC!M7 -> -12.52019 | N13: =NWC!M7-NWC!N7 -> -12.269531 | O13: =NWC!N7-NWC!O7 -> -12.131019 | P13: =NWC!O7-NWC!P7 -> -11.902714 | Q13: =NWC!P7-NWC!Q7 -> -11.584481 | ... S13: =NWC!R7-NWC!S7 -> -10.688662
B14: (Increase) / decrease in inventories | J14: =NWC!I9-NWC!J9 -> -11.051718 | K14: =NWC!J9-NWC!K9 -> -10.748977 | L14: =NWC!K9-NWC!L9 -> -13.75061 | M14: =NWC!L9-NWC!M9 -> -16.201163 | N14: =NWC!M9-NWC!N9 -> -15.990413 | O14: =NWC!N9-NWC!O9 -> -15.832999 | P14: =NWC!O9-NWC!P9 -> -15.563582 | Q14: =NWC!P9-NWC!Q9 -> -15.18203 | ... S14: =NWC!R9-NWC!S9 -> -14.095706
B15: (Increase) / decrease in prepaid & other | J15: =NWC!I11-NWC!J11 -> -2.1074938 | K15: =NWC!J11-NWC!K11 -> -2.7346878 | L15: =NWC!K11-NWC!L11 -> -3.3333445 | M15: =NWC!L11-NWC!M11 -> -3.4731007 | N15: =NWC!M11-NWC!N11 -> -3.4035678 | O15: =NWC!N11-NWC!O11 -> -3.3651447 | P15: =NWC!O11-NWC!P11 -> -3.3018129 | Q15: =NWC!P11-NWC!Q11 -> -3.2135351 | ... S15: =NWC!R11-NWC!S11 -> -2.9650349
B16: Increase / (decrease) in payables | J16: =NWC!J14-NWC!I14 -> 4.4738367 | K16: =NWC!K14-NWC!J14 -> 7.6586465 | L16: =NWC!L14-NWC!K14 -> 9.7973099 | M16: =NWC!M14-NWC!L14 -> 11.543329 | N16: =NWC!N14-NWC!M14 -> 11.393169 | O16: =NWC!O14-NWC!N14 -> 11.281012 | P16: =NWC!P14-NWC!O14 -> 11.089052 | Q16: =NWC!Q14-NWC!P14 -> 10.817197 | ... S16: =NWC!S14-NWC!R14 -> 10.043191
B17: Increase / (decrease) in accrued & other | J17: =NWC!J16-NWC!I16 -> 2.7389233 | K17: =NWC!K16-NWC!J16 -> 10.650889 | L17: =NWC!L16-NWC!K16 -> 12.9825 | M17: =NWC!M16-NWC!L16 -> 13.526813 | N17: =NWC!N16-NWC!M16 -> 13.256001 | O17: =NWC!O16-NWC!N16 -> 13.106353 | P17: =NWC!P16-NWC!O16 -> 12.859692 | Q17: =NWC!Q16-NWC!P16 -> 12.515874 | ... S17: =NWC!S16-NWC!R16 -> 11.548031
B18: Operating leases: liability less ROU | J18: =Fixed_Assets!J25 -> 0.80021513 | K18: =Fixed_Assets!K25 -> 1.5815194 | L18: =Fixed_Assets!L25 -> 1.9277334 | M18: =Fixed_Assets!M25 -> 2.0085569 | N18: =Fixed_Assets!N25 -> 1.9683447 | O18: =Fixed_Assets!O25 -> 1.946124 | P18: =Fixed_Assets!P25 -> 1.9094981 | Q18: =Fixed_Assets!Q25 -> 1.8584454 | ... S18: =Fixed_Assets!S25 -> 1.7147333
B19: Working capital & other (as reported, combined) | E19: =Hist!E68 -> 12.656 | F19: =Hist!F68 -> -2.789 | G19: =Hist!G68 -> 455.534 | H19: =Hist!H68 -> 169.895 | I19: =Hist!I68 -> -109.562
B20: Cash from operations | E20: =SUM(E7:E19) -> 567.165 | F20: =SUM(F7:F19) -> 603.142 | G20: =SUM(G7:G19) -> 930.444 | H20: =SUM(H7:H19) -> 992.486 | I20: =SUM(I7:I19) -> 710.431 | J20: =SUM(J7:J19) -> 793.30047 | K20: =SUM(K7:K19) -> 857.18555 | L20: =SUM(L7:L19) -> 915.24789 | ... S20: =SUM(S7:S19) -> 1188.5137
B21: Investing activities
B22: Capital expenditures | E22: =Hist!E70 -> -55.916 | F22: =Hist!F70 -> -104.19 | G22: =Hist!G70 -> -115.625 | H22: =Hist!H70 -> -69.347 | I22: =Hist!I70 -> -51.231 | J22: =-Fixed_Assets!J8 -> -65.664416 | K22: =-Fixed_Assets!K8 -> -67.967311 | L22: =-Fixed_Assets!L8 -> -70.774338 | M22: =-Fixed_Assets!M8 -> -73.699054 | N22: =-Fixed_Assets!N8 -> -76.565217 | O22: =-Fixed_Assets!O8 -> -79.399023 | P22: =-Fixed_Assets!P8 -> -82.179497 | Q22: =-Fixed_Assets!Q8 -> -84.885631 | ... S22: =-Fixed_Assets!S8 -> -89.993762
B23: Acquisitions, net of cash | E23: =Hist!E71 -> 0 | F23: =Hist!F71 -> -2046.881 | G23: =Hist!G71 -> 0 | H23: =Hist!H71 -> 0 | I23: =Hist!I71 -> 0 | J23: 0 | K23: 0 | L23: 0 | M23: 0 | N23: 0 | O23: 0 | P23: 0 | Q23: 0 | R23: 0 | S23: 0
B24: Other investing | E24: =Hist!E72 -> -0.009 | F24: =Hist!F72 -> -0.02 | G24: =Hist!G72 -> -0.046 | H24: =Hist!H72 -> 0 | I24: =Hist!I72 -> 0 | J24: 0 | K24: 0 | L24: 0 | M24: 0 | N24: 0 | O24: 0 | P24: 0 | Q24: 0 | R24: 0 | S24: 0
B25: Cash from investing | E25: =E22+E23+E24 -> -55.925 | F25: =F22+F23+F24 -> -2151.091 | G25: =G22+G23+G24 -> -115.671 | H25: =H22+H23+H24 -> -69.347 | I25: =I22+I23+I24 -> -51.231 | J25: =J22+J23+J24 -> -65.664416 | K25: =K22+K23+K24 -> -67.967311 | L25: =L22+L23+L24 -> -70.774338 | ... S25: =S22+S23+S24 -> -89.993762
B26: Financing activities
B27: Debt issued | E27: =Hist!E74 -> 1090 | F27: =Hist!F74 -> 2169.898 | G27: =Hist!G74 -> 257.905 | H27: =Hist!H74 -> 102.156 | I27: =Hist!I74 -> 819 | J27: =MAX(0,Debt!J17)+Debt!J42 -> 0 | K27: =MAX(0,Debt!K17)+Debt!K42 -> 0 | L27: =MAX(0,Debt!L17)+Debt!L42 -> 0 | M27: =MAX(0,Debt!M17)+Debt!M42 -> 350 | N27: =MAX(0,Debt!N17)+Debt!N42 -> 0 | O27: =MAX(0,Debt!O17)+Debt!O42 -> 350 | P27: =MAX(0,Debt!P17)+Debt!P42 -> 0 | Q27: =MAX(0,Debt!Q17)+Debt!Q42 -> 0 | ... S27: =MAX(0,Debt!S17)+Debt!S42 -> 4.6185005e-07
B28: Debt repaid | E28: =Hist!E75 -> -485 | F28: =Hist!F75 -> -575.285 | G28: =Hist!G75 -> -923.703 | H28: =Hist!H75 -> -425.405 | I28: =Hist!I75 -> -947 | J28: =-(MAX(0,-Debt!J17)+Debt!J25+Debt!J26+Debt!J32+Debt!J37) -> -125.88121 | K28: =-(MAX(0,-Debt!K17)+Debt!K25+Debt!K26+Debt!K32+Debt!K37) -> -157.84365 | L28: =-(MAX(0,-Debt!L17)+Debt!L25+Debt!L26+Debt!L32+Debt!L37) -> -168.89471 | M28: =-(MAX(0,-Debt!M17)+Debt!M25+Debt!M26+Debt!M32+Debt!M37) -> -459.38043 | N28: =-(MAX(0,-Debt!N17)+Debt!N25+Debt!N26+Debt!N32+Debt!N37) -> 0 | O28: =-(MAX(0,-Debt!O17)+Debt!O25+Debt!O26+Debt!O32+Debt!O37) -> -350 | P28: =-(MAX(0,-Debt!P17)+Debt!P25+Debt!P26+Debt!P32+Debt!P37) -> 0 | Q28: =-(MAX(0,-Debt!Q17)+Debt!Q25+Debt!Q26+Debt!Q32+Debt!Q37) -> 0 | ... S28: =-(MAX(0,-Debt!S17)+Debt!S25+Debt!S26+Debt!S32+Debt!S37) -> 0
B29: Share repurchases | E29: =Hist!E76 -> -1000 | F29: =Hist!F76 -> 0 | G29: =Hist!G76 -> -175.019 | H29: =Hist!H76 -> -552.451 | I29: =Hist!I76 -> -582.32 | J29: =-Equity!J10 -> -582.10885 | K29: =-Equity!K10 -> -631.37459 | L29: =-Equity!L10 -> -675.57884 | M29: =-Equity!M10 -> -712.77016 | N29: =-Equity!N10 -> -998.84175 | O29: =-Equity!O10 -> -963.49397 | P29: =-Equity!P10 -> -997.29812 | Q29: =-Equity!Q10 -> -1032.4296 | ... S29: =-Equity!S10 -> -1098.52
B30: Other financing | E30: =Hist!E77 -> -34.638 | F30: =Hist!F77 -> -64.954 | G30: =Hist!G77 -> -18.822 | H30: =Hist!H77 -> -10.348 | I30: =Hist!I77 -> -4.245 | J30: 0 | K30: 0 | L30: 0 | M30: 0 | N30: 0 | O30: 0 | P30: 0 | Q30: 0 | R30: 0 | S30: 0
B31: Cash from financing | E31: =E27+E28+E29+E30 -> -429.638 | F31: =F27+F28+F29+F30 -> 1529.659 | G31: =G27+G28+G29+G30 -> -859.639 | H31: =H27+H28+H29+H30 -> -886.048 | I31: =I27+I28+I29+I30 -> -714.565 | J31: =J27+J28+J29+J30 -> -707.99006 | K31: =K27+K28+K29+K30 -> -789.21823 | L31: =L27+L28+L29+L30 -> -844.47355 | ... S31: =S27+S28+S29+S30 -> -1098.52
B32: FX effect on cash | E32: =Hist!E79 -> -3.95 | F32: =Hist!F79 -> -3.75 | G32: =Hist!G79 -> 3.078 | H32: =Hist!H79 -> -6.51 | I32: =Hist!I79 -> 5.598 | J32: 0 | K32: 0 | L32: 0 | M32: 0 | N32: 0 | O32: 0 | P32: 0 | Q32: 0 | R32: 0 | S32: 0
B33: Net change in cash | E33: =E20+E25+E31+E32 -> 77.652 | F33: =F20+F25+F31+F32 -> -22.04 | G33: =G20+G25+G31+G32 -> -41.788 | H33: =H20+H25+H31+H32 -> 30.581 | I33: =I20+I25+I31+I32 -> -49.767 | J33: =J20+J25+J31+J32 -> 19.646 | K33: =K20+K25+K31+K32 -> -4.5474735e-13 | L33: =L20+L25+L31+L32 -> 9.094947e-13 | ... S33: =S20+S25+S31+S32 -> 4.6509535e-07
B34: Opening cash | J34: =BS!I7 -> 130.354 | K34: =BS!J7 -> 150 | L34: =BS!K7 -> 150 | M34: =BS!L7 -> 150 | N34: =BS!M7 -> 218.81211 | O34: =BS!N7 -> 150 | P34: =BS!O7 -> 150 | Q34: =BS!P7 -> 150 | ... S34: =BS!R7 -> 150
B35: Closing cash | J35: =J34+J33 -> 150 | K35: =K34+K33 -> 150 | L35: =L34+L33 -> 150 | M35: =M34+M33 -> 218.81211 | N35: =N34+N33 -> 150 | O35: =O34+O33 -> 150 | P35: =P34+P33 -> 150 | Q35: =Q34+Q33 -> 150 | ... S35: =S34+S33 -> 150
B36: Free cash flow
B37: Free cash flow (CFO - capex) | E37: =E20+E22 -> 511.249 | F37: =F20+F22 -> 498.952 | G37: =G20+G22 -> 814.819 | H37: =H20+H22 -> 923.139 | I37: =I20+I22 -> 659.2 | J37: =J20+J22 -> 727.63606 | K37: =K20+K22 -> 789.21823 | L37: =L20+L22 -> 844.47355 | ... S37: =S20+S22 -> 1098.52
B38: % revenue | E38: =E37/IS!E7 -> 0.22099311 | F38: =F37/IS!F7 -> 0.14035277 | G38: =G37/IS!G7 -> 0.2056405 | H38: =H37/IS!H7 -> 0.22504015 | I38: =I37/IS!I7 -> 0.16314219 | J38: =J37/IS!J7 -> 0.17729811 | K38: =K37/IS!K7 -> 0.18578772 | L38: =L37/IS!L7 -> 0.19091068 | ... S38: =S37/IS!S7 -> 0.19530598
B39: FCF after SBC | E39: =E37-E10 -> 473.127 | F39: =F37-F10 -> 467.649 | G39: =G37-G10 -> 785.747 | H39: =H37-H10 -> 890.086 | I39: =I37-I10 -> 622.499 | J39: =J37-J10 -> 690.69982 | K39: =K37-K10 -> 750.98662 | L39: =L37-L10 -> 804.66299 | ... S39: =S37-S10 -> 1047.8985
B40: FCF / net income | E40: =IFERROR(E37/IS!E23,"n.m.") -> 0.70449666 | F40: =IFERROR(F37/IS!F23,"n.m.") -> 0.9237132 | G40: =IFERROR(G37/IS!G23,"n.m.") -> 1.0280772 | H40: =IFERROR(H37/IS!H23,"n.m.") -> 0.97165162 | I40: =IFERROR(I37/IS!I23,"n.m.") -> -8.1184266 | J40: =J37/IS!J23 -> 1.1426739 | K40: =K37/IS!K23 -> 1.127729 | L40: =L37/IS!L23 -> 1.1201039 | M40: =M37/IS!M23 -> 1.1081681 | N40: =N37/IS!N23 -> 1.1000906 | O40: =O37/IS!O23 -> 1.0998604 | P40: =P37/IS!P23 -> 1.0999675 | Q40: =Q37/IS!Q23 -> 1.1000942 | ... S40: =S37/IS!S23 -> 1.1007259
B41: FCF per diluted share (US$) | E41: =E37/IS!E24 -> 8.0236197 | F41: =F37/IS!F24 -> 8.0468342 | G41: =G37/IS!G24 -> 13.152424 | H41: =H37/IS!H24 -> 15.428851 | I41: =I37/IS!I24 -> 12.160567 | J41: =J37/IS!J24 -> 15.051008 | K41: =K37/IS!K24 -> 17.950322 | L41: =L37/IS!L24 -> 21.144141 | ... S41: =S37/IS!S24 -> 58.686446
B42: Memo: cash interest paid | J42: =Debt!J51-Debt!J48 -> 60.961564 | K42: =Debt!K51-Debt!K48 -> 51.851325 | L42: =Debt!L51-Debt!L48 -> 41.973028 | M42: =Debt!M51-Debt!M48 -> 36.945462 | N42: =Debt!N51-Debt!N48 -> 36.5625 | O42: =Debt!O51-Debt!O48 -> 39.40625 | P42: =Debt!P51-Debt!P48 -> 42.25 | Q42: =Debt!Q51-Debt!Q48 -> 42.25 | ... S42: =Debt!S51-Debt!S48 -> 42.25
B43: Memo: cash taxes paid | E43: =Hist!E81 -> 159.68 | F43: =Hist!F81 -> 130.084 | G43: =Hist!G81 -> 176.564 | H43: =Hist!H81 -> 122.678 | I43: =Hist!I81 -> 185.066 | J43: =Tax!J12 -> 148.85851 | K43: =Tax!K12 -> 161.49916 | L43: =Tax!L12 -> 173.98253 | M43: =Tax!M12 -> 185.53753 | N43: =Tax!N12 -> 195.09505 | O43: =Tax!O12 -> 202.15727 | P43: =Tax!P12 -> 209.22957 | Q43: =Tax!Q12 -> 216.57508 | ... S43: =Tax!S12 -> 230.30676

Sheet NWC
B1: Working capital schedule
B2: Crocs, Inc. (NASDAQ: CROX) | US$ millions unless stated
B4: Fiscal year ending 31-Dec | C4: Unit | E4: FY2021A | F4: FY2022A | G4: FY2023A | H4: FY2024A | I4: FY2025A | J4: FY2026E | K4: FY2027E | L4: FY2028E | M4: FY2029E | N4: FY2030E | O4: FY2031E | P4: FY2032E | Q4: FY2033E | R4: FY2034E | S4: FY2035E
B6: Current assets
B7: Accounts receivable | E7: =Hist!E33 -> 182.629 | F7: =Hist!F33 -> 295.594 | G7: =Hist!G33 -> 305.747 | H7: =Hist!H33 -> 257.657 | I7: =Hist!I33 -> 278.191 | J7: =IS!J7*Inputs!J80/365 -> 281.09767 | K7: =IS!K7*Inputs!K80/365 -> 290.95595 | L7: =IS!L7*Inputs!L80/365 -> 302.97234 | M7: =IS!M7*Inputs!M80/365 -> 315.49253 | N7: =IS!N7*Inputs!N80/365 -> 327.76206 | O7: =IS!O7*Inputs!O80/365 -> 339.89308 | P7: =IS!P7*Inputs!P80/365 -> 351.79579 | Q7: =IS!Q7*Inputs!Q80/365 -> 363.38027 | ... S7: =IS!S7*Inputs!S80/365 -> 385.24727
B8: DSO (days) | E8: =E7/IS!E7*365 -> 28.814353 | F8: =F7/IS!F7*365 -> 30.349442 | G8: =G7/IS!G7*365 -> 28.164534 | H8: =H7/IS!H7*365 -> 22.92597 | I8: =I7/IS!I7*365 -> 25.129568 | J8: =Inputs!J80 -> 25 | K8: =Inputs!K80 -> 25 | L8: =Inputs!L80 -> 25 | M8: =Inputs!M80 -> 25 | N8: =Inputs!N80 -> 25 | O8: =Inputs!O80 -> 25 | P8: =Inputs!P80 -> 25 | Q8: =Inputs!Q80 -> 25 | ... S8: =Inputs!S80 -> 25
B9: Inventories | E9: =Hist!E34 -> 213.52 | F9: =Hist!F34 -> 471.551 | G9: =Hist!G34 -> 385.054 | H9: =Hist!H34 -> 356.254 | I9: =Hist!I34 -> 368.687 | J9: =IS!J9*Inputs!J84/365 -> 379.73872 | K9: =IS!K9*Inputs!K84/365 -> 390.4877 | L9: =IS!L9*Inputs!L84/365 -> 404.23831 | M9: =IS!M9*Inputs!M84/365 -> 420.43947 | N9: =IS!N9*Inputs!N84/365 -> 436.42988 | O9: =IS!O9*Inputs!O84/365 -> 452.26288 | P9: =IS!P9*Inputs!P84/365 -> 467.82646 | Q9: =IS!Q9*Inputs!Q84/365 -> 483.00849 | ... S9: =IS!S9*Inputs!S84/365 -> 511.79509
B10: DIO (days) | E10: =E9/IS!E9*365 -> 87.253861 | F10: =F9/IS!F9*365 -> 101.56123 | G10: =G9/IS!G9*365 -> 80.204156 | H10: =H9/IS!H9*365 -> 76.858297 | I10: =I9/IS!I9*365 -> 79.93074 | J10: =Inputs!J84 -> 80 | K10: =Inputs!K84 -> 80 | L10: =Inputs!L84 -> 80 | M10: =Inputs!M84 -> 80 | N10: =Inputs!N84 -> 80 | O10: =Inputs!O84 -> 80 | P10: =Inputs!P84 -> 80 | Q10: =Inputs!Q84 -> 80 | ... S10: =Inputs!S84 -> 80
B11: Prepaid & other current assets | E11: =Hist!E36 -> 34.922 | F11: =Hist!F36 -> 52.449 | G11: =Hist!G36 -> 66.202 | H11: =Hist!H36 -> 73.827 | I11: =Hist!I36 -> 75.869 | J11: =IS!J7*Inputs!J98 -> 77.976494 | K11: =IS!K7*Inputs!K98 -> 80.711182 | L11: =IS!L7*Inputs!L98 -> 84.044526 | M11: =IS!M7*Inputs!M98 -> 87.517627 | N11: =IS!N7*Inputs!N98 -> 90.921195 | O11: =IS!O7*Inputs!O98 -> 94.286339 | P11: =IS!P7*Inputs!P98 -> 97.588152 | Q11: =IS!Q7*Inputs!Q98 -> 100.80169 | ... S11: =IS!S7*Inputs!S98 -> 106.86759
B12: Income taxes receivable | E12: =Hist!E35 -> 22.301 | F12: =Hist!F35 -> 14.752 | G12: =Hist!G35 -> 4.413 | H12: =Hist!H35 -> 4.046 | I12: =Hist!I35 -> 32.782 | J12: =I12 -> 32.782 | K12: =J12 -> 32.782 | L12: =K12 -> 32.782 | M12: =L12 -> 32.782 | N12: =M12 -> 32.782 | O12: =N12 -> 32.782 | P12: =O12 -> 32.782 | Q12: =P12 -> 32.782 | ... S12: =R12 -> 32.782
B13: Current liabilities
B14: Accounts payable | E14: =Hist!E46 -> 162.145 | F14: =Hist!F46 -> 230.821 | G14: =Hist!G46 -> 260.978 | H14: =Hist!H46 -> 264.901 | I14: =Hist!I46 -> 266.09 | J14: =IS!J9*Inputs!J88/365 -> 270.56384 | K14: =IS!K9*Inputs!K88/365 -> 278.22248 | L14: =IS!L9*Inputs!L88/365 -> 288.01979 | M14: =IS!M9*Inputs!M88/365 -> 299.56312 | N14: =IS!N9*Inputs!N88/365 -> 310.95629 | O14: =IS!O9*Inputs!O88/365 -> 322.2373 | P14: =IS!P9*Inputs!P88/365 -> 333.32635 | Q14: =IS!Q9*Inputs!Q88/365 -> 344.14355 | ... S14: =IS!S9*Inputs!S88/365 -> 364.654
B15: DPO (days) | E15: =E14/IS!E9*365 -> 66.259729 | F15: =F14/IS!F9*365 -> 49.713528 | G15: =G14/IS!G9*365 -> 54.35996 | H15: =H14/IS!H9*365 -> 57.149786 | I15: =I14/IS!I9*365 -> 57.687878 | J15: =Inputs!J88 -> 57 | K15: =Inputs!K88 -> 57 | L15: =Inputs!L88 -> 57 | M15: =Inputs!M88 -> 57 | N15: =Inputs!N88 -> 57 | O15: =Inputs!O88 -> 57 | P15: =Inputs!P88 -> 57 | Q15: =Inputs!Q88 -> 57 | ... S15: =Inputs!S88 -> 57
B16: Accrued expenses & other | E16: =Hist!E47 -> 166.887 | F16: =Hist!F47 -> 239.424 | G16: =Hist!G47 -> 285.771 | H16: =Hist!H47 -> 298.068 | I16: =Hist!I47 -> 300.959 | J16: =IS!J7*Inputs!J97 -> 303.69792 | K16: =IS!K7*Inputs!K97 -> 314.34881 | L16: =IS!L7*Inputs!L97 -> 327.33131 | M16: =IS!M7*Inputs!M97 -> 340.85813 | N16: =IS!N7*Inputs!N97 -> 354.11413 | O16: =IS!O7*Inputs!O97 -> 367.22048 | P16: =IS!P7*Inputs!P97 -> 380.08017 | Q16: =IS!Q7*Inputs!Q97 -> 392.59605 | ... S16: =IS!S7*Inputs!S97 -> 416.22115
B17: Income taxes payable | E17: =Hist!E48 -> 16.279 | F17: =Hist!F48 -> 89.211 | G17: =Hist!G48 -> 65.952 | H17: =Hist!H48 -> 108.688 | I17: =Hist!I48 -> 47.308 | J17: =I17 -> 47.308 | K17: =J17 -> 47.308 | L17: =K17 -> 47.308 | M17: =L17 -> 47.308 | N17: =M17 -> 47.308 | O17: =N17 -> 47.308 | P17: =O17 -> 47.308 | Q17: =P17 -> 47.308 | ... S17: =R17 -> 47.308
B18: Other current liabilities | E18: =Hist!E51 -> 0 | F18: =Hist!F51 -> 0 | G18: =Hist!G51 -> 0 | H18: =Hist!H51 -> 0 | I18: =Hist!I51 -> 0 | J18: =I18 -> 0 | K18: =J18 -> 0 | L18: =K18 -> 0 | M18: =L18 -> 0 | N18: =M18 -> 0 | O18: =N18 -> 0 | P18: =O18 -> 0 | Q18: =P18 -> 0 | ... S18: =R18 -> 0
B19: Summary
B20: Operating working capital | E20: =E7+E9+E11+E12-E14-E16-E17-E18 -> 108.061 | F20: =F7+F9+F11+F12-F14-F16-F17-F18 -> 274.89 | G20: =G7+G9+G11+G12-G14-G16-G17-G18 -> 148.715 | H20: =H7+H9+H11+H12-H14-H16-H17-H18 -> 20.127 | I20: =I7+I9+I11+I12-I14-I16-I17-I18 -> 141.172 | J20: =J7+J9+J11+J12-J14-J16-J17-J18 -> 150.02512 | K20: =K7+K9+K11+K12-K14-K16-K17-K18 -> 155.05754 | L20: =L7+L9+L11+L12-L14-L16-L17-L18 -> 161.37806 | ... S20: =S7+S9+S11+S12-S14-S16-S17-S18 -> 208.5088
B21: % revenue | E21: =E20/IS!E7 -> 0.046710579 | F21: =F20/IS!F7 -> 0.077325221 | G21: =G20/IS!G7 -> 0.037532049 | H21: =H20/IS!H7 -> 0.0049065017 | I21: =I20/IS!I7 -> 0.034937969 | J21: =J20/IS!J7 -> 0.036555598 | K21: =K20/IS!K7 -> 0.036501673 | L21: =L20/IS!L7 -> 0.036482842 | ... S21: =S20/IS!S7 -> 0.0370708
B22: Cash conversion cycle (days) | E22: =E8+E10-E15 -> 49.808485 | F22: =F8+F10-F15 -> 82.19714 | G22: =G8+G10-G15 -> 54.008729 | H22: =H8+H10-H15 -> 42.634481 | I22: =I8+I10-I15 -> 47.372431 | J22: =J8+J10-J15 -> 48 | K22: =K8+K10-K15 -> 48 | L22: =L8+L10-L15 -> 48 | ... S22: =S8+S10-S15 -> 48
B23: (Increase) / decrease in working capital | J23: =I20-J20 -> -8.8531226 | K23: =J20-K20 -> -5.0324128 | L23: =K20-L20 -> -6.3205279 | M23: =L20-M20 -> -7.1243117 | N23: =M20-N20 -> -7.0143413 | O23: =N20-O20 -> -6.9417981 | P23: =O20-P20 -> -6.8193644 | Q23: =P20-Q20 -> -6.6469765 | ... S23: =R20-S20 -> -6.1581821

Sheet Fixed_Assets
B1: PP&E, intangibles & leases
B2: Crocs, Inc. (NASDAQ: CROX) | US$ millions unless stated
B4: Fiscal year ending 31-Dec | C4: Unit | E4: FY2021A | F4: FY2022A | G4: FY2023A | H4: FY2024A | I4: FY2025A | J4: FY2026E | K4: FY2027E | L4: FY2028E | M4: FY2029E | N4: FY2030E | O4: FY2031E | P4: FY2032E | Q4: FY2033E | R4: FY2034E | S4: FY2035E
B6: PP&E (incl. capitalised software)
B7: Opening PP&E, net | F7: =E11 -> 108.398 | G7: =F11 -> 181.529 | H7: =G11 -> 238.315 | I7: =H11 -> 244.335 | J7: =I11 -> 238.191 | K7: =J11 -> 249.07149 | L7: =K11 -> 259.75235 | M7: =L11 -> 270.78365 | ... S7: =R11 -> 341.13244
B8: Capital expenditures | E8: =-Hist!E70 -> 55.916 | F8: =-Hist!F70 -> 104.19 | G8: =-Hist!G70 -> 115.625 | H8: =-Hist!H70 -> 69.347 | I8: =-Hist!I70 -> 51.231 | J8: =IS!J7*Inputs!J92 -> 65.664416 | K8: =IS!K7*Inputs!K92 -> 67.967311 | L8: =IS!L7*Inputs!L92 -> 70.774338 | M8: =IS!M7*Inputs!M92 -> 73.699054 | N8: =IS!N7*Inputs!N92 -> 76.565217 | O8: =IS!O7*Inputs!O92 -> 79.399023 | P8: =IS!P7*Inputs!P92 -> 82.179497 | Q8: =IS!Q7*Inputs!Q92 -> 84.885631 | ... S8: =IS!S7*Inputs!S92 -> 89.993762
B9: Depreciation | E9: =Hist!E21-Hist!E22 -> 14.942 | F9: =Hist!F21-Hist!F22 -> 19.642 | G9: =Hist!G21-Hist!G22 -> 31.685 | H9: =Hist!H21-Hist!H22 -> 46.906 | I9: =Hist!I21-Hist!I22 -> 55.711 | J9: =J7*Inputs!J99 -> 54.78393 | K9: =K7*Inputs!K99 -> 57.286442 | L9: =L7*Inputs!L99 -> 59.743042 | M9: =M7*Inputs!M99 -> 62.28024 | N9: =N7*Inputs!N99 -> 64.906567 | O9: =O7*Inputs!O99 -> 67.588056 | P9: =P7*Inputs!P99 -> 70.304579 | Q9: =Q7*Inputs!Q99 -> 73.03581 | ... S9: =S7*Inputs!S99 -> 78.460462
B10: Disposals, FX & other | F10: =F11-F7-F8+F9 -> -11.417 | G10: =G11-G7-G8+G9 -> -27.154 | H10: =H11-H7-H8+H9 -> -16.421 | I10: =I11-I7-I8+I9 -> -1.664 | J10: 0 | K10: 0 | L10: 0 | M10: 0 | N10: 0 | O10: 0 | P10: 0 | Q10: 0 | R10: 0 | S10: 0
B11: Closing PP&E, net | E11: =Hist!E38 -> 108.398 | F11: =Hist!F38 -> 181.529 | G11: =Hist!G38 -> 238.315 | H11: =Hist!H38 -> 244.335 | I11: =Hist!I38 -> 238.191 | J11: =J7+J8-J9+J10 -> 249.07149 | K11: =K7+K8-K9+K10 -> 259.75235 | L11: =L7+L8-L9+L10 -> 270.78365 | M11: =M7+M8-M9+M10 -> 282.20247 | N11: =N7+N8-N9+N10 -> 293.86111 | O11: =O7+O8-O9+O10 -> 305.67208 | P11: =P7+P8-P9+P10 -> 317.547 | Q11: =Q7+Q8-Q9+Q10 -> 329.39682 | ... S11: =S7+S8-S9+S10 -> 352.66574
B12: capex / depreciation | E12: =E8/E9 -> 3.7422032 | F12: =F8/F9 -> 5.3044496 | G12: =G8/G9 -> 3.6492031 | H12: =H8/H9 -> 1.4784249 | I12: =I8/I9 -> 0.919585 | J12: =J8/J9 -> 1.1986073 | K12: =K8/K9 -> 1.1864467 | L12: =L8/L9 -> 1.1846457 | ... S12: =S8/S9 -> 1.1469951
B13: Goodwill & intangibles
B14: Opening finite-lived intangibles | F14: =E16 -> 24.984 | G14: =F16 -> 222.405 | H14: =G16 -> 212.787 | I14: =H16 -> 193.443 | J14: =I16 -> 181.231 | K14: =J16 -> 158.731 | L14: =K16 -> 138.331 | M14: =L16 -> 119.831 | ... S14: =R16 -> 29.431
B15: Amortisation | E15: =Hist!E22 -> 17.034 | F15: =Hist!F22 -> 19.587 | G15: =Hist!G22 -> 22.619 | H15: =Hist!H22 -> 22.934 | I15: =Hist!I22 -> 23.571 | J15: =MIN(J14,Inputs!J106) -> 22.5 | K15: =MIN(K14,Inputs!K106) -> 20.4 | L15: =MIN(L14,Inputs!L106) -> 18.5 | M15: =MIN(M14,Inputs!M106) -> 16.7 | N15: =MIN(N14,Inputs!N106) -> 14.9 | O15: =MIN(O14,Inputs!O106) -> 14.7 | P15: =MIN(P14,Inputs!P106) -> 14.7 | Q15: =MIN(Q14,Inputs!Q106) -> 14.7 | ... S15: =MIN(S14,Inputs!S106) -> 14.7
B16: Closing finite-lived intangibles | E16: =Hist!E42 -> 24.984 | F16: =Hist!F42 -> 222.405 | G16: =Hist!G42 -> 212.787 | H16: =Hist!H42 -> 193.443 | I16: =Hist!I42 -> 181.231 | J16: =J14-J15 -> 158.731 | K16: =K14-K15 -> 138.331 | L16: =L14-L15 -> 119.831 | M16: =M14-M15 -> 103.131 | N16: =N14-N15 -> 88.231 | O16: =O14-O15 -> 73.531 | P16: =P14-P15 -> 58.831 | Q16: =Q14-Q15 -> 44.131 | ... S16: =S14-S15 -> 14.731
B17: Indefinite-lived (HEYDUDE & Crocs trademarks) | E17: =Hist!E41-Hist!E42 -> 3.818 | F17: =Hist!F41-Hist!F42 -> 1577.762 | G17: =Hist!G41-Hist!G42 -> 1579.775 | H17: =Hist!H41-Hist!H42 -> 1583.637 | I17: =Hist!I41-Hist!I42 -> 1143.449 | J17: =I17 -> 1143.449 | K17: =J17 -> 1143.449 | L17: =K17 -> 1143.449 | M17: =L17 -> 1143.449 | N17: =M17 -> 1143.449 | O17: =N17 -> 1143.449 | P17: =O17 -> 1143.449 | Q17: =P17 -> 1143.449 | ... S17: =R17 -> 1143.449
B18: Intangible assets, net | E18: =E16+E17 -> 28.802 | F18: =F16+F17 -> 1800.167 | G18: =G16+G17 -> 1792.562 | H18: =H16+H17 -> 1777.08 | I18: =I16+I17 -> 1324.68 | J18: =J16+J17 -> 1302.18 | K18: =K16+K17 -> 1281.78 | L18: =L16+L17 -> 1263.28 | ... S18: =S16+S17 -> 1158.18
B19: Goodwill | E19: =Hist!E40 -> 1.6 | F19: =Hist!F40 -> 714.814 | G19: =Hist!G40 -> 711.588 | H19: =Hist!H40 -> 711.491 | I19: =Hist!I40 -> 404.689 | J19: =I19 -> 404.689 | K19: =J19 -> 404.689 | L19: =K19 -> 404.689 | M19: =L19 -> 404.689 | N19: =M19 -> 404.689 | O19: =N19 -> 404.689 | P19: =O19 -> 404.689 | Q19: =P19 -> 404.689 | ... S19: =R19 -> 404.689
B20: Operating leases (ASC 842)
B21: Operating lease liabilities - total | E21: =Hist!E49+Hist!E54 -> 192.169 | F21: =Hist!F49+Hist!F54 -> 272.575 | G21: =Hist!G49+Hist!G54 -> 332.036 | H21: =Hist!H49+Hist!H54 -> 351.957 | I21: =Hist!I49+Hist!I54 -> 382.964 | J21: =IS!J7*Inputs!J101 -> 389.88247 | K21: =IS!K7*Inputs!K101 -> 403.55591 | L21: =IS!L7*Inputs!L101 -> 420.22263 | M21: =IS!M7*Inputs!M101 -> 437.58813 | N21: =IS!N7*Inputs!N101 -> 454.60597 | O21: =IS!O7*Inputs!O101 -> 471.4317 | P21: =IS!P7*Inputs!P101 -> 487.94076 | Q21: =IS!Q7*Inputs!Q101 -> 504.00844 | ... S21: =IS!S7*Inputs!S101 -> 534.33796
B22: Operating lease ROU assets | E22: =Hist!E39 -> 160.768 | F22: =Hist!F39 -> 239.905 | G22: =Hist!G39 -> 287.44 | H22: =Hist!H39 -> 307.228 | I22: =Hist!I39 -> 338.669 | J22: =J21*$I$22/$I$21 -> 344.78725 | K22: =K21*$I$22/$I$21 -> 356.87917 | L22: =L21*$I$22/$I$21 -> 371.61816 | M22: =M21*$I$22/$I$21 -> 386.97511 | N22: =N21*$I$22/$I$21 -> 402.0246 | O22: =O21*$I$22/$I$21 -> 416.9042 | P22: =P21*$I$22/$I$21 -> 431.50377 | Q22: =Q21*$I$22/$I$21 -> 445.713 | ... S22: =S21*$I$22/$I$21 -> 472.5345
B23: of which: current | E23: =Hist!E49 -> 42.932 | F23: =Hist!F49 -> 57.456 | G23: =Hist!G49 -> 62.267 | H23: =Hist!H49 -> 68.551 | I23: =Hist!I49 -> 85.772 | J23: =J21*$I$23/$I$21 -> 87.321521 | K23: =K21*$I$23/$I$21 -> 90.383946 | L23: =L21*$I$23/$I$21 -> 94.116772 | M23: =M21*$I$23/$I$21 -> 98.006104 | N23: =N21*$I$23/$I$21 -> 101.81757 | O23: =O21*$I$23/$I$21 -> 105.58601 | P23: =P21*$I$23/$I$21 -> 109.28352 | Q23: =Q21*$I$23/$I$21 -> 112.88218 | ... S23: =S21*$I$23/$I$21 -> 119.67505
B24: of which: non-current | E24: =Hist!E54 -> 149.237 | F24: =Hist!F54 -> 215.119 | G24: =Hist!G54 -> 269.769 | H24: =Hist!H54 -> 283.406 | I24: =Hist!I54 -> 297.192 | J24: =J21-J23 -> 302.56095 | K24: =K21-K23 -> 313.17196 | L24: =L21-L23 -> 326.10586 | M24: =M21-M23 -> 339.58203 | N24: =N21-N23 -> 352.7884 | O24: =O21-O23 -> 365.84569 | P24: =P21-P23 -> 378.65724 | Q24: =Q21-Q23 -> 391.12626 | ... S24: =S21-S23 -> 414.66291
B25: Cash-flow effect: change in (liability - ROU) | J25: =(J21-J22)-(I21-I22) -> 0.80021513 | K25: =(K21-K22)-(J21-J22) -> 1.5815194 | L25: =(L21-L22)-(K21-K22) -> 1.9277334 | M25: =(M21-M22)-(L21-L22) -> 2.0085569 | N25: =(N21-N22)-(M21-M22) -> 1.9683447 | O25: =(O21-O22)-(N21-N22) -> 1.946124 | P25: =(P21-P22)-(O21-O22) -> 1.9094981 | Q25: =(Q21-Q22)-(P21-P22) -> 1.8584454 | ... S25: =(S21-S22)-(R21-R22) -> 1.7147333
B26: Memo: operating lease cost (in SG&A) | E26: =Hist!E24 -> 58.283 | F26: =Hist!F24 -> 66.012 | G26: =Hist!G24 -> 79.543 | H26: =Hist!H24 -> 85.13 | I26: =Hist!I24 -> 104.313 | J26: =I26*J21/I21 -> 106.19748 | K26: =J26*K21/J21 -> 109.92189 | L26: =K26*L21/K21 -> 114.46163 | M26: =L26*M21/L21 -> 119.1917 | N26: =M26*N21/M21 -> 123.82708 | O26: =N26*O21/N21 -> 128.41012 | P26: =O26*P21/O21 -> 132.90692 | Q26: =P26*Q21/P21 -> 137.28348 | ... S26: =R26*S21/R21 -> 145.54474

Sheet Tax
B1: Tax schedule - book vs cash
B2: Crocs, Inc. (NASDAQ: CROX) | US$ millions unless stated
B4: Fiscal year ending 31-Dec | C4: Unit | E4: FY2021A | F4: FY2022A | G4: FY2023A | H4: FY2024A | I4: FY2025A | J4: FY2026E | K4: FY2027E | L4: FY2028E | M4: FY2029E | N4: FY2030E | O4: FY2031E | P4: FY2032E | Q4: FY2033E | R4: FY2034E | S4: FY2035E
B6: Pre-tax income | E6: =IS!E20 -> 663.849 | F6: =IS!F20 -> 718.508 | G6: =IS!G20 -> 876.272 | H6: =IS!H20 -> 910.586 | I6: =IS!I20 -> 72.978 | J6: =IS!J20 -> 826.99173 | K6: =IS!K20 -> 897.21754 | L6: =IS!L20 -> 966.5696 | ... S6: =IS!S20 -> 1279.482
B7: GAAP effective tax rate | E7: =IFERROR(IS!E21/IS!E20,"n.m.") -> -0.093161246 | F7: =IFERROR(IS!F21/IS!F20,"n.m.") -> 0.24822131 | G7: =IFERROR(IS!G21/IS!G20,"n.m.") -> 0.095525134 | H7: =IFERROR(IS!H21/IS!H20,"n.m.") -> -0.043363285 | I7: =IFERROR(IS!I21/IS!I20,"n.m.") -> 2.1126367 | J7: =Inputs!J102 -> 0.23 | K7: =Inputs!K102 -> 0.22 | L7: =Inputs!L102 -> 0.22 | M7: =Inputs!M102 -> 0.22 | N7: =Inputs!N102 -> 0.22 | O7: =Inputs!O102 -> 0.22 | P7: =Inputs!P102 -> 0.22 | Q7: =Inputs!Q102 -> 0.22 | ... S7: =Inputs!S102 -> 0.22
B8: Book tax expense | E8: =IS!E21 -> -61.845 | F8: =IS!F21 -> 178.349 | G8: =IS!G21 -> 83.706 | H8: =IS!H21 -> -39.486 | I8: =IS!I21 -> 154.176 | J8: =MAX(0,J6)*J7 -> 190.2081 | K8: =MAX(0,K6)*K7 -> 197.38786 | L8: =MAX(0,L6)*L7 -> 212.64531 | M8: =MAX(0,M6)*M7 -> 226.7681 | N8: =MAX(0,N6)*N7 -> 238.44951 | O8: =MAX(0,O6)*O7 -> 247.0811 | P8: =MAX(0,P6)*P7 -> 255.72503 | Q8: =MAX(0,Q6)*Q7 -> 264.70288 | ... S8: =MAX(0,S6)*S7 -> 281.48604
B9: Cash / adjusted tax rate | J9: =Inputs!J103 -> 0.18 | K9: =Inputs!K103 -> 0.18 | L9: =Inputs!L103 -> 0.18 | M9: =Inputs!M103 -> 0.18 | N9: =Inputs!N103 -> 0.18 | O9: =Inputs!O103 -> 0.18 | P9: =Inputs!P103 -> 0.18 | Q9: =Inputs!Q103 -> 0.18 | ... S9: =Inputs!S103 -> 0.18
B10: Tax at cash rate | J10: =MAX(0,J6)*J9 -> 148.85851 | K10: =MAX(0,K6)*K9 -> 161.49916 | L10: =MAX(0,L6)*L9 -> 173.98253 | M10: =MAX(0,M6)*M9 -> 185.53753 | N10: =MAX(0,N6)*N9 -> 195.09505 | O10: =MAX(0,O6)*O9 -> 202.15727 | P10: =MAX(0,P6)*P9 -> 209.22957 | Q10: =MAX(0,Q6)*Q9 -> 216.57508 | ... S10: =MAX(0,S6)*S9 -> 230.30676
B11: Deferred tax expense (non-cash) | E11: =Hist!E67 -> -241.283 | F11: =Hist!F67 -> -4.76 | G11: =Hist!G67 -> -410.319 | H11: =Hist!H67 -> -254.454 | I11: =Hist!I67 -> 47.093 | J11: =MIN(J14,J8-J10) -> 41.349586 | K11: =MIN(K14,K8-K10) -> 35.888702 | L11: =MIN(L14,L8-L10) -> 38.662784 | M11: =MIN(M14,M8-M10) -> 41.230563 | N11: =MIN(N14,N8-N10) -> 43.354456 | O11: =MIN(O14,O8-O10) -> 44.923837 | P11: =MIN(P14,P8-P10) -> 46.49546 | Q11: =MIN(Q14,Q8-Q10) -> 48.127796 | ... S11: =MIN(S14,S8-S10) -> 51.17928
B12: Cash taxes | E12: =Hist!E81 -> 159.68 | F12: =Hist!F81 -> 130.084 | G12: =Hist!G81 -> 176.564 | H12: =Hist!H81 -> 122.678 | I12: =Hist!I81 -> 185.066 | J12: =J8-J11 -> 148.85851 | K12: =K8-K11 -> 161.49916 | L12: =L8-L11 -> 173.98253 | M12: =M8-M11 -> 185.53753 | N12: =N8-N11 -> 195.09505 | O12: =O8-O11 -> 202.15727 | P12: =P8-P11 -> 209.22957 | Q12: =Q8-Q11 -> 216.57508 | ... S12: =S8-S11 -> 230.30676
B13: Deferred tax asset
B14: Opening deferred tax assets | F14: =E15 -> 567.201 | G14: =F15 -> 528.278 | H14: =G15 -> 667.972 | I14: =H15 -> 872.35 | J14: =I15 -> 935.054 | K14: =J15 -> 893.70441 | L14: =K15 -> 857.81571 | M14: =L15 -> 819.15293 | ... S14: =R15 -> 545.3274
B15: Closing deferred tax assets | E15: =Hist!E43 -> 567.201 | F15: =Hist!F43 -> 528.278 | G15: =Hist!G43 -> 667.972 | H15: =Hist!H43 -> 872.35 | I15: =Hist!I43 -> 935.054 | J15: =J14-J11 -> 893.70441 | K15: =K14-K11 -> 857.81571 | L15: =L14-L11 -> 819.15293 | M15: =M14-M11 -> 777.92236 | N15: =N14-N11 -> 734.56791 | O15: =O14-O11 -> 689.64407 | P15: =P14-P11 -> 643.14861 | Q15: =Q14-Q11 -> 595.02081 | ... S15: =S14-S11 -> 494.14812

Sheet Debt
B1: Debt schedule, interest & cash sweep
B2: Crocs, Inc. (NASDAQ: CROX) | US$ millions unless stated
B4: Fiscal year ending 31-Dec | C4: Unit | E4: FY2021A | F4: FY2022A | G4: FY2023A | H4: FY2024A | I4: FY2025A | J4: FY2026E | K4: FY2027E | L4: FY2028E | M4: FY2029E | N4: FY2030E | O4: FY2031E | P4: FY2032E | Q4: FY2033E | R4: FY2034E | S4: FY2035E
B6: SOFR | J6: =Inputs!J104 -> 0.0375 | K6: =Inputs!K104 -> 0.035 | L6: =Inputs!L104 -> 0.0325 | M6: =Inputs!M104 -> 0.0325 | N6: =Inputs!N104 -> 0.0325 | O6: =Inputs!O104 -> 0.0325 | P6: =Inputs!P104 -> 0.0325 | Q6: =Inputs!Q104 -> 0.0325 | ... S6: =Inputs!S104 -> 0.0325
B7: Cash available for debt service
B8: Opening cash | J8: =BS!I7 -> 130.354 | K8: =BS!J7 -> 150 | L8: =BS!K7 -> 150 | M8: =BS!L7 -> 150 | N8: =BS!M7 -> 218.81211 | O8: =BS!N7 -> 150 | P8: =BS!O7 -> 150 | Q8: =BS!P7 -> 150 | ... S8: =BS!R7 -> 150
B9: Free cash flow before financing (CFO + CFI) | J9: =CF!J20+CF!J25 -> 727.63606 | K9: =CF!K20+CF!K25 -> 789.21823 | L9: =CF!L20+CF!L25 -> 844.47355 | M9: =CF!M20+CF!M25 -> 890.9627 | N9: =CF!N20+CF!N25 -> 930.02964 | O9: =CF!O20+CF!O25 -> 963.49397 | P9: =CF!P20+CF!P25 -> 997.29812 | Q9: =CF!Q20+CF!Q25 -> 1032.4296 | ... S9: =CF!S20+CF!S25 -> 1098.52
B10: Less: share repurchases | J10: =Equity!J10 -> 582.10885 | K10: =Equity!K10 -> 631.37459 | L10: =Equity!L10 -> 675.57884 | M10: =Equity!M10 -> 712.77016 | N10: =Equity!N10 -> 998.84175 | O10: =Equity!O10 -> 963.49397 | P10: =Equity!P10 -> 997.29812 | Q10: =Equity!Q10 -> 1032.4296 | ... S10: =Equity!S10 -> 1098.52
B11: Less: scheduled maturities, net of refinancing | J11: =J25+J32+J37-J42 -> 0 | K11: =K25+K32+K37-K42 -> 0 | L11: =L25+L32+L37-L42 -> 0 | M11: =M25+M32+M37-M42 -> 109.38043 | N11: =N25+N32+N37-N42 -> 0 | O11: =O25+O32+O37-O42 -> 0 | P11: =P25+P32+P37-P42 -> 0 | Q11: =Q25+Q32+Q37-Q42 -> 0 | ... S11: =S25+S32+S37-S42 -> 0
B12: Less: minimum cash | J12: =MinCash -> 150 | K12: =MinCash -> 150 | L12: =MinCash -> 150 | M12: =MinCash -> 150 | N12: =MinCash -> 150 | O12: =MinCash -> 150 | P12: =MinCash -> 150 | Q12: =MinCash -> 150 | ... S12: =MinCash -> 150
B13: Cash available / (shortfall) | J13: =J8+J9-J10-J11-J12 -> 125.88121 | K13: =K8+K9-K10-K11-K12 -> 157.84365 | L13: =L8+L9-L10-L11-L12 -> 168.89471 | M13: =M8+M9-M10-M11-M12 -> 68.812107 | N13: =N8+N9-N10-N11-N12 -> 0 | O13: =O8+O9-O10-O11-O12 -> 0 | P13: =P8+P9-P10-P11-P12 -> 0 | Q13: =Q8+Q9-Q10-Q11-Q12 -> 0 | ... S13: =S8+S9-S10-S11-S12 -> 3.2675871e-09
B14: Excess after repaying the revolver | J14: =MAX(0,J13-J16) -> 63.881211 | K14: =MAX(0,K13-K16) -> 157.84365 | L14: =MAX(0,L13-L16) -> 168.89471 | M14: =MAX(0,M13-M16) -> 68.812107 | N14: =MAX(0,N13-N16) -> 0 | O14: =MAX(0,O13-O16) -> 0 | P14: =MAX(0,P13-P16) -> 0 | Q14: =MAX(0,Q13-Q16) -> 0 | ... S14: =MAX(0,S13-S16) -> 3.1179752e-09
B15: Revolving credit facility ($1.0bn)
B16: Opening balance | J16: =I18 -> 62 | K16: =J18 -> 0 | L16: =K18 -> 0 | M16: =L18 -> 0 | N16: =M18 -> 0 | O16: =N18 -> 0 | P16: =O18 -> 0 | Q16: =P18 -> 0 | ... S16: =R18 -> 0
B17: Draw / (repayment) | J17: =J18-J16 -> -62 | K17: =K18-K16 -> 0 | L17: =L18-L16 -> 0 | M17: =M18-M16 -> 0 | N17: =N18-N16 -> 0 | O17: =O18-O16 -> 0 | P17: =P18-P16 -> 0 | Q17: =Q18-Q16 -> 0 | ... S17: =S18-S16 -> 0
B18: Closing balance | H18: =Hist!H108 -> 190 | I18: =Hist!I108 -> 62 | J18: =MIN(RevolverCap,MAX(0,J16-J13)) -> 0 | K18: =MIN(RevolverCap,MAX(0,K16-K13)) -> 0 | L18: =MIN(RevolverCap,MAX(0,L16-L13)) -> 0 | M18: =MIN(RevolverCap,MAX(0,M16-M13)) -> 0 | N18: =MIN(RevolverCap,MAX(0,N16-N13)) -> 0 | O18: =MIN(RevolverCap,MAX(0,O16-O13)) -> 0 | P18: =MIN(RevolverCap,MAX(0,P16-P13)) -> 0 | Q18: =MIN(RevolverCap,MAX(0,Q16-Q13)) -> 0 | ... S18: =MIN(RevolverCap,MAX(0,S16-S13)) -> 0
B19: rate (SOFR + margin) | J19: =J6+RevolverSpread -> 0.0525 | K19: =K6+RevolverSpread -> 0.05 | L19: =L6+RevolverSpread -> 0.0475 | M19: =M6+RevolverSpread -> 0.0475 | N19: =N6+RevolverSpread -> 0.0475 | O19: =O6+RevolverSpread -> 0.0475 | P19: =P6+RevolverSpread -> 0.0475 | Q19: =Q6+RevolverSpread -> 0.0475 | ... S19: =S6+RevolverSpread -> 0.0475
B20: Interest | J20: =J19*IF(CircSwitch=1,AVERAGE(J16,J18),J16) -> 1.6275 | K20: =K19*IF(CircSwitch=1,AVERAGE(K16,K18),K16) -> 0 | L20: =L19*IF(CircSwitch=1,AVERAGE(L16,L18),L16) -> 0 | M20: =M19*IF(CircSwitch=1,AVERAGE(M16,M18),M16) -> 0 | N20: =N19*IF(CircSwitch=1,AVERAGE(N16,N18),N16) -> 0 | O20: =O19*IF(CircSwitch=1,AVERAGE(O16,O18),O16) -> 0 | P20: =P19*IF(CircSwitch=1,AVERAGE(P16,P18),P16) -> 0 | Q20: =Q19*IF(CircSwitch=1,AVERAGE(Q16,Q18),Q16) -> 0 | ... S20: =S19*IF(CircSwitch=1,AVERAGE(S16,S18),S16) -> 0
B21: Commitment fee on undrawn | J21: =CommitFee*(RevolverCap-IF(CircSwitch=1,AVERAGE(J16,J18),J16)) -> 1.938 | K21: =CommitFee*(RevolverCap-IF(CircSwitch=1,AVERAGE(K16,K18),K16)) -> 2 | L21: =CommitFee*(RevolverCap-IF(CircSwitch=1,AVERAGE(L16,L18),L16)) -> 2 | M21: =CommitFee*(RevolverCap-IF(CircSwitch=1,AVERAGE(M16,M18),M16)) -> 2 | N21: =CommitFee*(RevolverCap-IF(CircSwitch=1,AVERAGE(N16,N18),N16)) -> 2 | O21: =CommitFee*(RevolverCap-IF(CircSwitch=1,AVERAGE(O16,O18),O16)) -> 2 | P21: =CommitFee*(RevolverCap-IF(CircSwitch=1,AVERAGE(P16,P18),P16)) -> 2 | Q21: =CommitFee*(RevolverCap-IF(CircSwitch=1,AVERAGE(Q16,Q18),Q16)) -> 2 | ... S21: =CommitFee*(RevolverCap-IF(CircSwitch=1,AVERAGE(S16,S18),S16)) -> 2
B22: Undrawn availability | J22: =RevolverCap-J18 -> 1000 | K22: =RevolverCap-K18 -> 1000 | L22: =RevolverCap-L18 -> 1000 | M22: =RevolverCap-M18 -> 1000 | N22: =RevolverCap-N18 -> 1000 | O22: =RevolverCap-O18 -> 1000 | P22: =RevolverCap-P18 -> 1000 | Q22: =RevolverCap-Q18 -> 1000 | ... S22: =RevolverCap-S18 -> 1000
B23: Term Loan B (SOFR + 2.25%, matures Feb-2029)
B24: Opening balance | J24: =I27 -> 500 | K24: =J27 -> 436.11879 | L24: =K27 -> 278.27514 | M24: =L27 -> 109.38043 | N24: =M27 -> 0 | O24: =N27 -> 0 | P24: =O27 -> 0 | Q24: =P27 -> 0 | ... S24: =R27 -> 0
B25: Scheduled repayment / maturity | J25: =IF(2026=2029,J24,0) -> 0 | K25: =IF(2027=2029,K24,0) -> 0 | L25: =IF(2028=2029,L24,0) -> 0 | M25: =IF(2029=2029,M24,0) -> 109.38043 | N25: =IF(2030=2029,N24,0) -> 0 | O25: =IF(2031=2029,O24,0) -> 0 | P25: =IF(2032=2029,P24,0) -> 0 | Q25: =IF(2033=2029,Q24,0) -> 0 | R25: =IF(2034=2029,R24,0) -> 0 | S25: =IF(2035=2029,S24,0) -> 0
B26: Optional prepayment (cash sweep) | J26: =MIN(J24-J25,J14*TLBSweep) -> 63.881211 | K26: =MIN(K24-K25,K14*TLBSweep) -> 157.84365 | L26: =MIN(L24-L25,L14*TLBSweep) -> 168.89471 | M26: =MIN(M24-M25,M14*TLBSweep) -> 0 | N26: =MIN(N24-N25,N14*TLBSweep) -> 0 | O26: =MIN(O24-O25,O14*TLBSweep) -> 0 | P26: =MIN(P24-P25,P14*TLBSweep) -> 0 | Q26: =MIN(Q24-Q25,Q14*TLBSweep) -> 0 | ... S26: =MIN(S24-S25,S14*TLBSweep) -> 0
B27: Closing balance | H27: =Hist!H107 -> 500 | I27: =Hist!I107 -> 500 | J27: =J24-J25-J26 -> 436.11879 | K27: =K24-K25-K26 -> 278.27514 | L27: =L24-L25-L26 -> 109.38043 | M27: =M24-M25-M26 -> 0 | N27: =N24-N25-N26 -> 0 | O27: =O24-O25-O26 -> 0 | P27: =P24-P25-P26 -> 0 | Q27: =Q24-Q25-Q26 -> 0 | ... S27: =S24-S25-S26 -> 0
B28: rate | J28: =J6+TLBSpread -> 0.06 | K28: =K6+TLBSpread -> 0.0575 | L28: =L6+TLBSpread -> 0.055 | M28: =M6+TLBSpread -> 0.055 | N28: =N6+TLBSpread -> 0.055 | O28: =O6+TLBSpread -> 0.055 | P28: =P6+TLBSpread -> 0.055 | Q28: =Q6+TLBSpread -> 0.055 | ... S28: =S6+TLBSpread -> 0.055
B29: Interest | J29: =J28*IF(CircSwitch=1,AVERAGE(J24,J27),J24) -> 28.083564 | K29: =K28*IF(CircSwitch=1,AVERAGE(K24,K27),K24) -> 20.538825 | L29: =L28*IF(CircSwitch=1,AVERAGE(L24,L27),L24) -> 10.660528 | M29: =M28*IF(CircSwitch=1,AVERAGE(M24,M27),M24) -> 3.0079619 | N29: =N28*IF(CircSwitch=1,AVERAGE(N24,N27),N24) -> 0 | O29: =O28*IF(CircSwitch=1,AVERAGE(O24,O27),O24) -> 0 | P29: =P28*IF(CircSwitch=1,AVERAGE(P24,P27),P24) -> 0 | Q29: =Q28*IF(CircSwitch=1,AVERAGE(Q24,Q27),Q24) -> 0 | ... S29: =S28*IF(CircSwitch=1,AVERAGE(S24,S27),S24) -> 0
B30: 4.25% senior notes due Mar-2029
B31: Opening balance | J31: =I33 -> 350 | K31: =J33 -> 350 | L31: =K33 -> 350 | M31: =L33 -> 350 | N31: =M33 -> 0 | O31: =N33 -> 0 | P31: =O33 -> 0 | Q31: =P33 -> 0 | ... S31: =R33 -> 0
B32: Repayment at maturity | J32: =IF(2026=2029,J31,0) -> 0 | K32: =IF(2027=2029,K31,0) -> 0 | L32: =IF(2028=2029,L31,0) -> 0 | M32: =IF(2029=2029,M31,0) -> 350 | N32: =IF(2030=2029,N31,0) -> 0 | O32: =IF(2031=2029,O31,0) -> 0 | P32: =IF(2032=2029,P31,0) -> 0 | Q32: =IF(2033=2029,Q31,0) -> 0 | R32: =IF(2034=2029,R31,0) -> 0 | S32: =IF(2035=2029,S31,0) -> 0
B33: Closing balance | H33: =Hist!H105 -> 350 | I33: =Hist!I105 -> 350 | J33: =J31-J32 -> 350 | K33: =K31-K32 -> 350 | L33: =L31-L32 -> 350 | M33: =M31-M32 -> 0 | N33: =N31-N32 -> 0 | O33: =O31-O32 -> 0 | P33: =P31-P32 -> 0 | Q33: =Q31-Q32 -> 0 | ... S33: =S31-S32 -> 0
B34: Interest | J34: =Coupon_Notes29*IF(CircSwitch=1,AVERAGE(J31,J33),J31) -> 14.875 | K34: =Coupon_Notes29*IF(CircSwitch=1,AVERAGE(K31,K33),K31) -> 14.875 | L34: =Coupon_Notes29*IF(CircSwitch=1,AVERAGE(L31,L33),L31) -> 14.875 | M34: =Coupon_Notes29*IF(CircSwitch=1,AVERAGE(M31,M33),M31) -> 7.4375 | N34: =Coupon_Notes29*IF(CircSwitch=1,AVERAGE(N31,N33),N31) -> 0 | O34: =Coupon_Notes29*IF(CircSwitch=1,AVERAGE(O31,O33),O31) -> 0 | P34: =Coupon_Notes29*IF(CircSwitch=1,AVERAGE(P31,P33),P31) -> 0 | Q34: =Coupon_Notes29*IF(CircSwitch=1,AVERAGE(Q31,Q33),Q31) -> 0 | ... S34: =Coupon_Notes29*IF(CircSwitch=1,AVERAGE(S31,S33),S31) -> 0
B35: 4.125% senior notes due Aug-2031
B36: Opening balance | J36: =I38 -> 350 | K36: =J38 -> 350 | L36: =K38 -> 350 | M36: =L38 -> 350 | N36: =M38 -> 350 | O36: =N38 -> 350 | P36: =O38 -> 0 | Q36: =P38 -> 0 | ... S36: =R38 -> 0
B37: Repayment at maturity | J37: =IF(2026=2031,J36,0) -> 0 | K37: =IF(2027=2031,K36,0) -> 0 | L37: =IF(2028=2031,L36,0) -> 0 | M37: =IF(2029=2031,M36,0) -> 0 | N37: =IF(2030=2031,N36,0) -> 0 | O37: =IF(2031=2031,O36,0) -> 350 | P37: =IF(2032=2031,P36,0) -> 0 | Q37: =IF(2033=2031,Q36,0) -> 0 | R37: =IF(2034=2031,R36,0) -> 0 | S37: =IF(2035=2031,S36,0) -> 0
B38: Closing balance | H38: =Hist!H106 -> 350 | I38: =Hist!I106 -> 350 | J38: =J36-J37 -> 350 | K38: =K36-K37 -> 350 | L38: =L36-L37 -> 350 | M38: =M36-M37 -> 350 | N38: =N36-N37 -> 350 | O38: =O36-O37 -> 0 | P38: =P36-P37 -> 0 | Q38: =Q36-Q37 -> 0 | ... S38: =S36-S37 -> 0
B39: Interest | J39: =Coupon_Notes31*IF(CircSwitch=1,AVERAGE(J36,J38),J36) -> 14.4375 | K39: =Coupon_Notes31*IF(CircSwitch=1,AVERAGE(K36,K38),K36) -> 14.4375 | L39: =Coupon_Notes31*IF(CircSwitch=1,AVERAGE(L36,L38),L36) -> 14.4375 | M39: =Coupon_Notes31*IF(CircSwitch=1,AVERAGE(M36,M38),M36) -> 14.4375 | N39: =Coupon_Notes31*IF(CircSwitch=1,AVERAGE(N36,N38),N36) -> 14.4375 | O39: =Coupon_Notes31*IF(CircSwitch=1,AVERAGE(O36,O38),O36) -> 7.21875 | P39: =Coupon_Notes31*IF(CircSwitch=1,AVERAGE(P36,P38),P36) -> 0 | Q39: =Coupon_Notes31*IF(CircSwitch=1,AVERAGE(Q36,Q38),Q36) -> 0 | ... S39: =Coupon_Notes31*IF(CircSwitch=1,AVERAGE(S36,S38),S36) -> 0
B40: Refinancing notes (issued to refinance maturing notes)
B41: Opening balance | J41: =I43 -> 0 | K41: =J43 -> 0 | L41: =K43 -> 0 | M41: =L43 -> 0 | N41: =M43 -> 350 | O41: =N43 -> 350 | P41: =O43 -> 700 | Q41: =P43 -> 700 | ... S41: =R43 -> 700
B42: Issuance | J42: =RefiSwitch*(J32+J37) -> 0 | K42: =RefiSwitch*(K32+K37) -> 0 | L42: =RefiSwitch*(L32+L37) -> 0 | M42: =RefiSwitch*(M32+M37) -> 350 | N42: =RefiSwitch*(N32+N37) -> 0 | O42: =RefiSwitch*(O32+O37) -> 350 | P42: =RefiSwitch*(P32+P37) -> 0 | Q42: =RefiSwitch*(Q32+Q37) -> 0 | ... S42: =RefiSwitch*(S32+S37) -> 0
B43: Closing balance | H43: =0 -> 0 | I43: =0 -> 0 | J43: =J41+J42 -> 0 | K43: =K41+K42 -> 0 | L43: =L41+L42 -> 0 | M43: =M41+M42 -> 350 | N43: =N41+N42 -> 350 | O43: =O41+O42 -> 700 | P43: =P41+P42 -> 700 | Q43: =Q41+Q42 -> 700 | ... S43: =S41+S42 -> 700
B44: Interest | J44: =RefiCoupon*IF(CircSwitch=1,AVERAGE(J41,J43),J41) -> 0 | K44: =RefiCoupon*IF(CircSwitch=1,AVERAGE(K41,K43),K41) -> 0 | L44: =RefiCoupon*IF(CircSwitch=1,AVERAGE(L41,L43),L41) -> 0 | M44: =RefiCoupon*IF(CircSwitch=1,AVERAGE(M41,M43),M41) -> 10.0625 | N44: =RefiCoupon*IF(CircSwitch=1,AVERAGE(N41,N43),N41) -> 20.125 | O44: =RefiCoupon*IF(CircSwitch=1,AVERAGE(O41,O43),O41) -> 30.1875 | P44: =RefiCoupon*IF(CircSwitch=1,AVERAGE(P41,P43),P41) -> 40.25 | Q44: =RefiCoupon*IF(CircSwitch=1,AVERAGE(Q41,Q43),Q41) -> 40.25 | ... S44: =RefiCoupon*IF(CircSwitch=1,AVERAGE(S41,S43),S41) -> 40.25
B45: Totals
B46: Total debt - face value | H46: =H18+H27+H33+H38+H43 -> 1390 | I46: =I18+I27+I33+I38+I43 -> 1262 | J46: =J18+J27+J33+J38+J43 -> 1136.1188 | K46: =K18+K27+K33+K38+K43 -> 978.27514 | L46: =L18+L27+L33+L38+L43 -> 809.38043 | M46: =M18+M27+M33+M38+M43 -> 700 | N46: =N18+N27+N33+N38+N43 -> 700 | O46: =O18+O27+O33+O38+O43 -> 700 | ... S46: =S18+S27+S33+S38+S43 -> 700
B47: Opening unamortised issuance costs | J47: =I49 -> 31.115 | K47: =J49 -> 22.115 | L47: =K49 -> 13.115 | M47: =L49 -> 4.115 | N47: =M49 -> 0 | O47: =N49 -> 0 | P47: =O49 -> 0 | Q47: =P49 -> 0 | ... S47: =R49 -> 0
B48: Amortisation of issuance costs (non-cash interest) | J48: =MIN(J47,FeeAmort) -> 9 | K48: =MIN(K47,FeeAmort) -> 9 | L48: =MIN(L47,FeeAmort) -> 9 | M48: =MIN(M47,FeeAmort) -> 4.115 | N48: =MIN(N47,FeeAmort) -> 0 | O48: =MIN(O47,FeeAmort) -> 0 | P48: =MIN(P47,FeeAmort) -> 0 | Q48: =MIN(Q47,FeeAmort) -> 0 | ... S48: =MIN(S47,FeeAmort) -> 0
B49: Closing unamortised issuance costs | E49: =Hist!E61 -> 13.61 | F49: =Hist!F61 -> 56.973 | G49: =Hist!G61 -> 49.004 | H49: =Hist!H61 -> 40.661 | I49: =Hist!I61 -> 31.115 | J49: =J47-J48 -> 22.115 | K49: =K47-K48 -> 13.115 | L49: =L47-L48 -> 4.115 | M49: =M47-M48 -> 0 | N49: =N47-N48 -> 0 | O49: =O47-O48 -> 0 | P49: =P47-P48 -> 0 | Q49: =Q47-Q48 -> 0 | ... S49: =S47-S48 -> 0
B50: Total debt - book value (face less fees) | E50: =Hist!E53+Hist!E50 -> 771.39 | F50: =Hist!F53+Hist!F50 -> 2322.389 | G50: =Hist!G53+Hist!G50 -> 1664.324 | H50: =Hist!H53+Hist!H50 -> 1349.339 | I50: =Hist!I53+Hist!I50 -> 1230.885 | J50: =J46-J49 -> 1114.0038 | K50: =K46-K49 -> 965.16014 | L50: =L46-L49 -> 805.26543 | M50: =M46-M49 -> 700 | N50: =N46-N49 -> 700 | O50: =O46-O49 -> 700 | P50: =P46-P49 -> 700 | Q50: =Q46-Q49 -> 700 | ... S50: =S46-S49 -> 700
B51: Total interest expense | E51: =Hist!E14 -> 21.647 | F51: =Hist!F14 -> 136.158 | G51: =Hist!G14 -> 161.351 | H51: =Hist!H14 -> 109.264 | I51: =Hist!I14 -> 88.287 | J51: =J20+J21+J29+J34+J39+J44+J48 -> 69.961564 | K51: =K20+K21+K29+K34+K39+K44+K48 -> 60.851325 | L51: =L20+L21+L29+L34+L39+L44+L48 -> 50.973028 | M51: =M20+M21+M29+M34+M39+M44+M48 -> 41.060462 | N51: =N20+N21+N29+N34+N39+N44+N48 -> 36.5625 | O51: =O20+O21+O29+O34+O39+O44+O48 -> 39.40625 | P51: =P20+P21+P29+P34+P39+P44+P48 -> 42.25 | Q51: =Q20+Q21+Q29+Q34+Q39+Q44+Q48 -> 42.25 | ... S51: =S20+S21+S29+S34+S39+S44+S48 -> 42.25
B52: Interest income on cash | E52: =Hist!E13 -> 0.775 | F52: =Hist!F13 -> 1.02 | G52: =Hist!G13 -> 2.406 | H52: =Hist!H13 -> 3.484 | I52: =Hist!I13 -> 1.844 | J52: =CashRate*IF(CircSwitch=1,AVERAGE(BS!I7,BS!J7),BS!I7) -> 4.20531 | K52: =CashRate*IF(CircSwitch=1,AVERAGE(BS!J7,BS!K7),BS!J7) -> 4.5 | L52: =CashRate*IF(CircSwitch=1,AVERAGE(BS!K7,BS!L7),BS!K7) -> 4.5 | M52: =CashRate*IF(CircSwitch=1,AVERAGE(BS!L7,BS!M7),BS!L7) -> 5.5321816 | N52: =CashRate*IF(CircSwitch=1,AVERAGE(BS!M7,BS!N7),BS!M7) -> 5.5321816 | O52: =CashRate*IF(CircSwitch=1,AVERAGE(BS!N7,BS!O7),BS!N7) -> 4.5 | P52: =CashRate*IF(CircSwitch=1,AVERAGE(BS!O7,BS!P7),BS!O7) -> 4.5 | Q52: =CashRate*IF(CircSwitch=1,AVERAGE(BS!P7,BS!Q7),BS!P7) -> 4.5 | ... S52: =CashRate*IF(CircSwitch=1,AVERAGE(BS!R7,BS!S7),BS!R7) -> 4.5
B53: Credit statistics
B54: Net debt (excl. leases) | E54: =E50-BS!E7 -> 558.193 | F54: =F50-BS!F7 -> 2130.76 | G54: =G50-BS!G7 -> 1515.036 | H54: =H50-BS!H7 -> 1168.854 | I54: =I50-BS!I7 -> 1100.531 | J54: =J50-BS!J7 -> 964.00379 | K54: =K50-BS!K7 -> 815.16014 | L54: =L50-BS!L7 -> 655.26543 | ... S54: =S50-BS!S7 -> 550
B55: Net debt / EBITDA | E55: =E54/IS!E33 -> 0.78064584 | F55: =F54/IS!F33 -> 2.3941527 | G55: =G54/IS!G33 -> 1.3768373 | H55: =H54/IS!H33 -> 1.047517 | I55: =I54/IS!I33 -> 1.1381915 | J55: =J54/IS!J33 -> 0.99378565 | K55: =K54/IS!K33 -> 0.79045425 | L55: =L54/IS!L33 -> 0.6004527 | ... S55: =S54/IS!S33 -> 0.38996238
B56: Gross debt / EBITDA | E56: =E50/IS!E33 -> 1.0788068 | F56: =F50/IS!F33 -> 2.6094698 | G56: =G50/IS!G33 -> 1.5125076 | H56: =H50/IS!H33 -> 1.2092661 | I56: =I50/IS!I33 -> 1.2730062 | J56: =J50/IS!J33 -> 1.1484197 | K56: =K50/IS!K33 -> 0.93590805 | L56: =L50/IS!L33 -> 0.73790525 | ... S56: =S50/IS!S33 -> 0.49631576
B57: Lease-adjusted debt / EBITDAR | E57: =(E50+Fixed_Assets!E21)/(IS!E33+Fixed_Assets!E26) -> 1.2459981 | F57: =(F50+Fixed_Assets!F21)/(IS!F33+Fixed_Assets!F26) -> 2.714406 | G57: =(G50+Fixed_Assets!G21)/(IS!G33+Fixed_Assets!G26) -> 1.6919495 | H57: =(H50+Fixed_Assets!H21)/(IS!H33+Fixed_Assets!H26) -> 1.4166098 | I57: =(I50+Fixed_Assets!I21)/(IS!I33+Fixed_Assets!I26) -> 1.5065453 | J57: =(J50+Fixed_Assets!J21)/(IS!J33+Fixed_Assets!J26) -> 1.3973659 | K57: =(K50+Fixed_Assets!K21)/(IS!K33+Fixed_Assets!K26) -> 1.1993896 | L57: =(L50+Fixed_Assets!L21)/(IS!L33+Fixed_Assets!L26) -> 1.0163722 | ... S57: =(S50+Fixed_Assets!S21)/(IS!S33+Fixed_Assets!S26) -> 0.79330835
B58: EBITDA / interest expense | E58: =IS!E33/E51 -> 33.031829 | F58: =IS!F33/F51 -> 6.5364136 | G58: =IS!G33/G51 -> 6.8197532 | H58: =IS!H33/H51 -> 10.212266 | I58: =IS!I33/I51 -> 10.951918 | J58: =IS!J33/J51 -> 13.865212 | K58: =IS!K33/K51 -> 16.94713 | L58: =IS!L33/L51 -> 21.409081 | ... S58: =IS!S33/S51 -> 33.38207

Sheet Equity
B1: Equity, share count & buybacks
B2: Crocs, Inc. (NASDAQ: CROX) | US$ millions unless stated
B4: Fiscal year ending 31-Dec | C4: Unit | E4: FY2021A | F4: FY2022A | G4: FY2023A | H4: FY2024A | I4: FY2025A | J4: FY2026E | K4: FY2027E | L4: FY2028E | M4: FY2029E | N4: FY2030E | O4: FY2031E | P4: FY2032E | Q4: FY2033E | R4: FY2034E | S4: FY2035E
B6: Stockholders' equity
B7: Opening equity | F7: =E12 -> 14.082 | G7: =F12 -> 817.931 | H7: =G12 -> 1453.923 | I7: =H12 -> 1835.732 | J7: =I12 -> 1293.283 | K7: =J12 -> 1384.894 | L7: =K12 -> 1491.5807 | M7: =L12 -> 1609.7367 | ... S7: =R12 -> 1450.6137
B8: Net income | E8: =IS!E23 -> 725.694 | F8: =IS!F23 -> 540.159 | G8: =IS!G23 -> 792.566 | H8: =IS!H23 -> 950.072 | I8: =IS!I23 -> -81.198 | J8: =IS!J23 -> 636.78363 | K8: =IS!K23 -> 699.82968 | L8: =IS!L23 -> 753.92429 | ... S8: =IS!S23 -> 997.99596
B9: Share-based compensation | E9: =Hist!E23 -> 38.122 | F9: =Hist!F23 -> 31.303 | G9: =Hist!G23 -> 29.072 | H9: =Hist!H23 -> 33.053 | I9: =Hist!I23 -> 36.701 | J9: =IS!J7*Inputs!J100 -> 36.936234 | K9: =IS!K7*Inputs!K100 -> 38.231612 | L9: =IS!L7*Inputs!L100 -> 39.810565 | M9: =IS!M7*Inputs!M100 -> 41.455718 | N9: =IS!N7*Inputs!N100 -> 43.067934 | O9: =IS!O7*Inputs!O100 -> 44.66195 | P9: =IS!P7*Inputs!P100 -> 46.225967 | Q9: =IS!Q7*Inputs!Q100 -> 47.748168 | ... S9: =IS!S7*Inputs!S100 -> 50.621491
B10: Share repurchases | E10: =-Hist!E76 -> 1000 | F10: =-Hist!F76 -> 0 | G10: =-Hist!G76 -> 175.019 | H10: =-Hist!H76 -> 552.451 | I10: =-Hist!I76 -> 582.32 | J10: =IF(AND(ExcessToBuybacks=1,Debt!J16+Debt!J24<0.01),MAX(MAX(0,Inputs!J105*Debt!J9),Debt!J8+Debt!J9-Debt!J11-MinCash),MAX(0,Inputs!J105*Debt!J9)) -> 582.10885 | K10: =IF(AND(ExcessToBuybacks=1,Debt!K16+Debt!K24<0.01),MAX(MAX(0,Inputs!K105*Debt!K9),Debt!K8+Debt!K9-Debt!K11-MinCash),MAX(0,Inputs!K105*Debt!K9)) -> 631.37459 | L10: =IF(AND(ExcessToBuybacks=1,Debt!L16+Debt!L24<0.01),MAX(MAX(0,Inputs!L105*Debt!L9),Debt!L8+Debt!L9-Debt!L11-MinCash),MAX(0,Inputs!L105*Debt!L9)) -> 675.57884 | M10: =IF(AND(ExcessToBuybacks=1,Debt!M16+Debt!M24<0.01),MAX(MAX(0,Inputs!M105*Debt!M9),Debt!M8+Debt!M9-Debt!M11-MinCash),MAX(0,Inputs!M105*Debt!M9)) -> 712.77016 | N10: =IF(AND(ExcessToBuybacks=1,Debt!N16+Debt!N24<0.01),MAX(MAX(0,Inputs!N105*Debt!N9),Debt!N8+Debt!N9-Debt!N11-MinCash),MAX(0,Inputs!N105*Debt!N9)) -> 998.84175 | O10: =IF(AND(ExcessToBuybacks=1,Debt!O16+Debt!O24<0.01),MAX(MAX(0,Inputs!O105*Debt!O9),Debt!O8+Debt!O9-Debt!O11-MinCash),MAX(0,Inputs!O105*Debt!O9)) -> 963.49397 | P10: =IF(AND(ExcessToBuybacks=1,Debt!P16+Debt!P24<0.01),MAX(MAX(0,Inputs!P105*Debt!P9),Debt!P8+Debt!P9-Debt!P11-MinCash),MAX(0,Inputs!P105*Debt!P9)) -> 997.29812 | Q10: =IF(AND(ExcessToBuybacks=1,Debt!Q16+Debt!Q24<0.01),MAX(MAX(0,Inputs!Q105*Debt!Q9),Debt!Q8+Debt!Q9-Debt!Q11-MinCash),MAX(0,Inputs!Q105*Debt!Q9)) -> 1032.4296 | ... S10: =IF(AND(ExcessToBuybacks=1,Debt!S16+Debt!S24<0.01),MAX(MAX(0,Inputs!S105*Debt!S9),Debt!S8+Debt!S9-Debt!S11-MinCash),MAX(0,Inputs!S105*Debt!S9)) -> 1098.52
B11: OCI, withholding & other | F11: =F12-F7-F8-F9+F10 -> 232.387 | G11: =G12-G7-G8-G9+G10 -> -10.627 | H11: =H12-H7-H8-H9+H10 -> -48.865 | I11: =I12-I7-I8-I9+I10 -> 84.368 | J11: 0 | K11: 0 | L11: 0 | M11: 0 | N11: 0 | O11: 0 | P11: 0 | Q11: 0 | R11: 0 | S11: 0
B12: Closing equity | E12: =Hist!E59 -> 14.082 | F12: =Hist!F59 -> 817.931 | G12: =Hist!G59 -> 1453.923 | H12: =Hist!H59 -> 1835.732 | I12: =Hist!I59 -> 1293.283 | J12: =J7+J8+J9-J10+J11 -> 1384.894 | K12: =K7+K8+K9-K10+K11 -> 1491.5807 | L12: =L7+L8+L9-L10+L11 -> 1609.7367 | M12: =M7+M8+M9-M10+M11 -> 1742.4183 | N12: =N7+N8+N9-N10+N11 -> 1632.0564 | O12: =O7+O8+O9-O10+O11 -> 1589.2392 | P12: =P7+P8+P9-P10+P11 -> 1544.8285 | Q12: =Q7+Q8+Q9-Q10+Q11 -> 1498.6391 | ... S12: =S7+S8+S9-S10+S11 -> 1400.7112
B13: Share count (m)
B14: Average repurchase price (US$) | J14: =SharePrice -> 118.54 | K14: =IF(BuybackPxMode=1,J14*IS!J39/IS!I39,J14*(1+PriceGrowth)) -> 135.92298 | L14: =IF(BuybackPxMode=1,K14*IS!K39/IS!J39,K14*(1+PriceGrowth)) -> 160.44218 | M14: =IF(BuybackPxMode=1,L14*IS!L39/IS!K39,L14*(1+PriceGrowth)) -> 190.1573 | N14: =IF(BuybackPxMode=1,M14*IS!M39/IS!L39,M14*(1+PriceGrowth)) -> 222.65637 | O14: =IF(BuybackPxMode=1,N14*IS!N39/IS!M39,N14*(1+PriceGrowth)) -> 260.7324 | P14: =IF(BuybackPxMode=1,O14*IS!O39/IS!N39,O14*(1+PriceGrowth)) -> 304.61555 | Q14: =IF(BuybackPxMode=1,P14*IS!P39/IS!O39,P14*(1+PriceGrowth)) -> 352.86897 | R14: =IF(BuybackPxMode=1,Q14*IS!Q39/IS!P39,Q14*(1+PriceGrowth)) -> 407.80958 | S14: =IF(BuybackPxMode=1,R14*IS!R39/IS!Q39,R14*(1+PriceGrowth)) -> 469.05198
B15: Opening basic shares | J15: =I18 -> 50.2 | K15: =J18 -> 45.689347 | L15: =K18 -> 41.444256 | M15: =L18 -> 37.633525 | N15: =M18 -> 34.285207 | O15: =N18 -> 30.199183 | P15: =O18 -> 26.903846 | Q15: =P18 -> 24.02989 | ... S15: =R18 -> 19.289462
B16: Shares repurchased | J16: =J10/J14 -> 4.9106533 | K16: =K10/K14 -> 4.6450908 | L16: =L10/L14 -> 4.2107308 | M16: =M10/M14 -> 3.7483186 | N16: =N10/N14 -> 4.4860236 | O16: =O10/O14 -> 3.6953366 | P16: =P10/P14 -> 3.2739567 | Q16: =Q10/Q14 -> 2.9258159 | ... S16: =S10/S14 -> 2.3420005
B17: Shares issued (RSU vesting, net) | J17: =RSUIssuance -> 0.4 | K17: =RSUIssuance -> 0.4 | L17: =RSUIssuance -> 0.4 | M17: =RSUIssuance -> 0.4 | N17: =RSUIssuance -> 0.4 | O17: =RSUIssuance -> 0.4 | P17: =RSUIssuance -> 0.4 | Q17: =RSUIssuance -> 0.4 | ... S17: =RSUIssuance -> 0.4
B18: Closing basic shares | E18: =Hist!E60 -> 58.3 | F18: =Hist!F60 -> 61.7 | G18: =Hist!G60 -> 60.5 | H18: =Hist!H60 -> 56.5 | I18: =Hist!I60 -> 50.2 | J18: =J15-J16+J17 -> 45.689347 | K18: =K15-K16+K17 -> 41.444256 | L18: =L15-L16+L17 -> 37.633525 | M18: =M15-M16+M17 -> 34.285207 | N18: =N15-N16+N17 -> 30.199183 | O18: =O15-O16+O17 -> 26.903846 | P18: =P15-P16+P17 -> 24.02989 | Q18: =Q15-Q16+Q17 -> 21.504074 | ... S18: =S15-S16+S17 -> 17.347461
B19: Weighted-average basic shares | J19: =AVERAGE(J15,J18) -> 47.944673 | K19: =AVERAGE(K15,K18) -> 43.566801 | L19: =AVERAGE(L15,L18) -> 39.53889 | M19: =AVERAGE(M15,M18) -> 35.959366 | N19: =AVERAGE(N15,N18) -> 32.242195 | O19: =AVERAGE(O15,O18) -> 28.551515 | P19: =AVERAGE(P15,P18) -> 25.466868 | Q19: =AVERAGE(Q15,Q18) -> 22.766982 | ... S19: =AVERAGE(S15,S18) -> 18.318461
B20: Diluted weighted-average shares | E20: =Hist!E19 -> 63.718 | F20: =Hist!F19 -> 62.006 | G20: =Hist!G19 -> 61.952 | H20: =Hist!H19 -> 59.832 | I20: =Hist!I19 -> 54.208 | J20: =J19+Dilution -> 48.344673 | K20: =K19+Dilution -> 43.966801 | L20: =L19+Dilution -> 39.93889 | M20: =M19+Dilution -> 36.359366 | N20: =N19+Dilution -> 32.642195 | O20: =O19+Dilution -> 28.951515 | P20: =P19+Dilution -> 25.866868 | Q20: =Q19+Dilution -> 23.166982 | ... S20: =S19+Dilution -> 18.718461
B21: change in diluted shares | F21: =IFERROR(F20/E20-1,"n.m.") -> -0.026868389 | G21: =IFERROR(G20/F20-1,"n.m.") -> -0.00087088346 | H21: =IFERROR(H20/G20-1,"n.m.") -> -0.034220041 | I21: =IFERROR(I20/H20-1,"n.m.") -> -0.093996524 | J21: =J20/I20-1 -> -0.10816349 | K21: =K20/J20-1 -> -0.090555417 | L21: =L20/K20-1 -> -0.09161255 | M21: =M20/L20-1 -> -0.08962504 | N21: =N20/M20-1 -> -0.10223421 | O21: =O20/N20-1 -> -0.11306471 | P21: =P20/O20-1 -> -0.10654526 | Q21: =Q20/P20-1 -> -0.10437623 | ... S21: =S20/R20-1 -> -0.099934101

Sheet WACC
B1: Cost of capital (WACC)
B2: Crocs, Inc. (NASDAQ: CROX) | US$ millions unless stated
B4: Cost of equity (CAPM)
B5: Risk-free rate - 10y US Treasury | C5: 0.05283 | D5: CBOE ^TNX close 30-Sep-2026
B6: Equity risk premium (US) | C6: 0.0423 | D6: Damodaran implied ERP, Jan-2026 (4.23%)
B7: Regression beta - 5y weekly vs S&P 500 | C7: 1.3132 | D7: OLS on 261 weekly returns; R-squared 0.16
B8: Blume-adjusted regression beta | C8: =0.67*Beta_Raw+0.33 -> 1.209844 | D8: Mean reversion towards 1.0
B9: Memo: regression beta - 2y daily | C9: 1.0881 | D9: Cross-check (noisier)
B10: Bottom-up unlevered beta - developed-market peer median | C10: 1.0434 | D10: Deckers, Steve Madden, Wolverine, Birkenstock, On, Dr. Martens - Hamada at market D/E
B11: Debt - face value at 30-Jun-2026 | C11: 1334 | D11: 10-Q: revolver 134 + TLB 500 + 2029 notes 350 + 2031 notes 350
B12: Market capitalisation | C12: =SharePrice*SharesOut -> 5683.4003
B13: Market debt / equity | C13: =DebtFace/MktCap -> 0.23471864
B14: Marginal tax rate (debt shield, relevering) | C14: 0.25 | D14: US federal 21% + state
B15: Bottom-up beta relevered at Crocs' D/E | C15: =Beta_BU_Unlev*(1+(1-TaxMarginal)*DE_Market) -> 1.2270791
B16: Selected beta - average of Blume and bottom-up | C16: =AVERAGE(Beta_Blume,Beta_BU_Relev) -> 1.2184615
B17: Cost of equity | C17: =Rf+Beta*ERP -> 0.10437092
B18: Cost of debt
B19: Credit spread - BB (S&P) / Ba2 (Moody's) | C19: 0.0225 | D19: Agency ratings: S&P BB stable (Feb-2025), Moody's Ba2 stable
B20: Pre-tax cost of debt | C20: =Rf+BBSpread -> 0.07533
B21: After-tax cost of debt | C21: =Kd*(1-TaxMarginal) -> 0.0564975
B22: Memo: FY26E EBIT / interest | C22: =IS!$J$15/IS!$J$18 -> 12.760549
B23: Memo: Damodaran synthetic rating from coverage | C23: =IF(Coverage26>8.5,"AAA",IF(Coverage26>6.5,"AA",IF(Coverage26>5.5,"A+",IF(Coverage26>4.25,"A",IF(Coverage26>3,"A-",IF(Coverage26>2.5,"BBB",IF(Coverage26>2.25,"BB+",IF(Coverage26>2,"BB","B")))))))) -> AAA | D23: Coverage says AAA; agencies say BB (single-brand fashion risk) - we use the agency view
B24: Weights and WACC
B25: Debt / (debt + equity) - market values | C25: =DebtFace/(DebtFace+MktCap) -> 0.19009889
B26: WACC | C26: =(1-Wd)*Ke+Wd*Kd_AT -> 0.095270238 | D26: Leases excluded: lease cost is in FCFF (US GAAP)
B29: Peer betas (5y weekly vs home index; Hamada unlevering)
B30: Peer | C30: Region | D30: Index | E30: Levered beta | F30: R-squared | G30: D/E (market) | H30: Unlevered beta
B31: Deckers Outdoor | C31: US | D31: ^GSPC | E31: 1.0299 | F31: 0.175003 | G31: 0 | H31: 1.0299
B32: Steven Madden | C32: US | D32: ^GSPC | E32: 1.176 | F32: 0.267031 | G32: 0.071676 | H32: 1.116
B33: Wolverine World Wide | C33: US | D33: ^GSPC | E33: 1.3541 | F33: 0.155716 | G33: 0.398715 | H33: 1.0424
B34: Birkenstock | C34: Europe | D34: ^GSPC | E34: 1.1946 | F34: 0.141891 | G34: 0.237294 | H34: 1.0141
B35: On Holding | C35: Europe | D35: ^GSPC | E35: 1.7864 | F35: 0.279183 | G35: 0 | H35: 1.7864
B36: Dr. Martens | C36: UK | D36: ^FTSE | E36: 1.336 | F36: 0.096979 | G36: 0.372159 | H36: 1.0445
B37: Metro Brands | C37: India | D37: ^NSEI | E37: 0.720343 | F37: 0.085542 | G37: 0 | H37: 0.720343
B38: Relaxo Footwears | C38: India | D38: ^NSEI | E38: 0.869736 | F38: 0.141699 | G38: 0 | H38: 0.869736
B39: Campus Activewear | C39: India | D39: ^NSEI | E39: 0.921675 | F39: 0.110153 | G39: 0.005683 | H39: 0.917773
B40: Bata India | C40: India | D40: ^NSEI | E40: 1.1095 | F40: 0.313935 | G40: 0 | H40: 1.1095

Sheet DCF
B1: Discounted cash flow - annual build
B2: Crocs, Inc. (NASDAQ: CROX) | US$ millions unless stated
B4: Fiscal year ending 31-Dec | C4: Unit | E4: FY2021A | F4: FY2022A | G4: FY2023A | H4: FY2024A | I4: FY2025A | J4: FY2026E | K4: FY2027E | L4: FY2028E | M4: FY2029E | N4: FY2030E | O4: FY2031E | P4: FY2032E | Q4: FY2033E | R4: FY2034E | S4: FY2035E
B6: Unlevered free cash flow (FCFF)
B7: Revenue | J7: =IS!J7 -> 4104.026 | K7: =IS!K7 -> 4247.9569 | L7: =IS!L7 -> 4423.3961 | M7: =IS!M7 -> 4606.1909 | N7: =IS!N7 -> 4785.326 | O7: =IS!O7 -> 4962.4389 | P7: =IS!P7 -> 5136.2185 | Q7: =IS!Q7 -> 5305.352 | ... S7: =IS!S7 -> 5624.6101
B8: EBIT (analyst: restructuring charges kept in) | J8: =IS!J15 -> 892.74798 | K8: =IS!K15 -> 953.56887 | L8: =IS!L15 -> 1013.0426 | M8: =IS!M15 -> 1066.2924 | N8: =IS!N15 -> 1114.8917 | O8: =IS!O15 -> 1158.0022 | P8: =IS!P15 -> 1200.1365 | Q8: =IS!Q15 -> 1240.9449 | ... S8: =IS!S15 -> 1317.232
B9: margin | J9: =J8/J7 -> 0.21752981 | K9: =K8/K7 -> 0.22447706 | L9: =L8/L7 -> 0.2290192 | M9: =M8/M7 -> 0.23149114 | N9: =N8/N7 -> 0.23298135 | O9: =O8/O7 -> 0.23335344 | P9: =P8/P7 -> 0.2336615 | Q9: =Q8/Q7 -> 0.23390435 | ... S9: =S8/S7 -> 0.23419081
B10: Cash tax rate on EBIT | J10: =Inputs!J103 -> 0.18 | K10: =Inputs!K103 -> 0.18 | L10: =Inputs!L103 -> 0.18 | M10: =Inputs!M103 -> 0.18 | N10: =Inputs!N103 -> 0.18 | O10: =Inputs!O103 -> 0.18 | P10: =Inputs!P103 -> 0.18 | Q10: =Inputs!Q103 -> 0.18 | ... S10: =Inputs!S103 -> 0.18
B11: Less: taxes on EBIT | J11: =-J8*J10 -> -160.69464 | K11: =-K8*K10 -> -171.6424 | L11: =-L8*L10 -> -182.34767 | M11: =-M8*M10 -> -191.93263 | N11: =-N8*N10 -> -200.68051 | O11: =-O8*O10 -> -208.44039 | P11: =-P8*P10 -> -216.02457 | Q11: =-Q8*Q10 -> -223.37008 | ... S11: =-S8*S10 -> -237.10176
B12: NOPAT | J12: =J8+J11 -> 732.05334 | K12: =K8+K11 -> 781.92647 | L12: =L8+L11 -> 830.69496 | M12: =M8+M11 -> 874.35974 | N12: =N8+N11 -> 914.21122 | O12: =O8+O11 -> 949.56178 | P12: =P8+P11 -> 984.11193 | Q12: =Q8+Q11 -> 1017.5748 | ... S12: =S8+S11 -> 1080.1302
B13: Plus: D&A | J13: =IS!J32 -> 77.28393 | K13: =IS!K32 -> 77.686442 | L13: =IS!L32 -> 78.243042 | M13: =IS!M32 -> 78.98024 | N13: =IS!N32 -> 79.806567 | O13: =IS!O32 -> 82.288056 | P13: =IS!P32 -> 85.004579 | Q13: =IS!Q32 -> 87.73581 | ... S13: =IS!S32 -> 93.160462
B14: Less: capital expenditures | J14: =-Fixed_Assets!J8 -> -65.664416 | K14: =-Fixed_Assets!K8 -> -67.967311 | L14: =-Fixed_Assets!L8 -> -70.774338 | M14: =-Fixed_Assets!M8 -> -73.699054 | N14: =-Fixed_Assets!N8 -> -76.565217 | O14: =-Fixed_Assets!O8 -> -79.399023 | P14: =-Fixed_Assets!P8 -> -82.179497 | Q14: =-Fixed_Assets!Q8 -> -84.885631 | ... S14: =-Fixed_Assets!S8 -> -89.993762
B15: Less: investment in working capital | J15: =NWC!J23 -> -8.8531226 | K15: =NWC!K23 -> -5.0324128 | L15: =NWC!L23 -> -6.3205279 | M15: =NWC!M23 -> -7.1243117 | N15: =NWC!N23 -> -7.0143413 | O15: =NWC!O23 -> -6.9417981 | P15: =NWC!P23 -> -6.8193644 | Q15: =NWC!Q23 -> -6.6469765 | ... S15: =NWC!S23 -> -6.1581821
B16: Plus: operating lease liability less ROU movement | J16: =Fixed_Assets!J25 -> 0.80021513 | K16: =Fixed_Assets!K25 -> 1.5815194 | L16: =Fixed_Assets!L25 -> 1.9277334 | M16: =Fixed_Assets!M25 -> 2.0085569 | N16: =Fixed_Assets!N25 -> 1.9683447 | O16: =Fixed_Assets!O25 -> 1.946124 | P16: =Fixed_Assets!P25 -> 1.9094981 | Q16: =Fixed_Assets!Q25 -> 1.8584454 | ... S16: =Fixed_Assets!S25 -> 1.7147333
B17: Unlevered free cash flow | J17: =J12+J13+J14+J15+J16 -> 735.61995 | K17: =K12+K13+K14+K15+K16 -> 788.19471 | L17: =L12+L13+L14+L15+L16 -> 833.77087 | M17: =M12+M13+M14+M15+M16 -> 874.52517 | N17: =N12+N13+N14+N15+N16 -> 912.40657 | O17: =O12+O13+O14+O15+O16 -> 947.45514 | P17: =P12+P13+P14+P15+P16 -> 982.02715 | Q17: =Q12+Q13+Q14+Q15+Q16 -> 1015.6365 | ... S17: =S12+S13+S14+S15+S16 -> 1078.8535
B18: net reinvestment rate | J18: =-(J14+J15+J16+J13)/J12 -> -0.0048720585 | K18: =-(K14+K15+K16+K13)/K12 -> -0.0080164027 | L18: =-(L14+L15+L16+L13)/L12 -> -0.0037028145 | M18: =-(M14+M15+M16+M13)/M12 -> -0.00018920211 | N18: =-(N14+N15+N16+N13)/N12 -> 0.0019739925 | O18: =-(O14+O15+O16+O13)/O12 -> 0.0022185394 | P18: =-(P14+P15+P16+P13)/P12 -> 0.0021184423 | Q18: =-(Q14+Q15+Q16+Q13)/Q12 -> 0.0019048749 | ... S18: =-(S14+S15+S16+S13)/S12 -> 0.0011820327
B19: Period fraction (H2-26 share of FY26 FCF) | J19: =H2Share -> 0.668 | K19: 1 | L19: 1 | M19: 1 | N19: 1 | O19: 1 | P19: 1 | Q19: 1 | R19: 1 | S19: 1
B20: FCFF in valuation period | J20: =J17*J19 -> 491.39413 | K20: =K17*K19 -> 788.19471 | L20: =L17*L19 -> 833.77087 | M20: =M17*M19 -> 874.52517 | N20: =N17*N19 -> 912.40657 | O20: =O17*O19 -> 947.45514 | P20: =P17*P19 -> 982.02715 | Q20: =Q17*Q19 -> 1015.6365 | ... S20: =S17*S19 -> 1078.8535
B21: Discount period (years from 30-Jun-2026, mid-period) | J21: 0.25 | K21: =2027-2026 -> 1 | L21: =2028-2026 -> 2 | M21: =2029-2026 -> 3 | N21: =2030-2026 -> 4 | O21: =2031-2026 -> 5 | P21: =2032-2026 -> 6 | Q21: =2033-2026 -> 7 | R21: =2034-2026 -> 8 | S21: =2035-2026 -> 9
B22: Discount factor at WACC | J22: =(1+WACC)^-J21 -> 0.97750655 | K22: =(1+WACC)^-K21 -> 0.91301668 | L22: =(1+WACC)^-L21 -> 0.83359946 | M22: =(1+WACC)^-M21 -> 0.76109022 | N22: =(1+WACC)^-N21 -> 0.69488807 | O22: =(1+WACC)^-O21 -> 0.6344444 | P22: =(1+WACC)^-P21 -> 0.57925832 | Q22: =(1+WACC)^-Q21 -> 0.52887251 | ... S22: =(1+WACC)^-S21 -> 0.44086784
B23: Present value of FCFF | J23: =J20*J22 -> 480.34098 | K23: =K20*K22 -> 719.63492 | L23: =L20*L22 -> 695.03095 | M23: =M20*M22 -> 665.59255 | N23: =N20*N22 -> 634.02044 | O23: =O20*O22 -> 601.10761 | P23: =P20*P22 -> 568.84739 | Q23: =Q20*Q22 -> 537.14221 | ... S23: =S20*S22 -> 475.6318
B24: Memo: EBITDA | J24: =IS!J33 -> 970.03191 | K24: =IS!K33 -> 1031.2553 | L24: =IS!L33 -> 1091.2857 | M24: =IS!M33 -> 1145.2726 | N24: =IS!N33 -> 1194.6983 | O24: =IS!O33 -> 1240.2902 | P24: =IS!P33 -> 1285.1411 | Q24: =IS!Q33 -> 1328.6807 | ... S24: =IS!S33 -> 1410.3925
B25: Free cash flow to equity (FCFE) - discounted at the cost of equity
B26: FCFE (CFO - capex + net borrowing) | J26: =CF!J20+CF!J22+CF!J27+CF!J28 -> 601.75485 | K26: =CF!K20+CF!K22+CF!K27+CF!K28 -> 631.37459 | L26: =CF!L20+CF!L22+CF!L27+CF!L28 -> 675.57884 | M26: =CF!M20+CF!M22+CF!M27+CF!M28 -> 781.58226 | N26: =CF!N20+CF!N22+CF!N27+CF!N28 -> 930.02964 | O26: =CF!O20+CF!O22+CF!O27+CF!O28 -> 963.49397 | P26: =CF!P20+CF!P22+CF!P27+CF!P28 -> 997.29812 | Q26: =CF!Q20+CF!Q22+CF!Q27+CF!Q28 -> 1032.4296 | ... S26: =CF!S20+CF!S22+CF!S27+CF!S28 -> 1098.52
B27: FCFE in valuation period | J27: =J26*J19 -> 401.97224 | K27: =K26*K19 -> 631.37459 | L27: =L26*L19 -> 675.57884 | M27: =M26*M19 -> 781.58226 | N27: =N26*N19 -> 930.02964 | O27: =O26*O19 -> 963.49397 | P27: =P26*P19 -> 997.29812 | Q27: =Q26*Q19 -> 1032.4296 | ... S27: =S26*S19 -> 1098.52
B28: Present value at Ke | J28: =J27*(1+Ke)^-J21 -> 392.11849 | K28: =K27*(1+Ke)^-K21 -> 571.70519 | L28: =L27*(1+Ke)^-L21 -> 553.91881 | M28: =M27*(1+Ke)^-M21 -> 580.26958 | N28: =N27*(1+Ke)^-N21 -> 625.22587 | O28: =O27*(1+Ke)^-O21 -> 586.50833 | P28: =P27*(1+Ke)^-P21 -> 549.712 | Q28: =Q27*(1+Ke)^-Q21 -> 515.29475 | ... S28: =S27*(1+Ke)^-S21 -> 449.54512
B29: Residual income (clean surplus) - discounted at the cost of equity
B30: Net income | J30: =IS!J23 -> 636.78363 | K30: =IS!K23 -> 699.82968 | L30: =IS!L23 -> 753.92429 | M30: =IS!M23 -> 803.99598 | N30: =IS!N23 -> 845.4119 | O30: =IS!O23 -> 876.01482 | P30: =IS!P23 -> 906.66147 | Q30: =IS!Q23 -> 938.49203 | ... S30: =IS!S23 -> 997.99596
B31: Opening book equity | J31: =BookEquityJun -> 1384.674 | K31: =Equity!K7 -> 1384.894 | L31: =Equity!L7 -> 1491.5807 | M31: =Equity!M7 -> 1609.7367 | N31: =Equity!N7 -> 1742.4183 | O31: =Equity!O7 -> 1632.0564 | P31: =Equity!P7 -> 1589.2392 | Q31: =Equity!Q7 -> 1544.8285 | R31: =Equity!R7 -> 1498.6391 | S31: =Equity!S7 -> 1450.6137
B32: Residual income = NI - Ke x opening book equity | J32: =0.5*J30-Ke*0.5*J31 -> 246.13196 | K32: =K30-Ke*K31 -> 555.28702 | L32: =L30-Ke*L31 -> 598.24663 | M32: =M30-Ke*M31 -> 635.98627 | N32: =N30-Ke*N31 -> 663.55409 | O32: =O30-Ke*O31 -> 705.67559 | P32: =P30-Ke*P31 -> 740.79111 | Q32: =Q30-Ke*Q31 -> 777.25685 | R32: =R30-Ke*R31 -> 812.60717 | S32: =S30-Ke*S31 -> 846.59406
B33: Present value at Ke | J33: =J32*(1+Ke)^-J21 -> 240.09841 | K33: =K32*(1+Ke)^-K21 -> 502.80844 | L33: =L32*(1+Ke)^-L21 -> 490.51279 | M33: =M32*(1+Ke)^-M21 -> 472.17485 | N33: =N32*(1+Ke)^-N21 -> 446.08383 | O33: =O32*(1+Ke)^-O21 -> 429.56637 | P33: =P32*(1+Ke)^-P21 -> 408.32501 | Q33: =Q32*(1+Ke)^-Q21 -> 387.93576 | ... S33: =S32*(1+Ke)^-S21 -> 346.44998
B34: HEYDUDE reporting unit - fair value for the ASC 350 impairment test
B35: HEYDUDE revenue | J35: =Rev_Build!J24 -> 694.67245 | K35: =Rev_Build!K24 -> 693.87172 | L35: =Rev_Build!L24 -> 701.25169 | M35: =Rev_Build!M24 -> 716.7096 | N35: =Rev_Build!N24 -> 734.90697 | O35: =Rev_Build!O24 -> 753.51895 | P35: =Rev_Build!P24 -> 772.54711 | Q35: =Rev_Build!Q24 -> 791.99403 | ... S35: =Rev_Build!S24 -> 832.15955
B36: Segment EBIT | J36: =IS!J44 -> 62.52052 | K36: =IS!K44 -> 72.856531 | L36: =IS!L44 -> 84.150203 | M36: =IS!M44 -> 89.588699 | N36: =IS!N44 -> 91.863371 | O36: =IS!O44 -> 94.189869 | P36: =IS!P44 -> 96.568388 | Q36: =IS!Q44 -> 98.999253 | ... S36: =IS!S44 -> 104.01994
B37: Less: allocated corporate costs | J37: =-J35*Inputs!J71*HD_CorpAlloc -> -24.313536 | K37: =-K35*Inputs!K71*HD_CorpAlloc -> -24.28551 | L37: =-L35*Inputs!L71*HD_CorpAlloc -> -24.543809 | M37: =-M35*Inputs!M71*HD_CorpAlloc -> -25.084836 | N37: =-N35*Inputs!N71*HD_CorpAlloc -> -25.721744 | O37: =-O35*Inputs!O71*HD_CorpAlloc -> -26.373163 | P37: =-P35*Inputs!P71*HD_CorpAlloc -> -27.039149 | Q37: =-Q35*Inputs!Q71*HD_CorpAlloc -> -27.719791 | ... S37: =-S35*Inputs!S71*HD_CorpAlloc -> -29.125584
B38: NOPAT | J38: =(J36+J37)*(1-Inputs!J103) -> 31.329727 | K38: =(K36+K37)*(1-Inputs!K103) -> 39.828237 | L38: =(L36+L37)*(1-Inputs!L103) -> 48.877243 | M38: =(M36+M37)*(1-Inputs!M103) -> 52.893168 | N38: =(N36+N37)*(1-Inputs!N103) -> 54.236134 | O38: =(O36+O37)*(1-Inputs!O103) -> 55.609699 | P38: =(P36+P37)*(1-Inputs!P103) -> 57.013976 | Q38: =(Q36+Q37)*(1-Inputs!Q103) -> 58.449159 | ... S38: =(S36+S37)*(1-Inputs!S103) -> 61.413375
B39: Free cash flow (after reinvestment) | J39: =J38*(1-HD_Reinvest)*J19 -> 18.835432 | K39: =K38*(1-HD_Reinvest)*K19 -> 35.845413 | L39: =L38*(1-HD_Reinvest)*L19 -> 43.989519 | M39: =M38*(1-HD_Reinvest)*M19 -> 47.603851 | N39: =N38*(1-HD_Reinvest)*N19 -> 48.812521 | O39: =O38*(1-HD_Reinvest)*O19 -> 50.048729 | P39: =P38*(1-HD_Reinvest)*P19 -> 51.312579 | Q39: =Q38*(1-HD_Reinvest)*Q19 -> 52.604243 | ... S39: =S38*(1-HD_Reinvest)*S19 -> 55.272037
B40: Present value at WACC + HEYDUDE premium | J40: =J39*(1+WACC+HD_Premium)^-J21 -> 18.369971 | K40: =K39*(1+WACC+HD_Premium)^-K21 -> 32.431357 | L40: =L39*(1+WACC+HD_Premium)^-L21 -> 36.009099 | M40: =M39*(1+WACC+HD_Premium)^-M21 -> 35.256294 | N40: =N39*(1+WACC+HD_Premium)^-N21 -> 32.708252 | O40: =O39*(1+WACC+HD_Premium)^-O21 -> 30.342452 | P40: =P39*(1+WACC+HD_Premium)^-P21 -> 28.14576 | Q40: =Q39*(1+WACC+HD_Premium)^-Q21 -> 26.106067 | ... S40: =S39*(1+WACC+HD_Premium)^-S21 -> 22.453766

Sheet Sensitivity
B1: Valuation sensitivities
B2: Crocs, Inc. (NASDAQ: CROX) | US$ millions unless stated
B4: Operating data-table inputs (leave at zero)
B5: Revenue growth shift applied to every leaf (all years) | C5: 0
B6: Gross margin shift applied to both brands (all years) | C6: 0
B8: Table 1 - DCF value per share: WACC vs terminal growth (Gordon)
B9: WACC (rows) / terminal growth (columns) | C9: =TG-0.01 -> 0.015 | D9: =TG-0.005 -> 0.02 | E9: =TG+0 -> 0.025 | F9: =TG+0.005 -> 0.03 | G9: =TG+0.01 -> 0.035
B10: =WACC-0.015 -> 0.080270238 | C10: =((SUMPRODUCT(DCF!$J$20:$S$20,(1+$B10)^-DCF!$J$21:$S$21)+FCFF_TV*(1+C$9)/($B10-C$9)*(1+$B10)^-N_End+Tax!$S$15/DTAYears*(1-(1+$B10)^-DTAYears)/$B10*(1+$B10)^-N_End)-DebtFace+CashJun-UTP*UTPPct)*(1+Ke)^RollFwd/SharesDil -> 260.08882 | D10: =((SUMPRODUCT(DCF!$J$20:$S$20,(1+$B10)^-DCF!$J$21:$S$21)+FCFF_TV*(1+D$9)/($B10-D$9)*(1+$B10)^-N_End+Tax!$S$15/DTAYears*(1-(1+$B10)^-DTAYears)/$B10*(1+$B10)^-N_End)-DebtFace+CashJun-UTP*UTPPct)*(1+Ke)^RollFwd/SharesDil -> 274.43613 | E10: =((SUMPRODUCT(DCF!$J$20:$S$20,(1+$B10)^-DCF!$J$21:$S$21)+FCFF_TV*(1+E$9)/($B10-E$9)*(1+$B10)^-N_End+Tax!$S$15/DTAYears*(1-(1+$B10)^-DTAYears)/$B10*(1+$B10)^-N_End)-DebtFace+CashJun-UTP*UTPPct)*(1+Ke)^RollFwd/SharesDil -> 291.37929 | F10: =((SUMPRODUCT(DCF!$J$20:$S$20,(1+$B10)^-DCF!$J$21:$S$21)+FCFF_TV*(1+F$9)/($B10-F$9)*(1+$B10)^-N_End+Tax!$S$15/DTAYears*(1-(1+$B10)^-DTAYears)/$B10*(1+$B10)^-N_End)-DebtFace+CashJun-UTP*UTPPct)*(1+Ke)^RollFwd/SharesDil -> 311.69286 | G10: =((SUMPRODUCT(DCF!$J$20:$S$20,(1+$B10)^-DCF!$J$21:$S$21)+FCFF_TV*(1+G$9)/($B10-G$9)*(1+$B10)^-N_End+Tax!$S$15/DTAYears*(1-(1+$B10)^-DTAYears)/$B10*(1+$B10)^-N_End)-DebtFace+CashJun-UTP*UTPPct)*(1+Ke)^RollFwd/SharesDil -> 336.49361
B11: =WACC-0.01 -> 0.085270238 | C11: =((SUMPRODUCT(DCF!$J$20:$S$20,(1+$B11)^-DCF!$J$21:$S$21)+FCFF_TV*(1+C$9)/($B11-C$9)*(1+$B11)^-N_End+Tax!$S$15/DTAYears*(1-(1+$B11)^-DTAYears)/$B11*(1+$B11)^-N_End)-DebtFace+CashJun-UTP*UTPPct)*(1+Ke)^RollFwd/SharesDil -> 239.17958 | D11: =((SUMPRODUCT(DCF!$J$20:$S$20,(1+$B11)^-DCF!$J$21:$S$21)+FCFF_TV*(1+D$9)/($B11-D$9)*(1+$B11)^-N_End+Tax!$S$15/DTAYears*(1-(1+$B11)^-DTAYears)/$B11*(1+$B11)^-N_End)-DebtFace+CashJun-UTP*UTPPct)*(1+Ke)^RollFwd/SharesDil -> 251.0115 | E11: =((SUMPRODUCT(DCF!$J$20:$S$20,(1+$B11)^-DCF!$J$21:$S$21)+FCFF_TV*(1+E$9)/($B11-E$9)*(1+$B11)^-N_End+Tax!$S$15/DTAYears*(1-(1+$B11)^-DTAYears)/$B11*(1+$B11)^-N_End)-DebtFace+CashJun-UTP*UTPPct)*(1+Ke)^RollFwd/SharesDil -> 264.80657 | F11: =((SUMPRODUCT(DCF!$J$20:$S$20,(1+$B11)^-DCF!$J$21:$S$21)+FCFF_TV*(1+F$9)/($B11-F$9)*(1+$B11)^-N_End+Tax!$S$15/DTAYears*(1-(1+$B11)^-DTAYears)/$B11*(1+$B11)^-N_End)-DebtFace+CashJun-UTP*UTPPct)*(1+Ke)^RollFwd/SharesDil -> 281.09757 | G11: =((SUMPRODUCT(DCF!$J$20:$S$20,(1+$B11)^-DCF!$J$21:$S$21)+FCFF_TV*(1+G$9)/($B11-G$9)*(1+$B11)^-N_End+Tax!$S$15/DTAYears*(1-(1+$B11)^-DTAYears)/$B11*(1+$B11)^-N_End)-DebtFace+CashJun-UTP*UTPPct)*(1+Ke)^RollFwd/SharesDil -> 300.62925
B12: =WACC-0.005 -> 0.090270238 | C12: =((SUMPRODUCT(DCF!$J$20:$S$20,(1+$B12)^-DCF!$J$21:$S$21)+FCFF_TV*(1+C$9)/($B12-C$9)*(1+$B12)^-N_End+Tax!$S$15/DTAYears*(1-(1+$B12)^-DTAYears)/$B12*(1+$B12)^-N_End)-DebtFace+CashJun-UTP*UTPPct)*(1+Ke)^RollFwd/SharesDil -> 221.05306 | D12: =((SUMPRODUCT(DCF!$J$20:$S$20,(1+$B12)^-DCF!$J$21:$S$21)+FCFF_TV*(1+D$9)/($B12-D$9)*(1+$B12)^-N_End+Tax!$S$15/DTAYears*(1-(1+$B12)^-DTAYears)/$B12*(1+$B12)^-N_End)-DebtFace+CashJun-UTP*UTPPct)*(1+Ke)^RollFwd/SharesDil -> 230.91992 | E12: =((SUMPRODUCT(DCF!$J$20:$S$20,(1+$B12)^-DCF!$J$21:$S$21)+FCFF_TV*(1+E$9)/($B12-E$9)*(1+$B12)^-N_End+Tax!$S$15/DTAYears*(1-(1+$B12)^-DTAYears)/$B12*(1+$B12)^-N_End)-DebtFace+CashJun-UTP*UTPPct)*(1+Ke)^RollFwd/SharesDil -> 242.29847 | F12: =((SUMPRODUCT(DCF!$J$20:$S$20,(1+$B12)^-DCF!$J$21:$S$21)+FCFF_TV*(1+F$9)/($B12-F$9)*(1+$B12)^-N_End+Tax!$S$15/DTAYears*(1-(1+$B12)^-DTAYears)/$B12*(1+$B12)^-N_End)-DebtFace+CashJun-UTP*UTPPct)*(1+Ke)^RollFwd/SharesDil -> 255.56495 | G12: =((SUMPRODUCT(DCF!$J$20:$S$20,(1+$B12)^-DCF!$J$21:$S$21)+FCFF_TV*(1+G$9)/($B12-G$9)*(1+$B12)^-N_End+Tax!$S$15/DTAYears*(1-(1+$B12)^-DTAYears)/$B12*(1+$B12)^-N_End)-DebtFace+CashJun-UTP*UTPPct)*(1+Ke)^RollFwd/SharesDil -> 271.23172
B13: =WACC+0 -> 0.095270238 | C13: =((SUMPRODUCT(DCF!$J$20:$S$20,(1+$B13)^-DCF!$J$21:$S$21)+FCFF_TV*(1+C$9)/($B13-C$9)*(1+$B13)^-N_End+Tax!$S$15/DTAYears*(1-(1+$B13)^-DTAYears)/$B13*(1+$B13)^-N_End)-DebtFace+CashJun-UTP*UTPPct)*(1+Ke)^RollFwd/SharesDil -> 205.18967 | D13: =((SUMPRODUCT(DCF!$J$20:$S$20,(1+$B13)^-DCF!$J$21:$S$21)+FCFF_TV*(1+D$9)/($B13-D$9)*(1+$B13)^-N_End+Tax!$S$15/DTAYears*(1-(1+$B13)^-DTAYears)/$B13*(1+$B13)^-N_End)-DebtFace+CashJun-UTP*UTPPct)*(1+Ke)^RollFwd/SharesDil -> 213.49783 | E13: =((SUMPRODUCT(DCF!$J$20:$S$20,(1+$B13)^-DCF!$J$21:$S$21)+FCFF_TV*(1+E$9)/($B13-E$9)*(1+$B13)^-N_End+Tax!$S$15/DTAYears*(1-(1+$B13)^-DTAYears)/$B13*(1+$B13)^-N_End)-DebtFace+CashJun-UTP*UTPPct)*(1+Ke)^RollFwd/SharesDil -> 222.98832 | F13: =((SUMPRODUCT(DCF!$J$20:$S$20,(1+$B13)^-DCF!$J$21:$S$21)+FCFF_TV*(1+F$9)/($B13-F$9)*(1+$B13)^-N_End+Tax!$S$15/DTAYears*(1-(1+$B13)^-DTAYears)/$B13*(1+$B13)^-N_End)-DebtFace+CashJun-UTP*UTPPct)*(1+Ke)^RollFwd/SharesDil -> 233.93283 | G13: =((SUMPRODUCT(DCF!$J$20:$S$20,(1+$B13)^-DCF!$J$21:$S$21)+FCFF_TV*(1+G$9)/($B13-G$9)*(1+$B13)^-N_End+Tax!$S$15/DTAYears*(1-(1+$B13)^-DTAYears)/$B13*(1+$B13)^-N_End)-DebtFace+CashJun-UTP*UTPPct)*(1+Ke)^RollFwd/SharesDil -> 246.69325
B14: =WACC+0.005 -> 0.10027024 | C14: =((SUMPRODUCT(DCF!$J$20:$S$20,(1+$B14)^-DCF!$J$21:$S$21)+FCFF_TV*(1+C$9)/($B14-C$9)*(1+$B14)^-N_End+Tax!$S$15/DTAYears*(1-(1+$B14)^-DTAYears)/$B14*(1+$B14)^-N_End)-DebtFace+CashJun-UTP*UTPPct)*(1+Ke)^RollFwd/SharesDil -> 191.1916 | D14: =((SUMPRODUCT(DCF!$J$20:$S$20,(1+$B14)^-DCF!$J$21:$S$21)+FCFF_TV*(1+D$9)/($B14-D$9)*(1+$B14)^-N_End+Tax!$S$15/DTAYears*(1-(1+$B14)^-DTAYears)/$B14*(1+$B14)^-N_End)-DebtFace+CashJun-UTP*UTPPct)*(1+Ke)^RollFwd/SharesDil -> 198.24693 | E14: =((SUMPRODUCT(DCF!$J$20:$S$20,(1+$B14)^-DCF!$J$21:$S$21)+FCFF_TV*(1+E$9)/($B14-E$9)*(1+$B14)^-N_End+Tax!$S$15/DTAYears*(1-(1+$B14)^-DTAYears)/$B14*(1+$B14)^-N_End)-DebtFace+CashJun-UTP*UTPPct)*(1+Ke)^RollFwd/SharesDil -> 206.2396 | F14: =((SUMPRODUCT(DCF!$J$20:$S$20,(1+$B14)^-DCF!$J$21:$S$21)+FCFF_TV*(1+F$9)/($B14-F$9)*(1+$B14)^-N_End+Tax!$S$15/DTAYears*(1-(1+$B14)^-DTAYears)/$B14*(1+$B14)^-N_End)-DebtFace+CashJun-UTP*UTPPct)*(1+Ke)^RollFwd/SharesDil -> 215.36968 | G14: =((SUMPRODUCT(DCF!$J$20:$S$20,(1+$B14)^-DCF!$J$21:$S$21)+FCFF_TV*(1+G$9)/($B14-G$9)*(1+$B14)^-N_End+Tax!$S$15/DTAYears*(1-(1+$B14)^-DTAYears)/$B14*(1+$B14)^-N_End)-DebtFace+CashJun-UTP*UTPPct)*(1+Ke)^RollFwd/SharesDil -> 225.89858
B15: =WACC+0.01 -> 0.10527024 | C15: =((SUMPRODUCT(DCF!$J$20:$S$20,(1+$B15)^-DCF!$J$21:$S$21)+FCFF_TV*(1+C$9)/($B15-C$9)*(1+$B15)^-N_End+Tax!$S$15/DTAYears*(1-(1+$B15)^-DTAYears)/$B15*(1+$B15)^-N_End)-DebtFace+CashJun-UTP*UTPPct)*(1+Ke)^RollFwd/SharesDil -> 178.74912 | D15: =((SUMPRODUCT(DCF!$J$20:$S$20,(1+$B15)^-DCF!$J$21:$S$21)+FCFF_TV*(1+D$9)/($B15-D$9)*(1+$B15)^-N_End+Tax!$S$15/DTAYears*(1-(1+$B15)^-DTAYears)/$B15*(1+$B15)^-N_End)-DebtFace+CashJun-UTP*UTPPct)*(1+Ke)^RollFwd/SharesDil -> 184.78568 | E15: =((SUMPRODUCT(DCF!$J$20:$S$20,(1+$B15)^-DCF!$J$21:$S$21)+FCFF_TV*(1+E$9)/($B15-E$9)*(1+$B15)^-N_End+Tax!$S$15/DTAYears*(1-(1+$B15)^-DTAYears)/$B15*(1+$B15)^-N_End)-DebtFace+CashJun-UTP*UTPPct)*(1+Ke)^RollFwd/SharesDil -> 191.57428 | F15: =((SUMPRODUCT(DCF!$J$20:$S$20,(1+$B15)^-DCF!$J$21:$S$21)+FCFF_TV*(1+F$9)/($B15-F$9)*(1+$B15)^-N_End+Tax!$S$15/DTAYears*(1-(1+$B15)^-DTAYears)/$B15*(1+$B15)^-N_End)-DebtFace+CashJun-UTP*UTPPct)*(1+Ke)^RollFwd/SharesDil -> 199.26477 | G15: =((SUMPRODUCT(DCF!$J$20:$S$20,(1+$B15)^-DCF!$J$21:$S$21)+FCFF_TV*(1+G$9)/($B15-G$9)*(1+$B15)^-N_End+Tax!$S$15/DTAYears*(1-(1+$B15)^-DTAYears)/$B15*(1+$B15)^-N_End)-DebtFace+CashJun-UTP*UTPPct)*(1+Ke)^RollFwd/SharesDil -> 208.04968
B16: =WACC+0.015 -> 0.11027024 | C16: =((SUMPRODUCT(DCF!$J$20:$S$20,(1+$B16)^-DCF!$J$21:$S$21)+FCFF_TV*(1+C$9)/($B16-C$9)*(1+$B16)^-N_End+Tax!$S$15/DTAYears*(1-(1+$B16)^-DTAYears)/$B16*(1+$B16)^-N_End)-DebtFace+CashJun-UTP*UTPPct)*(1+Ke)^RollFwd/SharesDil -> 167.61743 | D16: =((SUMPRODUCT(DCF!$J$20:$S$20,(1+$B16)^-DCF!$J$21:$S$21)+FCFF_TV*(1+D$9)/($B16-D$9)*(1+$B16)^-N_End+Tax!$S$15/DTAYears*(1-(1+$B16)^-DTAYears)/$B16*(1+$B16)^-N_End)-DebtFace+CashJun-UTP*UTPPct)*(1+Ke)^RollFwd/SharesDil -> 172.81701 | E16: =((SUMPRODUCT(DCF!$J$20:$S$20,(1+$B16)^-DCF!$J$21:$S$21)+FCFF_TV*(1+E$9)/($B16-E$9)*(1+$B16)^-N_End+Tax!$S$15/DTAYears*(1-(1+$B16)^-DTAYears)/$B16*(1+$B16)^-N_End)-DebtFace+CashJun-UTP*UTPPct)*(1+Ke)^RollFwd/SharesDil -> 178.62637 | F16: =((SUMPRODUCT(DCF!$J$20:$S$20,(1+$B16)^-DCF!$J$21:$S$21)+FCFF_TV*(1+F$9)/($B16-F$9)*(1+$B16)^-N_End+Tax!$S$15/DTAYears*(1-(1+$B16)^-DTAYears)/$B16*(1+$B16)^-N_End)-DebtFace+CashJun-UTP*UTPPct)*(1+Ke)^RollFwd/SharesDil -> 185.15945 | G16: =((SUMPRODUCT(DCF!$J$20:$S$20,(1+$B16)^-DCF!$J$21:$S$21)+FCFF_TV*(1+G$9)/($B16-G$9)*(1+$B16)^-N_End+Tax!$S$15/DTAYears*(1-(1+$B16)^-DTAYears)/$B16*(1+$B16)^-N_End)-DebtFace+CashJun-UTP*UTPPct)*(1+Ke)^RollFwd/SharesDil -> 192.56048
B19: Table 2 - value per share: WACC vs exit EV/EBITDA multiple
B20: WACC (rows) / exit multiple (columns) | C20: =ExitMultiple-2 -> 6 | D20: =ExitMultiple-1 -> 7 | E20: =ExitMultiple+0 -> 8 | F20: =ExitMultiple+1 -> 9 | G20: =ExitMultiple+2 -> 10
B21: =WACC-0.015 -> 0.080270238 | C21: =((SUMPRODUCT(DCF!$J$20:$S$20,(1+$B21)^-DCF!$J$21:$S$21)+DCF!$S$24*C$20*(1+$B21)^-N_End+Tax!$S$15/DTAYears*(1-(1+$B21)^-DTAYears)/$B21*(1+$B21)^-N_End)-DebtFace+CashJun-UTP*UTPPct)*(1+Ke)^RollFwd/SharesDil -> 183.76583 | D21: =((SUMPRODUCT(DCF!$J$20:$S$20,(1+$B21)^-DCF!$J$21:$S$21)+DCF!$S$24*D$20*(1+$B21)^-N_End+Tax!$S$15/DTAYears*(1-(1+$B21)^-DTAYears)/$B21*(1+$B21)^-N_End)-DebtFace+CashJun-UTP*UTPPct)*(1+Ke)^RollFwd/SharesDil -> 198.12764 | E21: =((SUMPRODUCT(DCF!$J$20:$S$20,(1+$B21)^-DCF!$J$21:$S$21)+DCF!$S$24*E$20*(1+$B21)^-N_End+Tax!$S$15/DTAYears*(1-(1+$B21)^-DTAYears)/$B21*(1+$B21)^-N_End)-DebtFace+CashJun-UTP*UTPPct)*(1+Ke)^RollFwd/SharesDil -> 212.48945 | F21: =((SUMPRODUCT(DCF!$J$20:$S$20,(1+$B21)^-DCF!$J$21:$S$21)+DCF!$S$24*F$20*(1+$B21)^-N_End+Tax!$S$15/DTAYears*(1-(1+$B21)^-DTAYears)/$B21*(1+$B21)^-N_End)-DebtFace+CashJun-UTP*UTPPct)*(1+Ke)^RollFwd/SharesDil -> 226.85127 | G21: =((SUMPRODUCT(DCF!$J$20:$S$20,(1+$B21)^-DCF!$J$21:$S$21)+DCF!$S$24*G$20*(1+$B21)^-N_End+Tax!$S$15/DTAYears*(1-(1+$B21)^-DTAYears)/$B21*(1+$B21)^-N_End)-DebtFace+CashJun-UTP*UTPPct)*(1+Ke)^RollFwd/SharesDil -> 241.21308
B22: =WACC-0.01 -> 0.085270238 | C22: =((SUMPRODUCT(DCF!$J$20:$S$20,(1+$B22)^-DCF!$J$21:$S$21)+DCF!$S$24*C$20*(1+$B22)^-N_End+Tax!$S$15/DTAYears*(1-(1+$B22)^-DTAYears)/$B22*(1+$B22)^-N_End)-DebtFace+CashJun-UTP*UTPPct)*(1+Ke)^RollFwd/SharesDil -> 177.19824 | D22: =((SUMPRODUCT(DCF!$J$20:$S$20,(1+$B22)^-DCF!$J$21:$S$21)+DCF!$S$24*D$20*(1+$B22)^-N_End+Tax!$S$15/DTAYears*(1-(1+$B22)^-DTAYears)/$B22*(1+$B22)^-N_End)-DebtFace+CashJun-UTP*UTPPct)*(1+Ke)^RollFwd/SharesDil -> 190.94363 | E22: =((SUMPRODUCT(DCF!$J$20:$S$20,(1+$B22)^-DCF!$J$21:$S$21)+DCF!$S$24*E$20*(1+$B22)^-N_End+Tax!$S$15/DTAYears*(1-(1+$B22)^-DTAYears)/$B22*(1+$B22)^-N_End)-DebtFace+CashJun-UTP*UTPPct)*(1+Ke)^RollFwd/SharesDil -> 204.68903 | F22: =((SUMPRODUCT(DCF!$J$20:$S$20,(1+$B22)^-DCF!$J$21:$S$21)+DCF!$S$24*F$20*(1+$B22)^-N_End+Tax!$S$15/DTAYears*(1-(1+$B22)^-DTAYears)/$B22*(1+$B22)^-N_End)-DebtFace+CashJun-UTP*UTPPct)*(1+Ke)^RollFwd/SharesDil -> 218.43442 | G22: =((SUMPRODUCT(DCF!$J$20:$S$20,(1+$B22)^-DCF!$J$21:$S$21)+DCF!$S$24*G$20*(1+$B22)^-N_End+Tax!$S$15/DTAYears*(1-(1+$B22)^-DTAYears)/$B22*(1+$B22)^-N_End)-DebtFace+CashJun-UTP*UTPPct)*(1+Ke)^RollFwd/SharesDil -> 232.17981
B23: =WACC-0.005 -> 0.090270238 | C23: =((SUMPRODUCT(DCF!$J$20:$S$20,(1+$B23)^-DCF!$J$21:$S$21)+DCF!$S$24*C$20*(1+$B23)^-N_End+Tax!$S$15/DTAYears*(1-(1+$B23)^-DTAYears)/$B23*(1+$B23)^-N_End)-DebtFace+CashJun-UTP*UTPPct)*(1+Ke)^RollFwd/SharesDil -> 170.90571 | D23: =((SUMPRODUCT(DCF!$J$20:$S$20,(1+$B23)^-DCF!$J$21:$S$21)+DCF!$S$24*D$20*(1+$B23)^-N_End+Tax!$S$15/DTAYears*(1-(1+$B23)^-DTAYears)/$B23*(1+$B23)^-N_End)-DebtFace+CashJun-UTP*UTPPct)*(1+Ke)^RollFwd/SharesDil -> 184.06379 | E23: =((SUMPRODUCT(DCF!$J$20:$S$20,(1+$B23)^-DCF!$J$21:$S$21)+DCF!$S$24*E$20*(1+$B23)^-N_End+Tax!$S$15/DTAYears*(1-(1+$B23)^-DTAYears)/$B23*(1+$B23)^-N_End)-DebtFace+CashJun-UTP*UTPPct)*(1+Ke)^RollFwd/SharesDil -> 197.22188 | F23: =((SUMPRODUCT(DCF!$J$20:$S$20,(1+$B23)^-DCF!$J$21:$S$21)+DCF!$S$24*F$20*(1+$B23)^-N_End+Tax!$S$15/DTAYears*(1-(1+$B23)^-DTAYears)/$B23*(1+$B23)^-N_End)-DebtFace+CashJun-UTP*UTPPct)*(1+Ke)^RollFwd/SharesDil -> 210.37996 | G23: =((SUMPRODUCT(DCF!$J$20:$S$20,(1+$B23)^-DCF!$J$21:$S$21)+DCF!$S$24*G$20*(1+$B23)^-N_End+Tax!$S$15/DTAYears*(1-(1+$B23)^-DTAYears)/$B23*(1+$B23)^-N_End)-DebtFace+CashJun-UTP*UTPPct)*(1+Ke)^RollFwd/SharesDil -> 223.53804
B24: =WACC+0 -> 0.095270238 | C24: =((SUMPRODUCT(DCF!$J$20:$S$20,(1+$B24)^-DCF!$J$21:$S$21)+DCF!$S$24*C$20*(1+$B24)^-N_End+Tax!$S$15/DTAYears*(1-(1+$B24)^-DTAYears)/$B24*(1+$B24)^-N_End)-DebtFace+CashJun-UTP*UTPPct)*(1+Ke)^RollFwd/SharesDil -> 164.87468 | D24: =((SUMPRODUCT(DCF!$J$20:$S$20,(1+$B24)^-DCF!$J$21:$S$21)+DCF!$S$24*D$20*(1+$B24)^-N_End+Tax!$S$15/DTAYears*(1-(1+$B24)^-DTAYears)/$B24*(1+$B24)^-N_End)-DebtFace+CashJun-UTP*UTPPct)*(1+Ke)^RollFwd/SharesDil -> 177.47307 | E24: =((SUMPRODUCT(DCF!$J$20:$S$20,(1+$B24)^-DCF!$J$21:$S$21)+DCF!$S$24*E$20*(1+$B24)^-N_End+Tax!$S$15/DTAYears*(1-(1+$B24)^-DTAYears)/$B24*(1+$B24)^-N_End)-DebtFace+CashJun-UTP*UTPPct)*(1+Ke)^RollFwd/SharesDil -> 190.07146 | F24: =((SUMPRODUCT(DCF!$J$20:$S$20,(1+$B24)^-DCF!$J$21:$S$21)+DCF!$S$24*F$20*(1+$B24)^-N_End+Tax!$S$15/DTAYears*(1-(1+$B24)^-DTAYears)/$B24*(1+$B24)^-N_End)-DebtFace+CashJun-UTP*UTPPct)*(1+Ke)^RollFwd/SharesDil -> 202.66984 | G24: =((SUMPRODUCT(DCF!$J$20:$S$20,(1+$B24)^-DCF!$J$21:$S$21)+DCF!$S$24*G$20*(1+$B24)^-N_End+Tax!$S$15/DTAYears*(1-(1+$B24)^-DTAYears)/$B24*(1+$B24)^-N_End)-DebtFace+CashJun-UTP*UTPPct)*(1+Ke)^RollFwd/SharesDil -> 215.26823
B25: =WACC+0.005 -> 0.10027024 | C25: =((SUMPRODUCT(DCF!$J$20:$S$20,(1+$B25)^-DCF!$J$21:$S$21)+DCF!$S$24*C$20*(1+$B25)^-N_End+Tax!$S$15/DTAYears*(1-(1+$B25)^-DTAYears)/$B25*(1+$B25)^-N_End)-DebtFace+CashJun-UTP*UTPPct)*(1+Ke)^RollFwd/SharesDil -> 159.09238 | D25: =((SUMPRODUCT(DCF!$J$20:$S$20,(1+$B25)^-DCF!$J$21:$S$21)+DCF!$S$24*D$20*(1+$B25)^-N_End+Tax!$S$15/DTAYears*(1-(1+$B25)^-DTAYears)/$B25*(1+$B25)^-N_End)-DebtFace+CashJun-UTP*UTPPct)*(1+Ke)^RollFwd/SharesDil -> 171.15726 | E25: =((SUMPRODUCT(DCF!$J$20:$S$20,(1+$B25)^-DCF!$J$21:$S$21)+DCF!$S$24*E$20*(1+$B25)^-N_End+Tax!$S$15/DTAYears*(1-(1+$B25)^-DTAYears)/$B25*(1+$B25)^-N_End)-DebtFace+CashJun-UTP*UTPPct)*(1+Ke)^RollFwd/SharesDil -> 183.22215 | F25: =((SUMPRODUCT(DCF!$J$20:$S$20,(1+$B25)^-DCF!$J$21:$S$21)+DCF!$S$24*F$20*(1+$B25)^-N_End+Tax!$S$15/DTAYears*(1-(1+$B25)^-DTAYears)/$B25*(1+$B25)^-N_End)-DebtFace+CashJun-UTP*UTPPct)*(1+Ke)^RollFwd/SharesDil -> 195.28703 | G25: =((SUMPRODUCT(DCF!$J$20:$S$20,(1+$B25)^-DCF!$J$21:$S$21)+DCF!$S$24*G$20*(1+$B25)^-N_End+Tax!$S$15/DTAYears*(1-(1+$B25)^-DTAYears)/$B25*(1+$B25)^-N_End)-DebtFace+CashJun-UTP*UTPPct)*(1+Ke)^RollFwd/SharesDil -> 207.35192
B26: =WACC+0.01 -> 0.10527024 | C26: =((SUMPRODUCT(DCF!$J$20:$S$20,(1+$B26)^-DCF!$J$21:$S$21)+DCF!$S$24*C$20*(1+$B26)^-N_End+Tax!$S$15/DTAYears*(1-(1+$B26)^-DTAYears)/$B26*(1+$B26)^-N_End)-DebtFace+CashJun-UTP*UTPPct)*(1+Ke)^RollFwd/SharesDil -> 153.54671 | D26: =((SUMPRODUCT(DCF!$J$20:$S$20,(1+$B26)^-DCF!$J$21:$S$21)+DCF!$S$24*D$20*(1+$B26)^-N_End+Tax!$S$15/DTAYears*(1-(1+$B26)^-DTAYears)/$B26*(1+$B26)^-N_End)-DebtFace+CashJun-UTP*UTPPct)*(1+Ke)^RollFwd/SharesDil -> 165.10295 | E26: =((SUMPRODUCT(DCF!$J$20:$S$20,(1+$B26)^-DCF!$J$21:$S$21)+DCF!$S$24*E$20*(1+$B26)^-N_End+Tax!$S$15/DTAYears*(1-(1+$B26)^-DTAYears)/$B26*(1+$B26)^-N_End)-DebtFace+CashJun-UTP*UTPPct)*(1+Ke)^RollFwd/SharesDil -> 176.65919 | F26: =((SUMPRODUCT(DCF!$J$20:$S$20,(1+$B26)^-DCF!$J$21:$S$21)+DCF!$S$24*F$20*(1+$B26)^-N_End+Tax!$S$15/DTAYears*(1-(1+$B26)^-DTAYears)/$B26*(1+$B26)^-N_End)-DebtFace+CashJun-UTP*UTPPct)*(1+Ke)^RollFwd/SharesDil -> 188.21543 | G26: =((SUMPRODUCT(DCF!$J$20:$S$20,(1+$B26)^-DCF!$J$21:$S$21)+DCF!$S$24*G$20*(1+$B26)^-N_End+Tax!$S$15/DTAYears*(1-(1+$B26)^-DTAYears)/$B26*(1+$B26)^-N_End)-DebtFace+CashJun-UTP*UTPPct)*(1+Ke)^RollFwd/SharesDil -> 199.77168
B27: =WACC+0.015 -> 0.11027024 | C27: =((SUMPRODUCT(DCF!$J$20:$S$20,(1+$B27)^-DCF!$J$21:$S$21)+DCF!$S$24*C$20*(1+$B27)^-N_End+Tax!$S$15/DTAYears*(1-(1+$B27)^-DTAYears)/$B27*(1+$B27)^-N_End)-DebtFace+CashJun-UTP*UTPPct)*(1+Ke)^RollFwd/SharesDil -> 148.22625 | D27: =((SUMPRODUCT(DCF!$J$20:$S$20,(1+$B27)^-DCF!$J$21:$S$21)+DCF!$S$24*D$20*(1+$B27)^-N_End+Tax!$S$15/DTAYears*(1-(1+$B27)^-DTAYears)/$B27*(1+$B27)^-N_End)-DebtFace+CashJun-UTP*UTPPct)*(1+Ke)^RollFwd/SharesDil -> 159.29745 | E27: =((SUMPRODUCT(DCF!$J$20:$S$20,(1+$B27)^-DCF!$J$21:$S$21)+DCF!$S$24*E$20*(1+$B27)^-N_End+Tax!$S$15/DTAYears*(1-(1+$B27)^-DTAYears)/$B27*(1+$B27)^-N_End)-DebtFace+CashJun-UTP*UTPPct)*(1+Ke)^RollFwd/SharesDil -> 170.36864 | F27: =((SUMPRODUCT(DCF!$J$20:$S$20,(1+$B27)^-DCF!$J$21:$S$21)+DCF!$S$24*F$20*(1+$B27)^-N_End+Tax!$S$15/DTAYears*(1-(1+$B27)^-DTAYears)/$B27*(1+$B27)^-N_End)-DebtFace+CashJun-UTP*UTPPct)*(1+Ke)^RollFwd/SharesDil -> 181.43984 | G27: =((SUMPRODUCT(DCF!$J$20:$S$20,(1+$B27)^-DCF!$J$21:$S$21)+DCF!$S$24*G$20*(1+$B27)^-N_End+Tax!$S$15/DTAYears*(1-(1+$B27)^-DTAYears)/$B27*(1+$B27)^-N_End)-DebtFace+CashJun-UTP*UTPPct)*(1+Ke)^RollFwd/SharesDil -> 192.51103
B30: Table 3 - DCF value per share: revenue growth shift (rows) vs gross margin shift (columns) - Excel data table re-running the full model
B31: =ValuePerShare -> 222.98832 | C31: -0.02 | D31: -0.01 | E31: 0 | F31: 0.01 | G31: 0.02
B32: -0.03 | C32: 157.45246 | D32: 166.31031 | E32: 175.16951 | F32: 184.02769 | G32: 192.88587
B33: -0.02 | C33: 170.84863 | D33: 180.39114 | E33: 189.93277 | F33: 199.4744 | G33: 209.01603
B34: -0.01 | C34: 185.28267 | D34: 195.56397 | E34: 205.8442 | F34: 216.12444 | G34: 226.40467
B35: 0 | C35: 200.83192 | D35: 211.91012 | E35: 222.98832 | F35: 234.06652 | G35: 245.14472
B36: 0.01 | C36: 217.57513 | D36: 229.51516 | E36: 241.45519 | F36: 253.39522 | G36: 265.33524
B37: 0.02 | C37: 235.59972 | D37: 248.47024 | E37: 261.34076 | F37: 274.21127 | G37: 287.08179
B38: 0.03 | C38: 254.9976 | D38: 268.87239 | E38: 282.74718 | F38: 296.62197 | G38: 310.49676
B40: Table 4 - value per share by treatment of the $640m uncertain tax positions
B41: Share of UTP treated as debt | C41: 0 | D41: 0.5 | E41: 1
B42: Value per share | C42: =((SUMPRODUCT(DCF!$J$20:$S$20,(1+WACC)^-DCF!$J$21:$S$21)+FCFF_TV*(1+TG)/(WACC-TG)*(1+WACC)^-N_End+Tax!$S$15/DTAYears*(1-(1+WACC)^-DTAYears)/WACC*(1+WACC)^-N_End)-DebtFace+CashJun-UTP*$C$41)*(1+Ke)^RollFwd/SharesDil -> 236.55027 | D42: =((SUMPRODUCT(DCF!$J$20:$S$20,(1+WACC)^-DCF!$J$21:$S$21)+FCFF_TV*(1+TG)/(WACC-TG)*(1+WACC)^-N_End+Tax!$S$15/DTAYears*(1-(1+WACC)^-DTAYears)/WACC*(1+WACC)^-N_End)-DebtFace+CashJun-UTP*$D$41)*(1+Ke)^RollFwd/SharesDil -> 229.76929 | E42: =((SUMPRODUCT(DCF!$J$20:$S$20,(1+WACC)^-DCF!$J$21:$S$21)+FCFF_TV*(1+TG)/(WACC-TG)*(1+WACC)^-N_End+Tax!$S$15/DTAYears*(1-(1+WACC)^-DTAYears)/WACC*(1+WACC)^-N_End)-DebtFace+CashJun-UTP*$E$41)*(1+Ke)^RollFwd/SharesDil -> 222.98832

Sheet Comps
B1: Trading comparables - US, UK/Europe, India
B2: Crocs, Inc. (NASDAQ: CROX) | US$ millions unless stated
B5: Company | C5: Region | D5: Basis | E5: Mkt cap | F5: Debt ex-leases | G5: Lease liab. | H5: Cash | I5: Revenue | J5: EBITDA reported | K5: Rent add-back | L5: P/E trailing | M5: P/E forward | N5: Growth next FY | O5: Op. margin | P5: EV incl. leases | Q5: EBITDA pre-rent | R5: EV/EBITDA (IFRS 16) | S5: Naive EV/EBITDA | T5: EV/Sales | U5: EBITDA margin
B6: Crocs, Inc. (CROX) | C6: US | D6: US GAAP | E6: 5683.8892 | F6: 1230.885 | G6: 382.964 | H6: 130.354 | I6: 4054.8659 | J6: 926.537 | K6: 104.313 | L6: 10.5191 | M6: 7.9315 | N6: 0.0241 | O6: 0.24221 | P6: =E6+F6+G6-H6 -> 7167.3842 | Q6: =J6+K6 -> 1030.85 | R6: =P6/Q6 -> 6.9528876 | S6: =(E6+F6-H6)/J6 -> 7.3223414 | T6: =P6/I6 -> 1.7676008 | U6: =Q6/I6 -> 0.25422542
B7: Deckers Outdoor (DECK) | C7: US | D7: US GAAP | E7: 10638.526 | F7: 0 | G7: 375.194 | H7: 1907.249 | I7: 5527.2888 | J7: 1326.9789 | K7: 88.921 | L7: 11.1124 | M7: 9.3831 | N7: 0.0723 | O7: 0.15233 | P7: =E7+F7+G7-H7 -> 9106.4715 | Q7: =J7+K7 -> 1415.8999 | R7: =P7/Q7 -> 6.4315786 | S7: =(E7+F7-H7)/J7 -> 6.5798164 | T7: =P7/I7 -> 1.6475476 | U7: =Q7/I7 -> 0.25616536
B8: Steven Madden (SHOO) | C8: US | D8: US GAAP | E8: 3266.9914 | F8: 234.166 | G8: 251.972 | H8: 112.423 | I8: 2740.5361 | J8: 277.484 | K8: 65.152 | L8: 22.3225 | M8: 16.0727 | N8: 0.0819 | O8: 0.06686 | P8: =E8+F8+G8-H8 -> 3640.7064 | Q8: =J8+K8 -> 342.636 | R8: =P8/Q8 -> 10.62558 | S8: =(E8+F8-H8)/J8 -> 12.21236 | T8: =P8/I8 -> 1.328465 | U8: =Q8/I8 -> 0.12502517
B9: Wolverine World Wide (WWW) | C9: US | D9: US GAAP | E9: 1559.2604 | F9: 621.7 | G9: 140.3 | H9: 206.3 | I9: 1951.8001 | J9: 198 | K9: 31.3 | L9: 14.7287 | M9: 10.2705 | N9: 0.0583 | O9: 0.09854 | P9: =E9+F9+G9-H9 -> 2114.9604 | Q9: =J9+K9 -> 229.3 | R9: =P9/Q9 -> 9.2235517 | S9: =(E9+F9-H9)/J9 -> 9.9730323 | T9: =P9/I9 -> 1.0835948 | U9: =Q9/I9 -> 0.11748129
B10: Birkenstock (BIRK) | C10: Europe | D10: IFRS | E10: 5335.8556 | F10: 1266.1659 | G10: 218.7786 | H10: 386.5094 | I10: 2569.856 | J10: 734.391 | K10: 0 | L10: 15.8401 | M10: 11.6858 | N10: 0.1378 | O10: 0.28973 | P10: =E10+F10+G10-H10 -> 6434.2907 | Q10: =J10+K10 -> 734.391 | R10: =P10/Q10 -> 8.7613964 | S10: =(E10+F10-H10)/J10 -> 8.4634917 | T10: =P10/I10 -> 2.5037553 | U10: =Q10/I10 -> 0.28577127
B11: On Holding (ONON) | C11: Europe | D11: IFRS | E11: 9864.3466 | F11: 0 | G11: 624.3714 | H11: 1290.8864 | I11: 3855.6582 | J11: 587.1366 | K11: 0 | L11: 20.7852 | M11: 14.414 | N11: 0.1886 | O11: 0.14019 | P11: =E11+F11+G11-H11 -> 9197.8316 | Q11: =J11+K11 -> 587.1366 | R11: =P11/Q11 -> 15.665574 | S11: =(E11+F11-H11)/J11 -> 14.602156 | T11: =P11/I11 -> 2.3855412 | U11: =Q11/I11 -> 0.15227921
B12: Dr. Martens (DOCS.L) | C12: UK | D12: IFRS | E12: 889.9119 | F12: 331.1891 | G12: 190.7288 | H12: 239.1405 | I12: 1014.5235 | J12: 113.668 | K12: 0 | L12: 35.05 | M12: 11.5372 | N12: 0.0487 | O12: 0.15647 | P12: =E12+F12+G12-H12 -> 1172.6893 | Q12: =J12+K12 -> 113.668 | R12: =P12/Q12 -> 10.316794 | S12: =(E12+F12-H12)/J12 -> 8.6388473 | T12: =P12/I12 -> 1.1559016 | U12: =Q12/I12 -> 0.11204078
B13: Metro Brands (METROBRAND.NS) | C13: India | D13: Ind AS | E13: 2394.6457 | F13: 0 | G13: 163.8708 | H13: 80.6408 | I13: 308.469 | J13: 97.5472 | K13: 0 | L13: 56.4554 | M13: 40.5712 | N13: 0.1623 | O13: 0.18002 | P13: =E13+F13+G13-H13 -> 2477.8757 | Q13: =J13+K13 -> 97.5472 | R13: =P13/Q13 -> 25.401813 | S13: =(E13+F13-H13)/J13 -> 23.7219 | T13: =P13/I13 -> 8.0328192 | U13: =Q13/I13 -> 0.31623016
B14: Relaxo Footwears (RELAXO.NS) | C14: India | D14: Ind AS | E14: 756.5323 | F14: 0 | G14: 24.2799 | H14: 21.5101 | I14: 287.2803 | J14: 41.3679 | K14: 0 | L14: 39.0349 | M14: 29.2958 | N14: 0.094 | O14: 0.09648 | P14: =E14+F14+G14-H14 -> 759.3021 | Q14: =J14+K14 -> 41.3679 | R14: =P14/Q14 -> 18.354862 | S14: =(E14+F14-H14)/J14 -> 17.767936 | T14: =P14/I14 -> 2.6430705 | U14: =Q14/I14 -> 0.14399839
B15: Campus Activewear (CAMPUS.NS) | C15: India | D15: Ind AS | E15: 666.1981 | F15: 3.7863 | G15: 20.8599 | H15: 13.4314 | I15: 189.5273 | J15: 26.3395 | K15: 0 | L15: 41.4345 | M15: 30.5107 | N15: 0.1279 | O15: 0.08323 | P15: =E15+F15+G15-H15 -> 677.4129 | Q15: =J15+K15 -> 26.3395 | R15: =P15/Q15 -> 25.718518 | S15: =(E15+F15-H15)/J15 -> 24.926555 | T15: =P15/I15 -> 3.5742233 | U15: =Q15/I15 -> 0.1389747
B16: Bata India (BATAINDIA.NS) | C16: India | D16: Ind AS | E16: 829.9563 | F16: 0 | G16: 144.7057 | H16: 54.937 | I16: 370.7565 | J16: 48.3931 | K16: 0 | L16: 54.4195 | M16: 29.0448 | N16: 0.0834 | O16: 0.10557 | P16: =E16+F16+G16-H16 -> 919.725 | Q16: =J16+K16 -> 48.3931 | R16: =P16/Q16 -> 19.005292 | S16: =(E16+F16-H16)/J16 -> 16.015079 | T16: =P16/I16 -> 2.4806713 | U16: =Q16/I16 -> 0.13052529
B18: Summary statistics (peers only; Crocs excluded)
B19: US median | L19: =MEDIAN(L7,L8,L9) -> 14.7287 | M19: =MEDIAN(M7,M8,M9) -> 10.2705 | N19: =MEDIAN(N7,N8,N9) -> 0.0723 | O19: =MEDIAN(O7,O8,O9) -> 0.09854 | R19: =MEDIAN(R7,R8,R9) -> 9.2235517 | T19: =MEDIAN(T7,T8,T9) -> 1.328465
B20: Europe median | L20: =MEDIAN(L10,L11) -> 18.31265 | M20: =MEDIAN(M10,M11) -> 13.0499 | N20: =MEDIAN(N10,N11) -> 0.1632 | O20: =MEDIAN(O10,O11) -> 0.21496 | R20: =MEDIAN(R10,R11) -> 12.213485 | T20: =MEDIAN(T10,T11) -> 2.4446483
B21: UK median | L21: =MEDIAN(L12) -> 35.05 | M21: =MEDIAN(M12) -> 11.5372 | N21: =MEDIAN(N12) -> 0.0487 | O21: =MEDIAN(O12) -> 0.15647 | R21: =MEDIAN(R12) -> 10.316794 | T21: =MEDIAN(T12) -> 1.1559016
B22: India median | L22: =MEDIAN(L13,L14,L15,L16) -> 47.927 | M22: =MEDIAN(M13,M14,M15,M16) -> 29.90325 | N22: =MEDIAN(N13,N14,N15,N16) -> 0.11095 | O22: =MEDIAN(O13,O14,O15,O16) -> 0.101025 | R22: =MEDIAN(R13,R14,R15,R16) -> 22.203552 | T22: =MEDIAN(T13,T14,T15,T16) -> 3.1086469
B23: Developed markets (US + Europe + UK) median | L23: =MEDIAN(L7,L8,L9,L10,L11,L12) -> 18.31265 | M23: =MEDIAN(M7,M8,M9,M10,M11,M12) -> 11.6115 | N23: =MEDIAN(N7,N8,N9,N10,N11,N12) -> 0.0771 | O23: =MEDIAN(O7,O8,O9,O10,O11,O12) -> 0.14626 | R23: =MEDIAN(R7,R8,R9,R10,R11,R12) -> 9.7701727 | T23: =MEDIAN(T7,T8,T9,T10,T11,T12) -> 1.4880063
B24: Developed markets 25th percentile | L24: =_xlfn.PERCENTILE.INC((L7,L8,L9,L10,L11,L12),0.25) -> 15.00655 | M24: =_xlfn.PERCENTILE.INC((M7,M8,M9,M10,M11,M12),0.25) -> 10.587175 | N24: =_xlfn.PERCENTILE.INC((N7,N8,N9,N10,N11,N12),0.25) -> 0.0618 | O24: =_xlfn.PERCENTILE.INC((O7,O8,O9,O10,O11,O12),0.25) -> 0.1089525 | R24: =_xlfn.PERCENTILE.INC((R7,R8,R9,R10,R11,R12),0.25) -> 8.8769353 | T24: =_xlfn.PERCENTILE.INC((T7,T8,T9,T10,T11,T12),0.25) -> 1.1990424
B25: Developed markets 75th percentile | L25: =_xlfn.PERCENTILE.INC((L7,L8,L9,L10,L11,L12),0.75) -> 21.938175 | M25: =_xlfn.PERCENTILE.INC((M7,M8,M9,M10,M11,M12),0.75) -> 13.73195 | N25: =_xlfn.PERCENTILE.INC((N7,N8,N9,N10,N11,N12),0.75) -> 0.123825 | O25: =_xlfn.PERCENTILE.INC((O7,O8,O9,O10,O11,O12),0.75) -> 0.155435 | R25: =_xlfn.PERCENTILE.INC((R7,R8,R9,R10,R11,R12),0.75) -> 10.548384 | T25: =_xlfn.PERCENTILE.INC((T7,T8,T9,T10,T11,T12),0.75) -> 2.2010428
B26: All peers median | L26: =MEDIAN(L7,L8,L9,L10,L11,L12,L13,L14,L15,L16) -> 28.68625 | M26: =MEDIAN(M7,M8,M9,M10,M11,M12,M13,M14,M15,M16) -> 15.24335 | N26: =MEDIAN(N7,N8,N9,N10,N11,N12,N13,N14,N15,N16) -> 0.0887 | O26: =MEDIAN(O7,O8,O9,O10,O11,O12,O13,O14,O15,O16) -> 0.12288 | R26: =MEDIAN(R7,R8,R9,R10,R11,R12,R13,R14,R15,R16) -> 13.145577 | T26: =MEDIAN(T7,T8,T9,T10,T11,T12,T13,T14,T15,T16) -> 2.4331063
B27: Crocs | L27: =L6 -> 10.5191 | M27: =M6 -> 7.9315 | N27: =N6 -> 0.0241 | O27: =O6 -> 0.24221 | R27: =R6 -> 6.9528876 | T27: =T6 -> 1.7676008
B29: Implied value for Crocs (developed-market multiples) | D29: 25th pct | E29: Median | F29: 75th pct
B30: EV/EBITDA (IFRS 16) x Crocs EBITDA pre-rent - bridge incl. leases & UTP | D30: =(R24*Q6-DebtFace-G6+CashJun-UTP*UTPPct)/SharesDil -> 144.05876 | E30: =(R23*Q6-DebtFace-G6+CashJun-UTP*UTPPct)/SharesDil -> 163.10507 | F30: =(R25*Q6-DebtFace-G6+CashJun-UTP*UTPPct)/SharesDil -> 179.6987
B31: Forward P/E x NTM adjusted EPS | D31: =M24*NTM_EPS -> 173.61888 | E31: =M23*NTM_EPS -> 190.41677 | F31: =M25*NTM_EPS -> 225.18999
B33: Cross-sectional regression: forward P/E = a + b1 x growth + b2 x op. margin + b3 x India (10 peers) | D33: Coefficient | E33: Std. error
B34: Intercept | D34: 8.2899 | E34: 3.7446
B35: Next-FY revenue growth | D35: 47.8833 | E35: 30.7258
B36: Operating margin | D36: -4.9908 | E36: 22.4032
B37: India dummy (turns of P/E) | D37: 19.0487 | E37: 2.6922
B38: R-squared / observations | D38: 0.922114 | E38: 10
B39: Crocs fitted forward P/E (India = 0) | D39: =D34+D35*N6+D36*O6 -> 8.2350659
B40: Crocs actual forward P/E | D40: =M6 -> 7.9315

Sheet Precedents
B1: Precedent transactions - footwear & branded apparel
B2: Crocs, Inc. (NASDAQ: CROX) | US$ millions unless stated
B5: Date | C5: Acquirer | D5: Target | E5: Type | F5: EV | G5: Revenue | H5: EBITDA | I5: EV/EBITDA | J5: EV/Revenue | K5: Premium | L5: EBITDA basis | M5: Source
B6: 2025-05-05 | C6: 3G Capital | D6: Skechers | E6: Sponsor take-private | F6: 9400 | G6: 8970 | H6: 1142 | I6: =IF(H6="","",F6/H6) -> 8.2311734 | J6: =F6/G6 -> 1.0479376 | K6: 0.3 | L6: LTM at signing (approx.) | M6: CNBC 5-May-2025; Fashion Dive (Evercore EV est.); Skechers DEFM14C (Greenhill 8.0-11.0x LTM range)
B7: 2025-02-19 | C7: Kontoor Brands | D7: Helly Hansen | E7: Strategic | F7: 900 | G7: 680 | H7: 80 | I7: =IF(H7="","",F7/H7) -> 11.25 | J7: =F7/G7 -> 1.3235294 | L7: FY2025E (forward) | M7: Kontoor 8-K EX-99 19-Feb-2025 (~11x FY25E adj. EBITDA)
B8: 2021-12-23 | C8: Crocs | D8: HEYDUDE | E8: Strategic | F8: 2500 | G8: 570 | H8: 200 | I8: =IF(H8="","",F8/H8) -> 12.5 | J8: =F8/G8 -> 4.3859649 | L8: FY2021E | M8: Crocs 8-K 23-Dec-2021; SGB Online; revenue ~$570m, 'less than 15x' EBITDA
B9: 2020-11-09 | C9: VF Corp | D9: Supreme | E9: Strategic | F9: 2100 | G9: 500 | H9: 141 | I9: =IF(H9="","",F9/H9) -> 14.893617 | J9: =F9/G9 -> 4.2 | L9: FY2021E | M9: VF 8-K EX-99.1 9-Nov-2020 (~15x EBITDA; ~$500m revenue)
B10: 2021-02-26 | C10: L Catterton / Financiere Agache | D10: Birkenstock | E10: Sponsor | F10: 4350 | G10: 795 | I10: =IF(H10="","",F10/H10) | J10: =F10/G10 -> 5.4716981 | L10: n.a. (EBITDA not disclosed) | M10: CNBC 26-Feb-2021 (~EUR4bn EV); FY2020 revenue EUR 728m
B11: 2021-08-12 | C11: Authentic Brands Group | D11: Reebok | E11: Brand management | F11: 2500 | G11: 1670 | I11: =IF(H11="","",F11/H11) | J11: =F11/G11 -> 1.497006 | L11: n.m. (loss-making) | M11: CNBC 12-Aug-2021; Reebok 2020 revenue EUR 1.4bn
B13: Statistics and implied control value for Crocs (x LTM Jun-26 EBITDA)
B14: Crocs LTM Jun-26 EBITDA (before impairments) | I14: 925.437 | J14: Value / share
B15: EV/EBITDA 25th percentile | I15: =_xlfn.PERCENTILE.INC(I6:I11,0.25) -> 10.495293 | J15: =(I15*LTM_EBITDA-DebtFace+CashJun-UTP*UTPPct)/SharesDil -> 163.60386
B16: EV/EBITDA Median | I16: =_xlfn.PERCENTILE.INC(I6:I11,0.5) -> 11.875 | J16: =(I16*LTM_EBITDA-DebtFace+CashJun-UTP*UTPPct)/SharesDil -> 190.01469
B17: EV/EBITDA 75th percentile | I17: =_xlfn.PERCENTILE.INC(I6:I11,0.75) -> 13.098404 | J17: =(I17*LTM_EBITDA-DebtFace+CashJun-UTP*UTPPct)/SharesDil -> 213.43353
B18: Median take-private premium | K18: =MEDIAN(K6:K11) -> 0.3
B19: Precedents are control values: they sit above trading values by the control premium, so they inform the LBO / take-private debate rather than the minority price target.

Sheet LBO
B1: LBO - sponsor take-private (3G / Skechers analogue)
B2: Crocs, Inc. (NASDAQ: CROX) | US$ millions unless stated
B4: Transaction assumptions
B5: Offer premium to current share price | C5: 0.3 | D5: 3G paid a 30% premium for Skechers
B6: Offer price per share (US$) | C6: =SharePrice*(1+LBO_Premium) -> 154.102
B7: Equity purchase price | C7: =LBO_OfferPx*SharesDil -> 7450.0612
B8: Existing debt refinanced (FY26E face) | C8: =Debt!$J$46 -> 1136.1188
B9: Existing cash used (FY26E) | C9: =BS!$J$7 -> 150
B10: Entry enterprise value | C10: =LBO_EqPrice+LBO_RefiDebt-LBO_ExistCash -> 8436.18
B11: FY26E EBITDA | C11: =IS!$J$33 -> 970.03191
B12: Entry EV / EBITDA | C12: =LBO_EV/LBO_EBITDA0 -> 8.6968067
B13: Term Loan B (x EBITDA) | C13: 3.5 | D13: Senior secured
B14: Senior unsecured notes (x EBITDA) | C14: 1.5 | D14: Total 5.0x - typical for a BB branded consumer
B15: Term Loan B margin over SOFR | C15: 0.0325
B16: Notes coupon | C16: 0.08
B17: Term Loan B mandatory amortisation p.a. (% of original) | C17: 0.01
B18: Excess cash sweep to Term Loan B | C18: 1
B19: M&A advisory & other fees (% of EV) | C19: 0.015
B20: Financing fees (% of new debt) | C20: 0.025
B21: Exit EV / EBITDA | C21: =ROUND(LBO_EntryMult,1) -> 8.7 | D21: Default: no multiple expansion
B22: Sources & uses
B23: Sources: Term Loan B | C23: =LBO_TLB_x*LBO_EBITDA0 -> 3395.1117
B24: Sources: senior notes | C24: =LBO_Notes_x*LBO_EBITDA0 -> 1455.0479
B25: Sources: existing cash | C25: =LBO_ExistCash -> 150
B26: Sources: sponsor equity (plug) | C26: =LBO_Uses-LBO_TLB-LBO_Notes-LBO_SrcCash -> 3983.8171
B27: Total sources | C27: =LBO_TLB+LBO_Notes+LBO_SrcCash+LBO_Equity0 -> 8983.9767
B28: Uses: purchase of equity | C28: =LBO_EqPrice -> 7450.0612
B29: Uses: refinance existing debt | C29: =LBO_RefiDebt -> 1136.1188
B30: Uses: advisory and financing fees | C30: =LBO_AdvFee*LBO_EV+LBO_FinFee*(LBO_TLB+LBO_Notes) -> 247.79669
B31: Uses: cash to balance sheet | C31: =MinCash -> 150
B32: Total uses | C32: =LBO_U_Eq+LBO_U_Refi+LBO_U_Fees+LBO_U_Cash -> 8983.9767
B33: Sponsor equity % of total capitalisation | C33: =LBO_Equity0/(LBO_Equity0+LBO_TLB+LBO_Notes) -> 0.45096532
B34: Exit and returns (FY31)
B35: FY31E EBITDA | C35: =IS!$O$33 -> 1240.2902
B36: Exit enterprise value | C36: =LBO_ExitMult*LBO_EBITDA5 -> 10790.525
B37: Net debt at exit | C37: =LBO_CF!$O$18+LBO_CF!$O$21-LBO_CF!$O$23 -> 1422.9635
B38: Exit equity value | C38: =LBO_ExitEV-LBO_ND5 -> 9367.5615
B39: Money-on-money multiple (MOIC) | C39: =LBO_ExitEq/LBO_Equity0 -> 2.3514035
B40: IRR (5 years, no interim distributions) | C40: =LBO_MOIC^(1/5)-1 -> 0.18649369
B41: Value-creation bridge (entry equity -> exit equity)
B42: EBITDA growth at entry multiple | C42: =(LBO_EBITDA5-LBO_EBITDA0)*LBO_EntryMult -> 2350.3844
B43: Multiple expansion / (contraction) | C43: =(LBO_ExitMult-LBO_EntryMult)*LBO_EBITDA5 -> 3.9606771
B44: Debt paydown & cash build (net debt at close less net debt at exit) | C44: =(LBO_TLB+LBO_Notes-MinCash)-LBO_ND5 -> 3277.196
B45: Transaction fees (value lost at entry) | C45: =-LBO_U_Fees -> -247.79669
B46: Check: bridge - (exit equity - entry equity) = 0 | C46: =LBO_VC_EBITDA+LBO_VC_Mult+LBO_VC_Delev+LBO_VC_Fees-(LBO_ExitEq-LBO_Equity0) -> 0
B47: What can a sponsor pay? (price for a target IRR)
B48: Maximum offer price for a 20% IRR (US$) | C48: =((LBO_TLB+LBO_Notes+LBO_SrcCash+LBO_ExitEq/(1+0.2)^5-LBO_RefiDebt-LBO_AdvFee*(LBO_RefiDebt-LBO_ExistCash)-LBO_FinFee*(LBO_TLB+LBO_Notes)-MinCash)/(1+LBO_AdvFee))/SharesDil -> 149.63484
B49: Maximum offer price for a 25% IRR (US$) | C49: =((LBO_TLB+LBO_Notes+LBO_SrcCash+LBO_ExitEq/(1+0.25)^5-LBO_RefiDebt-LBO_AdvFee*(LBO_RefiDebt-LBO_ExistCash)-LBO_FinFee*(LBO_TLB+LBO_Notes)-MinCash)/(1+LBO_AdvFee))/SharesDil -> 135.47043
B51: IRR sensitivity: offer premium (rows) vs exit multiple (columns)
B52: Premium / exit multiple | C52: =LBO_ExitMult-2 -> 6.7 | D52: =LBO_ExitMult-1 -> 7.7 | E52: =LBO_ExitMult+0 -> 8.7 | F52: =LBO_ExitMult+1 -> 9.7 | G52: =LBO_ExitMult+2 -> 10.7
B53: 0.15 | C53: =((C$52*LBO_EBITDA5-LBO_ND5)/((SharePrice*(1+$B53)*SharesDil*(1+LBO_AdvFee)+LBO_RefiDebt+LBO_AdvFee*(LBO_RefiDebt-LBO_ExistCash)+LBO_FinFee*(LBO_TLB+LBO_Notes)+MinCash)-LBO_TLB-LBO_Notes-LBO_SrcCash))^(1/5)-1 -> 0.1722423 | D53: =((D$52*LBO_EBITDA5-LBO_ND5)/((SharePrice*(1+$B53)*SharesDil*(1+LBO_AdvFee)+LBO_RefiDebt+LBO_AdvFee*(LBO_RefiDebt-LBO_ExistCash)+LBO_FinFee*(LBO_TLB+LBO_Notes)+MinCash)-LBO_TLB-LBO_Notes-LBO_SrcCash))^(1/5)-1 -> 0.21171522 | E53: =((E$52*LBO_EBITDA5-LBO_ND5)/((SharePrice*(1+$B53)*SharesDil*(1+LBO_AdvFee)+LBO_RefiDebt+LBO_AdvFee*(LBO_RefiDebt-LBO_ExistCash)+LBO_FinFee*(LBO_TLB+LBO_Notes)+MinCash)-LBO_TLB-LBO_Notes-LBO_SrcCash))^(1/5)-1 -> 0.24662813 | F53: =((F$52*LBO_EBITDA5-LBO_ND5)/((SharePrice*(1+$B53)*SharesDil*(1+LBO_AdvFee)+LBO_RefiDebt+LBO_AdvFee*(LBO_RefiDebt-LBO_ExistCash)+LBO_FinFee*(LBO_TLB+LBO_Notes)+MinCash)-LBO_TLB-LBO_Notes-LBO_SrcCash))^(1/5)-1 -> 0.27801838 | G53: =((G$52*LBO_EBITDA5-LBO_ND5)/((SharePrice*(1+$B53)*SharesDil*(1+LBO_AdvFee)+LBO_RefiDebt+LBO_AdvFee*(LBO_RefiDebt-LBO_ExistCash)+LBO_FinFee*(LBO_TLB+LBO_Notes)+MinCash)-LBO_TLB-LBO_Notes-LBO_SrcCash))^(1/5)-1 -> 0.30659702
B54: 0.2 | C54: =((C$52*LBO_EBITDA5-LBO_ND5)/((SharePrice*(1+$B54)*SharesDil*(1+LBO_AdvFee)+LBO_RefiDebt+LBO_AdvFee*(LBO_RefiDebt-LBO_ExistCash)+LBO_FinFee*(LBO_TLB+LBO_Notes)+MinCash)-LBO_TLB-LBO_Notes-LBO_SrcCash))^(1/5)-1 -> 0.15147725 | D54: =((D$52*LBO_EBITDA5-LBO_ND5)/((SharePrice*(1+$B54)*SharesDil*(1+LBO_AdvFee)+LBO_RefiDebt+LBO_AdvFee*(LBO_RefiDebt-LBO_ExistCash)+LBO_FinFee*(LBO_TLB+LBO_Notes)+MinCash)-LBO_TLB-LBO_Notes-LBO_SrcCash))^(1/5)-1 -> 0.19025094 | E54: =((E$52*LBO_EBITDA5-LBO_ND5)/((SharePrice*(1+$B54)*SharesDil*(1+LBO_AdvFee)+LBO_RefiDebt+LBO_AdvFee*(LBO_RefiDebt-LBO_ExistCash)+LBO_FinFee*(LBO_TLB+LBO_Notes)+MinCash)-LBO_TLB-LBO_Notes-LBO_SrcCash))^(1/5)-1 -> 0.22454541 | F54: =((F$52*LBO_EBITDA5-LBO_ND5)/((SharePrice*(1+$B54)*SharesDil*(1+LBO_AdvFee)+LBO_RefiDebt+LBO_AdvFee*(LBO_RefiDebt-LBO_ExistCash)+LBO_FinFee*(LBO_TLB+LBO_Notes)+MinCash)-LBO_TLB-LBO_Notes-LBO_SrcCash))^(1/5)-1 -> 0.25537961 | G54: =((G$52*LBO_EBITDA5-LBO_ND5)/((SharePrice*(1+$B54)*SharesDil*(1+LBO_AdvFee)+LBO_RefiDebt+LBO_AdvFee*(LBO_RefiDebt-LBO_ExistCash)+LBO_FinFee*(LBO_TLB+LBO_Notes)+MinCash)-LBO_TLB-LBO_Notes-LBO_SrcCash))^(1/5)-1 -> 0.283452
B55: 0.25 | C55: =((C$52*LBO_EBITDA5-LBO_ND5)/((SharePrice*(1+$B55)*SharesDil*(1+LBO_AdvFee)+LBO_RefiDebt+LBO_AdvFee*(LBO_RefiDebt-LBO_ExistCash)+LBO_FinFee*(LBO_TLB+LBO_Notes)+MinCash)-LBO_TLB-LBO_Notes-LBO_SrcCash))^(1/5)-1 -> 0.1327405 | D55: =((D$52*LBO_EBITDA5-LBO_ND5)/((SharePrice*(1+$B55)*SharesDil*(1+LBO_AdvFee)+LBO_RefiDebt+LBO_AdvFee*(LBO_RefiDebt-LBO_ExistCash)+LBO_FinFee*(LBO_TLB+LBO_Notes)+MinCash)-LBO_TLB-LBO_Notes-LBO_SrcCash))^(1/5)-1 -> 0.17088328 | E55: =((E$52*LBO_EBITDA5-LBO_ND5)/((SharePrice*(1+$B55)*SharesDil*(1+LBO_AdvFee)+LBO_RefiDebt+LBO_AdvFee*(LBO_RefiDebt-LBO_ExistCash)+LBO_FinFee*(LBO_TLB+LBO_Notes)+MinCash)-LBO_TLB-LBO_Notes-LBO_SrcCash))^(1/5)-1 -> 0.2046197 | F55: =((F$52*LBO_EBITDA5-LBO_ND5)/((SharePrice*(1+$B55)*SharesDil*(1+LBO_AdvFee)+LBO_RefiDebt+LBO_AdvFee*(LBO_RefiDebt-LBO_ExistCash)+LBO_FinFee*(LBO_TLB+LBO_Notes)+MinCash)-LBO_TLB-LBO_Notes-LBO_SrcCash))^(1/5)-1 -> 0.23495218 | G55: =((G$52*LBO_EBITDA5-LBO_ND5)/((SharePrice*(1+$B55)*SharesDil*(1+LBO_AdvFee)+LBO_RefiDebt+LBO_AdvFee*(LBO_RefiDebt-LBO_ExistCash)+LBO_FinFee*(LBO_TLB+LBO_Notes)+MinCash)-LBO_TLB-LBO_Notes-LBO_SrcCash))^(1/5)-1 -> 0.26256778
B56: 0.3 | C56: =((C$52*LBO_EBITDA5-LBO_ND5)/((SharePrice*(1+$B56)*SharesDil*(1+LBO_AdvFee)+LBO_RefiDebt+LBO_AdvFee*(LBO_RefiDebt-LBO_ExistCash)+LBO_FinFee*(LBO_TLB+LBO_Notes)+MinCash)-LBO_TLB-LBO_Notes-LBO_SrcCash))^(1/5)-1 -> 0.11569606 | D56: =((D$52*LBO_EBITDA5-LBO_ND5)/((SharePrice*(1+$B56)*SharesDil*(1+LBO_AdvFee)+LBO_RefiDebt+LBO_AdvFee*(LBO_RefiDebt-LBO_ExistCash)+LBO_FinFee*(LBO_TLB+LBO_Notes)+MinCash)-LBO_TLB-LBO_Notes-LBO_SrcCash))^(1/5)-1 -> 0.1532649 | E56: =((E$52*LBO_EBITDA5-LBO_ND5)/((SharePrice*(1+$B56)*SharesDil*(1+LBO_AdvFee)+LBO_RefiDebt+LBO_AdvFee*(LBO_RefiDebt-LBO_ExistCash)+LBO_FinFee*(LBO_TLB+LBO_Notes)+MinCash)-LBO_TLB-LBO_Notes-LBO_SrcCash))^(1/5)-1 -> 0.18649369 | F56: =((F$52*LBO_EBITDA5-LBO_ND5)/((SharePrice*(1+$B56)*SharesDil*(1+LBO_AdvFee)+LBO_RefiDebt+LBO_AdvFee*(LBO_RefiDebt-LBO_ExistCash)+LBO_FinFee*(LBO_TLB+LBO_Notes)+MinCash)-LBO_TLB-LBO_Notes-LBO_SrcCash))^(1/5)-1 -> 0.21636975 | G56: =((G$52*LBO_EBITDA5-LBO_ND5)/((SharePrice*(1+$B56)*SharesDil*(1+LBO_AdvFee)+LBO_RefiDebt+LBO_AdvFee*(LBO_RefiDebt-LBO_ExistCash)+LBO_FinFee*(LBO_TLB+LBO_Notes)+MinCash)-LBO_TLB-LBO_Notes-LBO_SrcCash))^(1/5)-1 -> 0.24356981
B57: 0.35 | C57: =((C$52*LBO_EBITDA5-LBO_ND5)/((SharePrice*(1+$B57)*SharesDil*(1+LBO_AdvFee)+LBO_RefiDebt+LBO_AdvFee*(LBO_RefiDebt-LBO_ExistCash)+LBO_FinFee*(LBO_TLB+LBO_Notes)+MinCash)-LBO_TLB-LBO_Notes-LBO_SrcCash))^(1/5)-1 -> 0.10008323 | D57: =((D$52*LBO_EBITDA5-LBO_ND5)/((SharePrice*(1+$B57)*SharesDil*(1+LBO_AdvFee)+LBO_RefiDebt+LBO_AdvFee*(LBO_RefiDebt-LBO_ExistCash)+LBO_FinFee*(LBO_TLB+LBO_Notes)+MinCash)-LBO_TLB-LBO_Notes-LBO_SrcCash))^(1/5)-1 -> 0.13712633 | E57: =((E$52*LBO_EBITDA5-LBO_ND5)/((SharePrice*(1+$B57)*SharesDil*(1+LBO_AdvFee)+LBO_RefiDebt+LBO_AdvFee*(LBO_RefiDebt-LBO_ExistCash)+LBO_FinFee*(LBO_TLB+LBO_Notes)+MinCash)-LBO_TLB-LBO_Notes-LBO_SrcCash))^(1/5)-1 -> 0.16989013 | F57: =((F$52*LBO_EBITDA5-LBO_ND5)/((SharePrice*(1+$B57)*SharesDil*(1+LBO_AdvFee)+LBO_RefiDebt+LBO_AdvFee*(LBO_RefiDebt-LBO_ExistCash)+LBO_FinFee*(LBO_TLB+LBO_Notes)+MinCash)-LBO_TLB-LBO_Notes-LBO_SrcCash))^(1/5)-1 -> 0.1993481 | G57: =((G$52*LBO_EBITDA5-LBO_ND5)/((SharePrice*(1+$B57)*SharesDil*(1+LBO_AdvFee)+LBO_RefiDebt+LBO_AdvFee*(LBO_RefiDebt-LBO_ExistCash)+LBO_FinFee*(LBO_TLB+LBO_Notes)+MinCash)-LBO_TLB-LBO_Notes-LBO_SrcCash))^(1/5)-1 -> 0.22616754
B58: 0.4 | C58: =((C$52*LBO_EBITDA5-LBO_ND5)/((SharePrice*(1+$B58)*SharesDil*(1+LBO_AdvFee)+LBO_RefiDebt+LBO_AdvFee*(LBO_RefiDebt-LBO_ExistCash)+LBO_FinFee*(LBO_TLB+LBO_Notes)+MinCash)-LBO_TLB-LBO_Notes-LBO_SrcCash))^(1/5)-1 -> 0.085695915 | D58: =((D$52*LBO_EBITDA5-LBO_ND5)/((SharePrice*(1+$B58)*SharesDil*(1+LBO_AdvFee)+LBO_RefiDebt+LBO_AdvFee*(LBO_RefiDebt-LBO_ExistCash)+LBO_FinFee*(LBO_TLB+LBO_Notes)+MinCash)-LBO_TLB-LBO_Notes-LBO_SrcCash))^(1/5)-1 -> 0.12225456 | E58: =((E$52*LBO_EBITDA5-LBO_ND5)/((SharePrice*(1+$B58)*SharesDil*(1+LBO_AdvFee)+LBO_RefiDebt+LBO_AdvFee*(LBO_RefiDebt-LBO_ExistCash)+LBO_FinFee*(LBO_TLB+LBO_Notes)+MinCash)-LBO_TLB-LBO_Notes-LBO_SrcCash))^(1/5)-1 -> 0.15458985 | F58: =((F$52*LBO_EBITDA5-LBO_ND5)/((SharePrice*(1+$B58)*SharesDil*(1+LBO_AdvFee)+LBO_RefiDebt+LBO_AdvFee*(LBO_RefiDebt-LBO_ExistCash)+LBO_FinFee*(LBO_TLB+LBO_Notes)+MinCash)-LBO_TLB-LBO_Notes-LBO_SrcCash))^(1/5)-1 -> 0.18366257 | G58: =((G$52*LBO_EBITDA5-LBO_ND5)/((SharePrice*(1+$B58)*SharesDil*(1+LBO_AdvFee)+LBO_RefiDebt+LBO_AdvFee*(LBO_RefiDebt-LBO_ExistCash)+LBO_FinFee*(LBO_TLB+LBO_Notes)+MinCash)-LBO_TLB-LBO_Notes-LBO_SrcCash))^(1/5)-1 -> 0.21013125
